Workbook

Sheet Portada
B5: Sistema de Bibliotecas - Apoyo a la Investigación
B10: Informe de Productividad Científica
B15: 2024 – 2025
B21: Investigadores con afiliación · Universidad Finis Terrae
B23: Información recopilada a partir de SciVal y Scopus
C29: 589 | F29: 396 | I29: 853
C31: Publicaciones únicas | F31: Investigadores | I31: Participaciones (autoría/coautoría)
B45: UNIVERSIDAD FINIS TERRAE
B49: Santiago de Chile · 2026

Sheet Investigadores
A1: Ranking de investigadores · Universidad Finis Terrae · 2024–2025 | AA1: Autor (norm.) | AB1: Año | AC1: Tipo
A2: Publicaciones con afiliación institucional (participaciones autor–publicación). Fuente: SciVal y Scopus. | AA2: Mujika I. | AB2: 2024 | AC2: Article
AA3: Fernández-Verdejo R. | AB3: 2024 | AC3: Review
A4: # | B4: Investigador | C4: 2024 | D4: 2025 | E4: Total | AA4: Tuñón-Suárez M. | AB4: 2024 | AC4: Review
A5: 1 | B5: Orellana-Donoso M. | C5: =COUNTIFS($AA:$AA,$B5,$AB:$AB,2024) -> 16 | D5: =COUNTIFS($AA:$AA,$B5,$AB:$AB,2025) -> 16 | E5: =C5+D5 -> 32 | AA5: Chavez-Reyes A. | AB5: 2024 | AC5: Review
A6: 2 | B6: Yanine F.F. | C6: =COUNTIFS($AA:$AA,$B6,$AB:$AB,2024) -> 13 | D6: =COUNTIFS($AA:$AA,$B6,$AB:$AB,2025) -> 9 | E6: =C6+D6 -> 22 | AA6: Mayo B. | AB6: 2024 | AC6: Review
A7: 3 | B7: Ferre A. | C7: =COUNTIFS($AA:$AA,$B7,$AB:$AB,2024) -> 9 | D7: =COUNTIFS($AA:$AA,$B7,$AB:$AB,2025) -> 12 | E7: =C7+D7 -> 21 | AA7: Penroz S. | AB7: 2024 | AC7: Review
A8: 4 | B8: Mujika I. | C8: =COUNTIFS($AA:$AA,$B8,$AB:$AB,2024) -> 7 | D8: =COUNTIFS($AA:$AA,$B8,$AB:$AB,2025) -> 14 | E8: =C8+D8 -> 21 | AA8: Torres K. | AB8: 2024 | AC8: Review
A9: 5 | B9: Giglio A. | C9: =COUNTIFS($AA:$AA,$B9,$AB:$AB,2024) -> 6 | D9: =COUNTIFS($AA:$AA,$B9,$AB:$AB,2025) -> 13 | E9: =C9+D9 -> 19 | AA9: Simón L. | AB9: 2024 | AC9: Review
A10: 6 | B10: Strauss F.J. | C10: =COUNTIFS($AA:$AA,$B10,$AB:$AB,2024) -> 10 | D10: =COUNTIFS($AA:$AA,$B10,$AB:$AB,2025) -> 6 | E10: =C10+D10 -> 16 | AA10: Fuentealba J.M. | AB10: 2025 | AC10: Review
A11: 7 | B11: Díaz F. | C11: =COUNTIFS($AA:$AA,$B11,$AB:$AB,2024) -> 5 | D11: =COUNTIFS($AA:$AA,$B11,$AB:$AB,2025) -> 10 | E11: =C11+D11 -> 15 | AA11: Hidalgo-Rosa Y. | AB11: 2024 | AC11: Article
A12: 8 | B12: Henríquez-Olguín C. | C12: =COUNTIFS($AA:$AA,$B12,$AB:$AB,2024) -> 6 | D12: =COUNTIFS($AA:$AA,$B12,$AB:$AB,2025) -> 7 | E12: =C12+D12 -> 13 | AA12: Strauss F.J. | AB12: 2024 | AC12: Article
A13: 9 | B13: López-Arana S. | C13: =COUNTIFS($AA:$AA,$B13,$AB:$AB,2024) -> 3 | D13: =COUNTIFS($AA:$AA,$B13,$AB:$AB,2025) -> 10 | E13: =C13+D13 -> 13 | AA13: Yanine F.F. | AB13: 2025 | AC13: Review
A14: 10 | B14: Fernández-Verdejo R. | C14: =COUNTIFS($AA:$AA,$B14,$AB:$AB,2024) -> 9 | D14: =COUNTIFS($AA:$AA,$B14,$AB:$AB,2025) -> 3 | E14: =C14+D14 -> 12 | AA14: Yanine F.F. | AB14: 2024 | AC14: Article
A15: 11 | B15: Mariotti-Celis M.S. | C15: =COUNTIFS($AA:$AA,$B15,$AB:$AB,2024) -> 8 | D15: =COUNTIFS($AA:$AA,$B15,$AB:$AB,2025) -> 4 | E15: =C15+D15 -> 12 | AA15: Fernández-Verdejo R. | AB15: 2024 | AC15: Review
A16: 12 | B16: Cancino-López J. | C16: =COUNTIFS($AA:$AA,$B16,$AB:$AB,2024) -> 4 | D16: =COUNTIFS($AA:$AA,$B16,$AB:$AB,2025) -> 7 | E16: =C16+D16 -> 11 | AA16: Henríquez-Olguín C. | AB16: 2024 | AC16: Article
... A400: 396 | B400: Candell M.B. | C400: =COUNTIFS($AA:$AA,$B400,$AB:$AB,2024) -> 0 | D400: =COUNTIFS($AA:$AA,$B400,$AB:$AB,2025) -> 1 | E400: =C400+D400 -> 1 | AA400: Giglio A. | AB400: 2025 | AC400: Letter
AA401: Ferre A. | AB401: 2025 | AC401: Letter
AA402: Garcia J. | AB402: 2025 | AC402: Letter
AA403: González I. | AB403: 2025 | AC403: Article
AA404: Maldonado-Agurto R. | AB404: 2025 | AC404: Article
AA405: Benites M.H. | AB405: 2025 | AC405: Article
AA406: Saenz A. | AB406: 2025 | AC406: Article
AA407: Dreyse J. | AB407: 2025 | AC407: Article
AA408: Giglio A. | AB408: 2025 | AC408: Article
AA409: Díaz F. | AB409: 2025 | AC409: Article
AA410: Carvajal C. | AB410: 2025 | AC410: Article
AA411: Orellana-Donoso M. | AB411: 2024 | AC411: Review
AA412: Orellana-Donoso M. | AB412: 2024 | AC412: Review
... AA854: Zambrano C. | AB854: 2025 | AC854: Conference Paper

Sheet Resumen y gráficos
A1: Resumen y gráficos · Universidad Finis Terrae · 2024–2025 | AA1: Autor (norm.) | AB1: Año | AC1: Tipo
A2: Fuente: Scopus con afiliación UFT (2024–2025). Ranking y matriz por investigador = participaciones autor-publicación (cada par autor-paper único). Tabla y gráfico 'por tipo' = publicaciones únicas (589, sin duplicar coautorías). Autores agrupados por apellido + inicial. | AA2: Mujika I. | AB2: 2024 | AC2: Article
AA3: Fernández-Verdejo R. | AB3: 2024 | AC3: Review
A4: # | B4: Investigador | C4: 2024 | D4: 2025 | E4: Total | G4: Tipo de publicación | H4: Publ. únicas | AA4: Tuñón-Suárez M. | AB4: 2024 | AC4: Review
A5: 1 | B5: Orellana-Donoso M. | C5: =COUNTIFS($AA:$AA,$B5,$AB:$AB,2024) -> 16 | D5: =COUNTIFS($AA:$AA,$B5,$AB:$AB,2025) -> 16 | E5: =C5+D5 -> 32 | G5: Article | H5: =COUNTIF('Publicaciones unificadas'!$D$2:$D$590,G5) -> 412 | AA5: Chavez-Reyes A. | AB5: 2024 | AC5: Review
A6: 2 | B6: Yanine F.F. | C6: =COUNTIFS($AA:$AA,$B6,$AB:$AB,2024) -> 13 | D6: =COUNTIFS($AA:$AA,$B6,$AB:$AB,2025) -> 9 | E6: =C6+D6 -> 22 | G6: Review | H6: =COUNTIF('Publicaciones unificadas'!$D$2:$D$590,G6) -> 103 | AA6: Mayo B. | AB6: 2024 | AC6: Review
A7: 3 | B7: Ferre A. | C7: =COUNTIFS($AA:$AA,$B7,$AB:$AB,2024) -> 9 | D7: =COUNTIFS($AA:$AA,$B7,$AB:$AB,2025) -> 12 | E7: =C7+D7 -> 21 | G7: Letter | H7: =COUNTIF('Publicaciones unificadas'!$D$2:$D$590,G7) -> 21 | AA7: Penroz S. | AB7: 2024 | AC7: Review
A8: 4 | B8: Mujika I. | C8: =COUNTIFS($AA:$AA,$B8,$AB:$AB,2024) -> 7 | D8: =COUNTIFS($AA:$AA,$B8,$AB:$AB,2025) -> 14 | E8: =C8+D8 -> 21 | G8: Chapter | H8: =COUNTIF('Publicaciones unificadas'!$D$2:$D$590,G8) -> 17 | AA8: Torres K. | AB8: 2024 | AC8: Review
A9: 5 | B9: Giglio A. | C9: =COUNTIFS($AA:$AA,$B9,$AB:$AB,2024) -> 6 | D9: =COUNTIFS($AA:$AA,$B9,$AB:$AB,2025) -> 13 | E9: =C9+D9 -> 19 | G9: Conference Paper | H9: =COUNTIF('Publicaciones unificadas'!$D$2:$D$590,G9) -> 14 | AA9: Simón L. | AB9: 2024 | AC9: Review
A10: 6 | B10: Strauss F.J. | C10: =COUNTIFS($AA:$AA,$B10,$AB:$AB,2024) -> 10 | D10: =COUNTIFS($AA:$AA,$B10,$AB:$AB,2025) -> 6 | E10: =C10+D10 -> 16 | G10: Editorial | H10: =COUNTIF('Publicaciones unificadas'!$D$2:$D$590,G10) -> 7 | AA10: Fuentealba J.M. | AB10: 2025 | AC10: Review
A11: 7 | B11: Díaz F. | C11: =COUNTIFS($AA:$AA,$B11,$AB:$AB,2024) -> 5 | D11: =COUNTIFS($AA:$AA,$B11,$AB:$AB,2025) -> 10 | E11: =C11+D11 -> 15 | G11: Erratum | H11: =COUNTIF('Publicaciones unificadas'!$D$2:$D$590,G11) -> 4 | AA11: Hidalgo-Rosa Y. | AB11: 2024 | AC11: Article
A12: 8 | B12: Henríquez-Olguín C. | C12: =COUNTIFS($AA:$AA,$B12,$AB:$AB,2024) -> 6 | D12: =COUNTIFS($AA:$AA,$B12,$AB:$AB,2025) -> 7 | E12: =C12+D12 -> 13 | G12: Note | H12: =COUNTIF('Publicaciones unificadas'!$D$2:$D$590,G12) -> 6 | AA12: Strauss F.J. | AB12: 2024 | AC12: Article
A13: 9 | B13: López-Arana S. | C13: =COUNTIFS($AA:$AA,$B13,$AB:$AB,2024) -> 3 | D13: =COUNTIFS($AA:$AA,$B13,$AB:$AB,2025) -> 10 | E13: =C13+D13 -> 13 | G13: Short Survey | H13: =COUNTIF('Publicaciones unificadas'!$D$2:$D$590,G13) -> 3 | AA13: Yanine F.F. | AB13: 2025 | AC13: Review
A14: 10 | B14: Fernández-Verdejo R. | C14: =COUNTIFS($AA:$AA,$B14,$AB:$AB,2024) -> 9 | D14: =COUNTIFS($AA:$AA,$B14,$AB:$AB,2025) -> 3 | E14: =C14+D14 -> 12 | G14: Book | H14: =COUNTIF('Publicaciones unificadas'!$D$2:$D$590,G14) -> 1 | AA14: Yanine F.F. | AB14: 2024 | AC14: Article
A15: 11 | B15: Mariotti-Celis M.S. | C15: =COUNTIFS($AA:$AA,$B15,$AB:$AB,2024) -> 8 | D15: =COUNTIFS($AA:$AA,$B15,$AB:$AB,2025) -> 4 | E15: =C15+D15 -> 12 | G15: Total | H15: =SUM(H5:H14) -> 588 | AA15: Fernández-Verdejo R. | AB15: 2024 | AC15: Review
A16: 12 | B16: Cancino-López J. | C16: =COUNTIFS($AA:$AA,$B16,$AB:$AB,2024) -> 4 | D16: =COUNTIFS($AA:$AA,$B16,$AB:$AB,2025) -> 7 | E16: =C16+D16 -> 11 | AA16: Henríquez-Olguín C. | AB16: 2024 | AC16: Article
A17: 13 | B17: Dreyse J. | C17: =COUNTIFS($AA:$AA,$B17,$AB:$AB,2024) -> 6 | D17: =COUNTIFS($AA:$AA,$B17,$AB:$AB,2025) -> 4 | E17: =C17+D17 -> 10 | G17: Investigador | H17: Article | I17: Review | J17: Letter | K17: Chapter | L17: Conf. Paper | M17: Otros | N17: Total | AA17: Salas-Guzmán N. | AB17: 2024 | AC17: Review
A18: 14 | B18: Bustos-Arriagada E. | C18: =COUNTIFS($AA:$AA,$B18,$AB:$AB,2024) -> 4 | D18: =COUNTIFS($AA:$AA,$B18,$AB:$AB,2025) -> 5 | E18: =C18+D18 -> 9 | G18: =B5 -> Orellana-Donoso M. | H18: =COUNTIFS($AA:$AA,$G18,$AC:$AC,"Article") -> 8 | I18: =COUNTIFS($AA:$AA,$G18,$AC:$AC,"Review") -> 23 | J18: =COUNTIFS($AA:$AA,$G18,$AC:$AC,"Letter") -> 0 | K18: =COUNTIFS($AA:$AA,$G18,$AC:$AC,"Chapter") -> 0 | L18: =COUNTIFS($AA:$AA,$G18,$AC:$AC,"Conference Paper") -> 0 | M18: =N18-SUM(H18:L18) -> 1 | N18: =E5 -> 32 | AA18: Yanine F.F. | AB18: 2024 | AC18: Article
A19: 15 | B19: Hidalgo M. | C19: =COUNTIFS($AA:$AA,$B19,$AB:$AB,2024) -> 2 | D19: =COUNTIFS($AA:$AA,$B19,$AB:$AB,2025) -> 7 | E19: =C19+D19 -> 9 | G19: =B6 -> Yanine F.F. | H19: =COUNTIFS($AA:$AA,$G19,$AC:$AC,"Article") -> 10 | I19: =COUNTIFS($AA:$AA,$G19,$AC:$AC,"Review") -> 2 | J19: =COUNTIFS($AA:$AA,$G19,$AC:$AC,"Letter") -> 0 | K19: =COUNTIFS($AA:$AA,$G19,$AC:$AC,"Chapter") -> 8 | L19: =COUNTIFS($AA:$AA,$G19,$AC:$AC,"Conference Paper") -> 2 | M19: =N19-SUM(H19:L19) -> 0 | N19: =E6 -> 22 | AA19: Morales J.-P. | AB19: 2024 | AC19: Short Survey
G20: =B7 -> Ferre A. | H20: =COUNTIFS($AA:$AA,$G20,$AC:$AC,"Article") -> 12 | I20: =COUNTIFS($AA:$AA,$G20,$AC:$AC,"Review") -> 4 | J20: =COUNTIFS($AA:$AA,$G20,$AC:$AC,"Letter") -> 5 | K20: =COUNTIFS($AA:$AA,$G20,$AC:$AC,"Chapter") -> 0 | L20: =COUNTIFS($AA:$AA,$G20,$AC:$AC,"Conference Paper") -> 0 | M20: =N20-SUM(H20:L20) -> 0 | N20: =E7 -> 21 | AA20: De la Fuente M. | AB20: 2025 | AC20: Article
G21: =B8 -> Mujika I. | H21: =COUNTIFS($AA:$AA,$G21,$AC:$AC,"Article") -> 16 | I21: =COUNTIFS($AA:$AA,$G21,$AC:$AC,"Review") -> 1 | J21: =COUNTIFS($AA:$AA,$G21,$AC:$AC,"Letter") -> 0 | K21: =COUNTIFS($AA:$AA,$G21,$AC:$AC,"Chapter") -> 1 | L21: =COUNTIFS($AA:$AA,$G21,$AC:$AC,"Conference Paper") -> 0 | M21: =N21-SUM(H21:L21) -> 3 | N21: =E8 -> 21 | AA21: Benites M.H. | AB21: 2025 | AC21: Review
G22: =B9 -> Giglio A. | H22: =COUNTIFS($AA:$AA,$G22,$AC:$AC,"Article") -> 12 | I22: =COUNTIFS($AA:$AA,$G22,$AC:$AC,"Review") -> 3 | J22: =COUNTIFS($AA:$AA,$G22,$AC:$AC,"Letter") -> 4 | K22: =COUNTIFS($AA:$AA,$G22,$AC:$AC,"Chapter") -> 0 | L22: =COUNTIFS($AA:$AA,$G22,$AC:$AC,"Conference Paper") -> 0 | M22: =N22-SUM(H22:L22) -> 0 | N22: =E9 -> 19 | AA22: Mujika I. | AB22: 2024 | AC22: Article
G23: =B10 -> Strauss F.J. | H23: =COUNTIFS($AA:$AA,$G23,$AC:$AC,"Article") -> 14 | I23: =COUNTIFS($AA:$AA,$G23,$AC:$AC,"Review") -> 2 | J23: =COUNTIFS($AA:$AA,$G23,$AC:$AC,"Letter") -> 0 | K23: =COUNTIFS($AA:$AA,$G23,$AC:$AC,"Chapter") -> 0 | L23: =COUNTIFS($AA:$AA,$G23,$AC:$AC,"Conference Paper") -> 0 | M23: =N23-SUM(H23:L23) -> 0 | N23: =E10 -> 16 | AA23: Ayares G. | AB23: 2025 | AC23: Review
G24: =B11 -> Díaz F. | H24: =COUNTIFS($AA:$AA,$G24,$AC:$AC,"Article") -> 8 | I24: =COUNTIFS($AA:$AA,$G24,$AC:$AC,"Review") -> 0 | J24: =COUNTIFS($AA:$AA,$G24,$AC:$AC,"Letter") -> 5 | K24: =COUNTIFS($AA:$AA,$G24,$AC:$AC,"Chapter") -> 0 | L24: =COUNTIFS($AA:$AA,$G24,$AC:$AC,"Conference Paper") -> 0 | M24: =N24-SUM(H24:L24) -> 2 | N24: =E11 -> 15 | AA24: Mariotti-Celis M.S. | AB24: 2024 | AC24: Article
G25: =B12 -> Henríquez-Olguín C. | H25: =COUNTIFS($AA:$AA,$G25,$AC:$AC,"Article") -> 10 | I25: =COUNTIFS($AA:$AA,$G25,$AC:$AC,"Review") -> 3 | J25: =COUNTIFS($AA:$AA,$G25,$AC:$AC,"Letter") -> 0 | K25: =COUNTIFS($AA:$AA,$G25,$AC:$AC,"Chapter") -> 0 | L25: =COUNTIFS($AA:$AA,$G25,$AC:$AC,"Conference Paper") -> 0 | M25: =N25-SUM(H25:L25) -> 0 | N25: =E12 -> 13 | AA25: Orellana-Donoso M. | AB25: 2024 | AC25: Review
G26: =B13 -> López-Arana S. | H26: =COUNTIFS($AA:$AA,$G26,$AC:$AC,"Article") -> 10 | I26: =COUNTIFS($AA:$AA,$G26,$AC:$AC,"Review") -> 1 | J26: =COUNTIFS($AA:$AA,$G26,$AC:$AC,"Letter") -> 2 | K26: =COUNTIFS($AA:$AA,$G26,$AC:$AC,"Chapter") -> 0 | L26: =COUNTIFS($AA:$AA,$G26,$AC:$AC,"Conference Paper") -> 0 | M26: =N26-SUM(H26:L26) -> 0 | N26: =E13 -> 13 | AA26: Yanine F.F. | AB26: 2024 | AC26: Article
G27: =B14 -> Fernández-Verdejo R. | H27: =COUNTIFS($AA:$AA,$G27,$AC:$AC,"Article") -> 6 | I27: =COUNTIFS($AA:$AA,$G27,$AC:$AC,"Review") -> 3 | J27: =COUNTIFS($AA:$AA,$G27,$AC:$AC,"Letter") -> 1 | K27: =COUNTIFS($AA:$AA,$G27,$AC:$AC,"Chapter") -> 0 | L27: =COUNTIFS($AA:$AA,$G27,$AC:$AC,"Conference Paper") -> 0 | M27: =N27-SUM(H27:L27) -> 2 | N27: =E14 -> 12 | AA27: Santos M. | AB27: 2024 | AC27: Article
G28: =B15 -> Mariotti-Celis M.S. | H28: =COUNTIFS($AA:$AA,$G28,$AC:$AC,"Article") -> 12 | I28: =COUNTIFS($AA:$AA,$G28,$AC:$AC,"Review") -> 0 | J28: =COUNTIFS($AA:$AA,$G28,$AC:$AC,"Letter") -> 0 | K28: =COUNTIFS($AA:$AA,$G28,$AC:$AC,"Chapter") -> 0 | L28: =COUNTIFS($AA:$AA,$G28,$AC:$AC,"Conference Paper") -> 0 | M28: =N28-SUM(H28:L28) -> 0 | N28: =E15 -> 12 | AA28: Henríquez-Olguín C. | AB28: 2025 | AC28: Article
G29: =B16 -> Cancino-López J. | H29: =COUNTIFS($AA:$AA,$G29,$AC:$AC,"Article") -> 6 | I29: =COUNTIFS($AA:$AA,$G29,$AC:$AC,"Review") -> 3 | J29: =COUNTIFS($AA:$AA,$G29,$AC:$AC,"Letter") -> 1 | K29: =COUNTIFS($AA:$AA,$G29,$AC:$AC,"Chapter") -> 0 | L29: =COUNTIFS($AA:$AA,$G29,$AC:$AC,"Conference Paper") -> 0 | M29: =N29-SUM(H29:L29) -> 1 | N29: =E16 -> 11 | AA29: Lucero-Mora J. | AB29: 2024 | AC29: Article
AA30: Yanine F.F. | AB30: 2025 | AC30: Article
AA31: Morales-Guevara R. | AB31: 2024 | AC31: Article
AA32: Mujika I. | AB32: 2025 | AC32: Article
AA33: Díaz-Castro F. | AB33: 2024 | AC33: Article
AA34: Tuñón-Suárez M. | AB34: 2024 | AC34: Article
AA35: Cancino J. | AB35: 2024 | AC35: Article
AA36: Figueroa A.M. | AB36: 2024 | AC36: Article
AA37: Gutiérrez J. | AB37: 2024 | AC37: Article
AA38: Zbinden-Foncea H. | AB38: 2024 | AC38: Article
AA39: Henríquez-Olguín C. | AB39: 2024 | AC39: Article
AA40: Castro-Sepúlveda M. | AB40: 2024 | AC40: Article
AA41: Hartmann Schatloff D. | AB41: 2024 | AC41: Review
... AA854: Zambrano C. | AB854: 2025 | AC854: Conference Paper

Sheet Publicaciones unificadas
A1: # | B1: Título | C1: Año | D1: Tipo | E1: Revista | F1: N° autores UFT | G1: Autores UFT (autoría / coautoría) | H1: DOI | I1: N° autores (total) | J1: % part. UFT
A2: 1 | B2: "Writing from no language": Henri Michaux's signs in motion. | C2: 2025 | D2: Article | E2: Logos: Revista de Linguistica, Filosofia y Literatura | F2: =IF($G2="",0,LEN($G2)-LEN(SUBSTITUTE($G2,"|",""))+1) -> 1 | G2: Kobayashi M.A. | H2: 10.15443/RL3502 | I2: 1 | J2: =IFERROR(F2/I2,"") -> 1
A3: 2 | B3: A New Approach to Evaluating Diversity and Difficulty in Procedurally Generated 2D Platformer Game Levels Through the Relationship Between Structural Metrics and Game Mechanic Constraints in Intelligent Agents | C3: 2025 | D3: Conference Paper | E3: Proceedings - International Conference of the Chilean Computer Science Society, SCCC | F3: =IF($G3="",0,LEN($G3)-LEN(SUBSTITUTE($G3,"|",""))+1) -> 2 | G3: Perez S. | Rojas D. | H3: 10.1109/SCCC67219.2025.11420775 | I3: 2 | J3: =IFERROR(F3/I3,"") -> 1
A4: 3 | B4: A ORDENAÇÃO DOS DESEJOS POR MEIO DA PRÁTICA DAS VIRTUDES E O DESENVOLVIMENTO DO RACIOCÍNIO PRÁTICO: UMA PROPOSTA PARA O FLORESCIMENTO HUMANO BASEADA NO PENSAMENTO DE ALASDAIR MACINTYRE | C4: 2025 | D4: Article | E4: Kriterion (Brazil) | F4: =IF($G4="",0,LEN($G4)-LEN(SUBSTITUTE($G4,"|",""))+1) -> 1 | G4: Rugeles F.L. | H4: 10.1590/0100-512X2025n16202flr | I4: 1 | J4: =IFERROR(F4/I4,"") -> 1
A5: 4 | B5: A Study of Software Architects’ Cognitive Approaches: Kolb’s Learning Styles Inventory in Action | C5: 2025 | D5: Conference Paper | E5: Communications in Computer and Information Science | F5: =IF($G5="",0,LEN($G5)-LEN(SUBSTITUTE($G5,"|",""))+1) -> 1 | G5: Hidalgo M. | H5: 10.1007/978-3-031-75147-9_16 | I5: 3 | J5: =IFERROR(F5/I5,"") -> 0.33333333
A6: 5 | B6: A Sub-Hourly Precipitation Dataset from a Pluviographic Network in Central Chile | C6: 2025 | D6: Article | E6: Data | F6: =IF($G6="",0,LEN($G6)-LEN(SUBSTITUTE($G6,"|",""))+1) -> 1 | G6: Paredes R. | H6: 10.3390/data10070095 | I6: 10 | J6: =IFERROR(F6/I6,"") -> 0.1
A7: 6 | B7: A Systematic Review and Meta-Analysis on the Prevalence of Variants in the Pancreaticobiliary Duct Junction and Its Association with Cancer | C7: 2025 | D7: Review | E7: Biomedicines | F7: =IF($G7="",0,LEN($G7)-LEN(SUBSTITUTE($G7,"|",""))+1) -> 1 | G7: Orellana-Donoso M. | H7: 10.3390/biomedicines13051039 | I7: 13 | J7: =IFERROR(F7/I7,"") -> 0.076923077
A8: 7 | B8: A Systematic Review of Anatomical Variations of the Inferior Thyroid Artery: Clinical and Surgical Considerations | C8: 2025 | D8: Review | E8: Diagnostics | F8: =IF($G8="",0,LEN($G8)-LEN(SUBSTITUTE($G8,"|",""))+1) -> 1 | G8: Orellana-Donoso M. | H8: 10.3390/diagnostics15151858 | I8: 12 | J8: =IFERROR(F8/I8,"") -> 0.083333333
A9: 8 | B9: A Systematic Review with a Meta-Analysis of the Morphological Variants of the Corpus Callosum: Related Neurocognitive Clinical Implications | C9: 2025 | D9: Review | E9: World Neurosurgery | F9: =IF($G9="",0,LEN($G9)-LEN(SUBSTITUTE($G9,"|",""))+1) -> 1 | G9: Orellana-Donoso M. | H9: 10.1016/j.wneu.2025.124317 | I9: 14 | J9: =IFERROR(F9/I9,"") -> 0.071428571
A10: 9 | B10: A comprehensive review of smart energy management systems for photovoltaic power generation utilizing the internet of things | C10: 2025 | D10: Review | E10: Unconventional Resources | F10: =IF($G10="",0,LEN($G10)-LEN(SUBSTITUTE($G10,"|",""))+1) -> 1 | G10: Yanine F.F. | H10: 10.1016/j.uncres.2025.100197 | I10: 3 | J10: =IFERROR(F10/I10,"") -> 0.33333333
A11: 10 | B11: A gender-integrated biopsychosocial model to understand cardiovascular risk in women working under environmental hazards: the case of chronic intermittent hypoxia | C11: 2025 | D11: Short Survey | E11: Frontiers in Public Health | F11: =IF($G11="",0,LEN($G11)-LEN(SUBSTITUTE($G11,"|",""))+1) -> 1 | G11: Lang M. | H11: 10.3389/fpubh.2025.1672503 | I11: 4 | J11: =IFERROR(F11/I11,"") -> 0.25
A12: 11 | B12: A map of collective pedagogical content knowledge as a basis for studying the development of biology teachers’ personal PCK of evolution | C12: 2025 | D12: Article | E12: International Journal of Science Education | F12: =IF($G12="",0,LEN($G12)-LEN(SUBSTITUTE($G12,"|",""))+1) -> 1 | G12: Santibáñez D. | H12: 10.1080/09500693.2024.2381841 | I12: 7 | J12: =IFERROR(F12/I12,"") -> 0.14285714
A13: 12 | B13: A review of IoT-based smart energy solutions for photovoltaic systems | C13: 2025 | D13: Article | E13: Electrical Engineering | F13: =IF($G13="",0,LEN($G13)-LEN(SUBSTITUTE($G13,"|",""))+1) -> 1 | G13: Yanine F.F. | H13: 10.1007/s00202-025-03312-3 | I13: 3 | J13: =IFERROR(F13/I13,"") -> 0.33333333
... A131: 130 | B131: INSTRUMENTS FOR MEASURING ANXIETY IN DENTAL STUDENTS: A BIBLIOMETRIC ANALYSIS | C131: 2025 | D131: Article | E131: Journal of Oral Research | F131: =IF($G131="",0,LEN($G131)-LEN(SUBSTITUTE($G131,"|",""))+1) -> 4 | G131: Zamorano S. | Caro J.C. | Ponce N. | Moya P. | H131: 10.17126/joralres.2025.020 | I131: 4 | J131: =IFERROR(F131/I131,"") -> 1
A132: 131 | B132: Immediate loading of definitive restorations in partially edentulous patients requiring an implant-supported prosthesis: A scoping review | C132: 2025 | D132: Review | E132: Journal of Prosthetic Dentistry | F132: 1 | G132: Strauss F.J. | H132: 10.1016/j.prosdent.2024.04.013 | I132: 7 | J132: =IFERROR(F132/I132,"") -> 0.14285714
A133: 132 | B133: Immunomodulation and Immunotherapy for Patients with Prostate Cancer: An Up-to-Date Review | C133: 2025 | D133: Review | E133: Biomedicines | F133: =IF($G133="",0,LEN($G133)-LEN(SUBSTITUTE($G133,"|",""))+1) -> 1 | G133: Murray N.P. | H133: 10.3390/biomedicines13051179 | I133: 1 | J133: =IFERROR(F133/I133,"") -> 1
A134: 133 | B134: Immunotherapy-Related Pancreatitis: A Case Series of 8 Patients from a High-Volume Oncology Centre | C134: 2025 | D134: Article | E134: Case Reports in Oncology | F134: =IF($G134="",0,LEN($G134)-LEN(SUBSTITUTE($G134,"|",""))+1) -> 1 | G134: San Martín T. | H134: 10.1159/000548016 | I134: 5 | J134: =IFERROR(F134/I134,"") -> 0.2
A135: 134 | B135: Impact of Teleworking on Work-Related and Home-Related Stress at During the First Global Lockdown–The International COVISTRESS Study | C135: 2025 | D135: Article | E135: Brain and Behavior | F135: =IF($G135="",0,LEN($G135)-LEN(SUBSTITUTE($G135,"|",""))+1) -> 1 | G135: Avilès Dorlhiac R. | H135: 10.1002/brb3.70592 | I135: 18 | J135: =IFERROR(F135/I135,"") -> 0.055555556
A136: 135 | B136: Impact of strength-based video-feedback intervention on maternal sensitivity in mother–infant dyads with maternal depressive symptoms | C136: 2025 | D136: Article | E136: Infant Mental Health Journal | F136: =IF($G136="",0,LEN($G136)-LEN(SUBSTITUTE($G136,"|",""))+1) -> 1 | G136: Muzard A. | H136: 10.1002/imhj.22154 | I136: 8 | J136: =IFERROR(F136/I136,"") -> 0.125
A137: 136 | B137: In situ simulation in the intensive care unit: A phenomenological study of staff experiences | C137: 2025 | D137: Article | E137: Perfusion (United Kingdom) | F137: =IF($G137="",0,LEN($G137)-LEN(SUBSTITUTE($G137,"|",""))+1) -> 6 | G137: Ferre A. | Giglio A. | Van Sint Jan N. | Benites M.H. | Dreyse J. | Hasbun P. | H137: 10.1177/02676591241272058 | I137: 9 | J137: =IFERROR(F137/I137,"") -> 0.66666667
A138: 137 | B138: In vivo experimental study comparing alveolar ridge preservation versus guided bone regeneration after unassisted socket healing at intact and damaged sites in narrow alveolar ridges | C138: 2025 | D138: Article | E138: Journal of Periodontology | F138: =IF($G138="",0,LEN($G138)-LEN(SUBSTITUTE($G138,"|",""))+1) -> 1 | G138: Strauss F.J. | H138: 10.1002/JPER.24-0125 | I138: 6 | J138: =IFERROR(F138/I138,"") -> 0.16666667
A139: 138 | B139: Inclusion of ΑVβ3 integrin into extracellular vesicles in a caveolin-1 tyrosine-14- phosphorylation dependent manner and subsequent transfer to recipient melanoma cells promotes migration, invasion and metastasis | C139: 2025 | D139: Article | E139: System.Xml.XmlElement | F139: =IF($G139="",0,LEN($G139)-LEN(SUBSTITUTE($G139,"|",""))+1) -> 1 | G139: Simón L. | H139: 10.1186/s12964-025-02131-0 | I139: 11 | J139: =IFERROR(F139/I139,"") -> 0.090909091
A140: 139 | B140: Infectious morbidity and white blood cell count associated with grade repetition and school absenteeism | C140: 2025 | D140: Article | E140: Acta Paediatrica, International Journal of Paediatrics | F140: =IF($G140="",0,LEN($G140)-LEN(SUBSTITUTE($G140,"|",""))+1) -> 1 | G140: López-Arana S. | H140: 10.1111/apa.17513 | I140: 6 | J140: =IFERROR(F140/I140,"") -> 0.16666667
A141: 140 | B141: Influence of Iodine Substitutions on the Photophysical Properties of Rhenium(I) Tricarbonyl Complexes With Pyridine Schiff Base (PSB-IHB) | C141: 2025 | D141: Article | E141: International Journal of Quantum Chemistry | F141: =IF($G141="",0,LEN($G141)-LEN(SUBSTITUTE($G141,"|",""))+1) -> 1 | G141: Morales-Guevara R. | H141: 10.1002/qua.70005 | I141: 4 | J141: =IFERROR(F141/I141,"") -> 0.25
A142: 141 | B142: Inhibition of the formation of 2-amino-1-methyl-6-phenylimidazo[4,5-b]pyridine (PhIP) and 2-amino-3,8-dimethyl-3H-imidazo[4,5-f]quinoxaline (MeIQx) by phenolics in model systems and beef patties | C142: 2025 | D142: Article | E142: Food Chemistry | F142: =IF($G142="",0,LEN($G142)-LEN(SUBSTITUTE($G142,"|",""))+1) -> 1 | G142: Mariotti-Cellis M.S. | H142: 10.1016/j.foodchem.2025.144091 | I142: 6 | J142: =IFERROR(F142/I142,"") -> 0.16666667
A143: 142 | B143: Integral training for food sustainability: a pending subject in Latin America | C143: 2025 | D143: Article | E143: Revista Chilena de Nutricion | F143: =IF($G143="",0,LEN($G143)-LEN(SUBSTITUTE($G143,"|",""))+1) -> 1 | G143: López-Arana S. | H143: 10.64159/RCHNUT-52-5-10 | I143: 3 | J143: =IFERROR(F143/I143,"") -> 0.33333333
A144: 143 | B144: Integrated strategies for reducing acrylamide, 5-HMF, and furan in colored native and commercial potato chips: Synergistic effects of nutrient solution conductivity and pre-frying treatments | C144: 2025 | D144: Article | E144: LWT | F144: =IF($G144="",0,LEN($G144)-LEN(SUBSTITUTE($G144,"|",""))+1) -> 1 | G144: Mariotti-Celis M.S. | H144: 10.1016/j.lwt.2025.118398 | I144: 7 | J144: =IFERROR(F144/I144,"") -> 0.14285714
... A234: 233 | B234: Severe middle childhood acne treated with isotretinoin | C234: 2025 | D234: Article | E234: Piel | F234: =IF($G234="",0,LEN($G234)-LEN(SUBSTITUTE($G234,"|",""))+1) -> 1 | G234: Hartmann D. | H234: 10.1016/j.piel.2024.04.006 | I234: 6 | J234: =IFERROR(F234/I234,"") -> 0.16666667
A235: 234 | B235: Severe obesity and menopause symptoms are associated with cognitive impairment in postmenopausal women from Latin America | C235: 2025 | D235: Article | E235: Climacteric | F235: 1 | G235: Aedo S. | H235: 10.1080/13697137.2025.2491637 | I235: 18 | J235: =IFERROR(F235/I235,"") -> 0.055555556
A236: 235 | B236: Sexual Dimorphism in the Atlas Vertebra of Normal and Overweight Patients with its Possible Surgical Implications | C236: 2025 | D236: Article | E236: World Neurosurgery | F236: =IF($G236="",0,LEN($G236)-LEN(SUBSTITUTE($G236,"|",""))+1) -> 1 | G236: Orellana-Donoso M. | H236: 10.1016/j.wneu.2025.124531 | I236: 11 | J236: =IFERROR(F236/I236,"") -> 0.090909091
A237: 236 | B237: Should we move beyond the concept of fluid responsiveness? | C237: 2025 | D237: Letter | E237: Intensive Care Medicine | F237: =IF($G237="",0,LEN($G237)-LEN(SUBSTITUTE($G237,"|",""))+1) -> 4 | G237: Giglio Jimenez A. | Tovar W. | Pedreros C. | Ferre A. | H237: 10.1007/s00134-025-07787-3 | I237: 4 | J237: =IFERROR(F237/I237,"") -> 1
A238: 237 | B238: Skeletal muscle Rac1 mediates exercise training adaptations towards muscle glycogen resynthesis and protein synthesis | C238: 2025 | D238: Article | E238: Redox Biology | F238: =IF($G238="",0,LEN($G238)-LEN(SUBSTITUTE($G238,"|",""))+1) -> 1 | G238: Henríquez-Olguín C. | H238: 10.1016/j.redox.2025.103844 | I238: 21 | J238: =IFERROR(F238/I238,"") -> 0.047619048
A239: 238 | B239: Sleep Restriction and Weekend Sleep Compensation Relate to Eating Behavior in School-Aged Children | C239: 2025 | D239: Article | E239: Nature and Science of Sleep | F239: =IF($G239="",0,LEN($G239)-LEN(SUBSTITUTE($G239,"|",""))+1) -> 1 | G239: Gutierrez M. | H239: 10.2147/NSS.S509636 | I239: 5 | J239: =IFERROR(F239/I239,"") -> 0.2
A240: 239 | B240: Snapshot of a Decade: Idiopathic Inflammatory Myopathies in Chile - A 10-Year Short Report | C240: 2025 | D240: Article | E240: Journal of Clinical Rheumatology | F240: =IF($G240="",0,LEN($G240)-LEN(SUBSTITUTE($G240,"|",""))+1) -> 1 | G240: Giglio A. | H240: 10.1097/RHU.0000000000002230 | I240: 5 | J240: =IFERROR(F240/I240,"") -> 0.2
A241: 240 | B241: Social Media and Plastic Surgery, the Good, the Bad, and Where are We Going? | C241: 2025 | D241: Review | E241: Aesthetic Plastic Surgery | F241: =IF($G241="",0,LEN($G241)-LEN(SUBSTITUTE($G241,"|",""))+1) -> 6 | G241: Maldonado J D. | Arriagada I C. | Conejero R A. | Covarrubias C P. | Doña V J. | Hurtado D M.J. | H241: 10.1007/s00266-025-04748-5 | I241: 6 | J241: =IFERROR(F241/I241,"") -> 1
A242: 241 | B242: Social and health factors affecting work-related accidents among older informal workers in Chile: A probit model analysis based on CASEN 2022 | C242: 2025 | D242: Article | E242: Social Sciences and Humanities Open | F242: =IF($G242="",0,LEN($G242)-LEN(SUBSTITUTE($G242,"|",""))+1) -> 1 | G242: Arenas-Massa A. | H242: 10.1016/j.ssaho.2025.102231 | I242: 2 | J242: =IFERROR(F242/I242,"") -> 0.5
A243: 242 | B243: Soft-tissue volume augmentation during early, delayed, and late dental implant therapy: A systematic review and meta-analysis on professionally determined esthetics and self-reported patient satisfaction on esthetics | C243: 2025 | D243: Review | E243: Periodontology 2000 | F243: =IF($G243="",0,LEN($G243)-LEN(SUBSTITUTE($G243,"|",""))+1) -> 1 | G243: Strauss F.J. | H243: 10.1111/prd.12628 | I243: 6 | J243: =IFERROR(F243/I243,"") -> 0.16666667
A244: 243 | B244: Some Considerations on the Psychological Experience of Time in Friendship According to Thomas Aquinas | C244: 2025 | D244: Article | E244: Scripta Mediaevalia | F244: =IF($G244="",0,LEN($G244)-LEN(SUBSTITUTE($G244,"|",""))+1) -> 1 | G244: Muszalski H. | H244: 10.48162/rev.35.048 | I244: 1 | J244: =IFERROR(F244/I244,"") -> 1
A245: 244 | B245: Submaximal Accentuated Eccentric Jump Training Improves Punching Performance and Countermovement Jump Force–Time Variables in Amateur Boxers | C245: 2025 | D245: Article | E245: Applied Sciences (Switzerland) | F245: =IF($G245="",0,LEN($G245)-LEN(SUBSTITUTE($G245,"|",""))+1) -> 1 | G245: Cancino-López J. | H245: 10.3390/app15147873 | I245: 11 | J245: =IFERROR(F245/I245,"") -> 0.090909091
A246: 245 | B246: Subtalar joint revision arthrodesis due to non-union: a case report | C246: 2025 | D246: Article | E246: Revista Medica Clinica Las Condes | F246: =IF($G246="",0,LEN($G246)-LEN(SUBSTITUTE($G246,"|",""))+1) -> 5 | G246: Verschae G. | Val V. | Alba V. | Pavez S. | Cid N. | H246: 10.1016/j.rmclc.2025.01.002 | I246: 6 | J246: =IFERROR(F246/I246,"") -> 0.83333333
A247: 246 | B247: Sudden Cardiac Death: Trend Analysis by Sex and Age, Chile 2010 to 2020 | C247: 2025 | D247: Article | E247: Revista Medica de Chile | F247: =IF($G247="",0,LEN($G247)-LEN(SUBSTITUTE($G247,"|",""))+1) -> 1 | G247: Valderrama P. | H247: 10.4067/s0034-98872025001100760 | I247: 6 | J247: =IFERROR(F247/I247,"") -> 0.16666667
... A350: 349 | B350: Association of Peri-Implant Mucosa Dimensions With Emergence Profile Angles of the Implant Prosthesis | C350: 2024 | D350: Article | E350: Clinical and Experimental Dental Research | F350: =IF($G350="",0,LEN($G350)-LEN(SUBSTITUTE($G350,"|",""))+1) -> 1 | G350: Strauss F.J. | H350: 10.1002/cre2.939 | I350: 6 | J350: =IFERROR(F350/I350,"") -> 0.16666667
A351: 350 | B351: Association of muscle disorders in late postmenopausal women according to the type of experienced menopause | C351: 2024 | D351: Article | E351: Menopause | F351: 1 | G351: Aedo S. | H351: 10.1097/GME.0000000000002367 | I351: 18 | J351: =IFERROR(F351/I351,"") -> 0.055555556
A352: 351 | B352: Attitudes of early childhood educators to deal with emotional crisis situations of children with autism | C352: 2024 | D352: Article | E352: European Public and Social Innovation Review | F352: =IF($G352="",0,LEN($G352)-LEN(SUBSTITUTE($G352,"|",""))+1) -> 1 | G352: Aqueveque-Muñoz C. | H352: 10.31637/epsir-2024-719 | I352: 1 | J352: =IFERROR(F352/I352,"") -> 1
A353: 352 | B353: Augmentation of keratinized tissue using autogenous soft-tissue grafts and collagen-based soft-tissue substitutes at teeth and dental implants: Histological findings in a pilot pre-clinical study | C353: 2024 | D353: Article | E353: Journal of Clinical Periodontology | F353: =IF($G353="",0,LEN($G353)-LEN(SUBSTITUTE($G353,"|",""))+1) -> 1 | G353: Strauss F.J. | H353: 10.1111/jcpe.13949 | I353: 6 | J353: =IFERROR(F353/I353,"") -> 0.16666667
A354: 353 | B354: Author Correction: Neurocognitive correlates of semantic memory navigation in Parkinson’s disease (npj Parkinson's Disease, (2024), 10, 1, (15), 10.1038/s41531-024-00630-4) | C354: 2024 | D354: Erratum | E354: npj Parkinson's Disease | F354: =IF($G354="",0,LEN($G354)-LEN(SUBSTITUTE($G354,"|",""))+1) -> 1 | G354: Rojas-Costa G.M. | H354: 10.1038/s41531-024-00644-y | I354: 15 | J354: =IFERROR(F354/I354,"") -> 0.066666667
A355: 354 | B355: BMAL1 and CLOCK proteins exhibit differential association with mitochondrial dynamics, protein synthesis pathways and muscle strength in human muscle | C355: 2024 | D355: Article | E355: Journal of Physiology | F355: =IF($G355="",0,LEN($G355)-LEN(SUBSTITUTE($G355,"|",""))+1) -> 6 | G355: Figueroa-Toledo A.M. | Gutiérrez-Pino J. | Carriel-Nesvara A. | Marchese-Bittencourt M. | Zbinden-Foncea H. | Castro-Sepúlveda M. | H355: 10.1113/JP285955 | I355: 6 | J355: =IFERROR(F355/I355,"") -> 1
A356: 355 | B356: Biceps femoris long head stiffens after 2 weeks of training cessation in highly trained sprinters | C356: 2024 | D356: Article | E356: European Journal of Applied Physiology | F356: =IF($G356="",0,LEN($G356)-LEN(SUBSTITUTE($G356,"|",""))+1) -> 1 | G356: Mujika I. | H356: 10.1007/s00421-024-05536-w | I356: 6 | J356: =IFERROR(F356/I356,"") -> 0.16666667
A357: 356 | B357: Biomarkers of minimal residual disease and treatment | C357: 2024 | D357: Chapter | E357: Advances in Clinical Chemistry | F357: =IF($G357="",0,LEN($G357)-LEN(SUBSTITUTE($G357,"|",""))+1) -> 1 | G357: Murray N.P. | H357: 10.1016/bs.acc.2024.02.002 | I357: 1 | J357: =IFERROR(F357/I357,"") -> 1
A358: 357 | B358: Bodily events in metaphorical embodiment of stress relief | C358: 2024 | D358: Article | E358: Current Psychology | F358: =IF($G358="",0,LEN($G358)-LEN(SUBSTITUTE($G358,"|",""))+1) -> 1 | G358: Farsani D. | H358: 10.1007/s12144-024-06884-8 | I358: 5 | J358: =IFERROR(F358/I358,"") -> 0.2
A359: 358 | B359: CHILEAN PATIENTS BELONGING TO VULNERABLE GROUPS: A LOOK FROM THE RULINGS OF THE INTER-AMERICAN COURT* | C359: 2024 | D359: Article | E359: Iberoamerica (Russian Federation) | F359: =IF($G359="",0,LEN($G359)-LEN(SUBSTITUTE($G359,"|",""))+1) -> 1 | G359: Massa A.A. | H359: 10.37656/s20768400-2024-1-06 | I359: 4 | J359: =IFERROR(F359/I359,"") -> 0.25
A360: 359 | B360: COPD management in the modern era | C360: 2024 | D360: Article | E360: Revista Medica Clinica Las Condes | F360: =IF($G360="",0,LEN($G360)-LEN(SUBSTITUTE($G360,"|",""))+1) -> 1 | G360: Dreyse J. | H360: 10.1016/j.rmclc.2024.05.002 | I360: 1 | J360: =IFERROR(F360/I360,"") -> 1
A361: 360 | B361: Can beliefs improve mental health? A dive into resilience during pandemic times in South America | C361: 2024 | D361: Article | E361: Social Sciences and Humanities Open | F361: =IF($G361="",0,LEN($G361)-LEN(SUBSTITUTE($G361,"|",""))+1) -> 1 | G361: Morales J.-P. | H361: 10.1016/j.ssaho.2024.100883 | I361: 6 | J361: =IFERROR(F361/I361,"") -> 0.16666667
A362: 361 | B362: Cardiologic Involvement in an Experimental Model of Reperfused Ischemic Stroke | C362: 2024 | D362: Letter | E362: Revista Argentina de Cardiologia | F362: =IF($G362="",0,LEN($G362)-LEN(SUBSTITUTE($G362,"|",""))+1) -> 1 | G362: Verdugo F.J. | H362: 10.7775/rac.es.v92.i4.20810 | I362: 4 | J362: =IFERROR(F362/I362,"") -> 0.25
A363: 362 | B363: Care: Following the Micropolitics of Pathologization and Depathologization of Children in Chilean Schools | C363: 2024 | D363: Chapter | E363: Pathologisation, Depathologisation and Mental Health: Keys for a Contemporary Discussion from Ibero-America | F363: =IF($G363="",0,LEN($G363)-LEN(SUBSTITUTE($G363,"|",""))+1) -> 1 | G363: Tabilo-Prieto I. | H363: 10.1007/978-3-031-70043-9_6 | I363: 3 | J363: =IFERROR(F363/I363,"") -> 0.33333333
... A375: 374 | B375: Closed-shell d10-d10 mechanochromic [AuPh(CNPh)]n complex: quantum chemistry electronic and optical properties | C375: 2024 | D375: Article | E375: RSC Advances | F375: =IF($G375="",0,LEN($G375)-LEN(SUBSTITUTE($G375,"|",""))+1) -> 1 | G375: Ceron M.L. | H375: 10.1039/d3ra08935e | I375: 4 | J375: =IFERROR(F375/I375,"") -> 0.25
A376: 375 | B376: Cognitive, emotional, and social factors promoting psychosocial adaptation: a study of latent profiles in people living in socially vulnerable contexts | C376: 2024 | D376: Article | E376: Frontiers in Psychology | F376: =IF($G376="",0,LEN($G376)-LEN(SUBSTITUTE($G376,"|",""))+1) -> 0 | H376: 10.3389/fpsyg.2024.1321242 | I376: 10 | J376: =IFERROR(F376/I376,"") -> 0
A377: 376 | B377: Cold-induced shivering for metabolic health: Energy homeostasis | C377: 2024 | D377: Note | E377: Nature Metabolism | F377: =IF($G377="",0,LEN($G377)-LEN(SUBSTITUTE($G377,"|",""))+1) -> 1 | G377: Fernández-Verdejo R. | H377: 10.1038/s42255-024-01147-z | I377: 2 | J377: =IFERROR(F377/I377,"") -> 0.5
A378: 377 | B378: Colorectal cancer screening: emerging non-invasive tests | C378: 2024 | D378: Article | E378: Revista Medica Clinica Las Condes | F378: =IF($G378="",0,LEN($G378)-LEN(SUBSTITUTE($G378,"|",""))+1) -> 1 | G378: Zárate A. | H378: 10.1016/j.rmclc.2024.03.006 | I378: 5 | J378: =IFERROR(F378/I378,"") -> 0.2
A379: 378 | B379: Coma Prevalence in Critical Care Units in Chile: Results of a Cross-Sectional Survey on World Coma Day | C379: 2024 | D379: Article | E379: Neurocritical Care | F379: =IF($G379="",0,LEN($G379)-LEN(SUBSTITUTE($G379,"|",""))+1) -> 5 | G379: Giglio A. | Reccius A. | Carvajal C. | Pedreros C. | Ferre A. | H379: 10.1007/s12028-024-01986-4 | I379: 10 | J379: =IFERROR(F379/I379,"") -> 0.5
A380: 379 | B380: Comparative Analysis of Sustainable Extraction Methods and Green Solvents for Olive Leaf Extracts with Antioxidant and Antihyperglycemic Activities | C380: 2024 | D380: Article | E380: Antioxidants | F380: =IF($G380="",0,LEN($G380)-LEN(SUBSTITUTE($G380,"|",""))+1) -> 1 | G380: Mariotti-Celis M.S. | H380: 10.3390/antiox13121523 | I380: 6 | J380: =IFERROR(F380/I380,"") -> 0.16666667
A381: 380 | B381: Concurrent ankle-assisted movement, biofeedback, and proprioceptive stimulation reduces lower limb motor impairment and improves gait in persons with stroke | C381: 2024 | D381: Article | E381: Physiotherapy Theory and Practice | F381: =IF($G381="",0,LEN($G381)-LEN(SUBSTITUTE($G381,"|",""))+1) -> 1 | G381: Varas-Diaz G. | H381: 10.1080/09593985.2022.2122763 | I381: 6 | J381: =IFERROR(F381/I381,"") -> 0.16666667
A382: 381 | B382: Consumers at risk: Analysis of the influence of the use of algorithms on the supplier's benefit | C382: 2024 | D382: Article | E382: Revista Chilena de Derecho y Tecnologia | F382: =IF($G382="",0,LEN($G382)-LEN(SUBSTITUTE($G382,"|",""))+1) -> 1 | G382: Martínez-Cárdenas B. | H382: 10.5354/0719-2584.2024.70418 | I382: 2 | J382: =IFERROR(F382/I382,"") -> 0.5
A383: 382 | B383: Correction to: Obesity and brain structure in schizophrenia – ENIGMA study in 3021 individuals (Molecular Psychiatry, (2022), 27, 9, (3731-3737), 10.1038/s41380-022-01616-5) | C383: 2024 | D383: Erratum | E383: Molecular Psychiatry | F383: =IF($G383="",0,LEN($G383)-LEN(SUBSTITUTE($G383,"|",""))+1) -> 1 | G383: Gonzalez-Valderrama A. | H383: 10.1038/s41380-023-02055-6 | I383: 43 | J383: =IFERROR(F383/I383,"") -> 0.023255814
A384: 383 | B384: Corrigendum: The role of cholesterol and mitochondrial bioenergetics in activation of the inflammasome in IBD (Front. Immunol., (2022), 13, 1028953, 10.3389/fimmu.2022.1028953) | C384: 2024 | D384: Erratum | E384: Frontiers in Immunology | F384: =IF($G384="",0,LEN($G384)-LEN(SUBSTITUTE($G384,"|",""))+1) -> 2 | G384: De la Fuente M. | Landskron G. | H384: 10.3389/fimmu.2024.1384162 | I384: 8 | J384: =IFERROR(F384/I384,"") -> 0.25
A385: 384 | B385: Creatine Supplementation Prior to Strength Exercise Training Is Not Superior in Preventing Muscle Mass Loss Compared with Standard Nutritional Recommendations in Females After Bariatric Surgery: A Pilot Study | C385: 2024 | D385: Article | E385: Obesity Surgery | F385: =IF($G385="",0,LEN($G385)-LEN(SUBSTITUTE($G385,"|",""))+1) -> 3 | G385: Diaz-Pizarro M. | Pino-Zúñiga J. | Cancino-López J. | H385: 10.1007/s11695-024-07451-7 | I385: 7 | J385: =IFERROR(F385/I385,"") -> 0.42857143
A386: 385 | B386: Criteria for Designating a Health Care Facility as a Teaching Institution: An Analysis of International Regulations and Practices | C386: 2024 | D386: Article | E386: Revista Medica de Chile | F386: =IF($G386="",0,LEN($G386)-LEN(SUBSTITUTE($G386,"|",""))+1) -> 2 | G386: Cortina A.H. | Soto-Suazo M. | H386: 10.4067/s0034-98872024000300382 | I386: 3 | J386: =IFERROR(F386/I386,"") -> 0.66666667
A387: 386 | B387: Curcumin Administration Routes in Breast Cancer Treatment | C387: 2024 | D387: Review | E387: International Journal of Molecular Sciences | F387: =IF($G387="",0,LEN($G387)-LEN(SUBSTITUTE($G387,"|",""))+1) -> 4 | G387: Mayo B. | Penroz S. | Torres K. | Simón L. | H387: 10.3390/ijms252111492 | I387: 4 | J387: =IFERROR(F387/I387,"") -> 1
A388: 387 | B388: Current liver failure support systems: Biding time for transplantation | C388: 2024 | D388: Review | E388: Revista Medica Clinica Las Condes | F388: =IF($G388="",0,LEN($G388)-LEN(SUBSTITUTE($G388,"|",""))+1) -> 3 | G388: Nazal L. | Valenzuela R. | Ferre A. | H388: 10.1016/j.rmclc.2023.12.002 | I388: 3 | J388: =IFERROR(F388/I388,"") -> 1
... A398: 397 | B398: Developing a Guided Web App for Postpartum Depression Symptoms: User-Centered Design Approach | C398: 2024 | D398: Article | E398: JMIR Formative Research | F398: =IF($G398="",0,LEN($G398)-LEN(SUBSTITUTE($G398,"|",""))+1) -> 1 | G398: Muzard A. | H398: 10.2196/56319 | I398: 5 | J398: =IFERROR(F398/I398,"") -> 0.2
A399: 398 | B399: Development of a 31P magnetic resonance spectroscopy technique to quantify NADH and NAD+ at 3 T | C399: 2024 | D399: Article | E399: System.Xml.XmlElement | F399: 1 | G399: Mancilla R. | H399: 10.1038/s41467-024-53292-4 | I399: 14 | J399: =IFERROR(F399/I399,"") -> 0.071428571
A400: 399 | B400: Development of gestural language in childhood: how is it addressed in the guidelines proposed in documents that control kindergarten education in Chile? | C400: 2024 | D400: Article | E400: Estudios Pedagogicos | F400: =IF($G400="",0,LEN($G400)-LEN(SUBSTITUTE($G400,"|",""))+1) -> 1 | G400: Díaz-Galaz L. | H400: 10.4067/S0718-07052024000100323 | I400: 1 | J400: =IFERROR(F400/I400,"") -> 1
A401: 400 | B401: Diagnosing grid's service quality issues: the virtual microgrid and the digitization and innovations in the power distribution grid | C401: 2024 | D401: Conference Paper | E401: Procedia Computer Science | F401: =IF($G401="",0,LEN($G401)-LEN(SUBSTITUTE($G401,"|",""))+1) -> 1 | G401: Yanine F.F. | H401: 10.1016/j.procs.2024.08.134 | I401: 5 | J401: =IFERROR(F401/I401,"") -> 0.2
A402: 401 | B402: Differential Extraction and Preliminary Identification of Polyphenols from Ugni candollei (White Murta) Berries | C402: 2024 | D402: Article | E402: Antioxidants | F402: =IF($G402="",0,LEN($G402)-LEN(SUBSTITUTE($G402,"|",""))+1) -> 1 | G402: Mariotti-Celis M.S. | H402: 10.3390/antiox13060623 | I402: 5 | J402: =IFERROR(F402/I402,"") -> 0.2
A403: 402 | B403: Distributed embodiment of the Persian term dæqi:qæn in forward gestures | C403: 2024 | D403: Review | E403: Journal of Cultural Cognitive Science | F403: =IF($G403="",0,LEN($G403)-LEN(SUBSTITUTE($G403,"|",""))+1) -> 1 | G403: Farsani D. | H403: 10.1007/s41809-023-00136-0 | I403: 6 | J403: =IFERROR(F403/I403,"") -> 0.16666667
A404: 403 | B404: Dystopian imaginaries and ecosocial imaginaries: artistic practices at the beginning of the pandemic in Chile and Spain. | C404: 2024 | D404: Article | E404: Arte, Individuo y Sociedad | F404: =IF($G404="",0,LEN($G404)-LEN(SUBSTITUTE($G404,"|",""))+1) -> 1 | G404: Villalobos P. | H404: 10.5209/aris.93263 | I404: 1 | J404: =IFERROR(F404/I404,"") -> 1
A405: 404 | B405: EDUCATION FOR ALL FROM THE EARLY YEARS: INCLUSIVE EXPERIENCE IN CHILE | C405: 2024 | D405: Chapter | E405: International Perspectives on Inclusive Education | F405: =IF($G405="",0,LEN($G405)-LEN(SUBSTITUTE($G405,"|",""))+1) -> 2 | G405: de la Cruz P.S. | López Y.M. | H405: 10.1108/S1479-363620240000024004 | I405: 3 | J405: =IFERROR(F405/I405,"") -> 0.66666667
A406: 405 | B406: EV Battery Charging System | C406: 2024 | D406: Chapter | E406: Electric Vehicle Design: Design, Simulation and Applications | F406: =IF($G406="",0,LEN($G406)-LEN(SUBSTITUTE($G406,"|",""))+1) -> 0 | H406: - | I406: 4 | J406: =IFERROR(F406/I406,"") -> 0
A407: 406 | B407: Early Development of the Thalamo-Pallial Stage of the Tectofugal Visual Pathway in the Chicken (Gallus gallus) | C407: 2024 | D407: Article | E407: Journal of Comparative Neurology | F407: =IF($G407="",0,LEN($G407)-LEN(SUBSTITUTE($G407,"|",""))+1) -> 1 | G407: Marín G.J. | H407: 10.1002/cne.25657 | I407: 5 | J407: =IFERROR(F407/I407,"") -> 0.2
A408: 407 | B408: Early Exercise Through Telerehabilitation After Bariatric Surgery: Is It Feasible? | C408: 2024 | D408: Article | E408: Obesity Surgery | F408: =IF($G408="",0,LEN($G408)-LEN(SUBSTITUTE($G408,"|",""))+1) -> 3 | G408: Pino-Zúñiga J. | Olivares M. | Cancino-López J. | H408: 10.1007/s11695-024-07185-6 | I408: 6 | J408: =IFERROR(F408/I408,"") -> 0.5
A409: 408 | B409: Early implant placement versus ridge preservation and delayed implant placement: Analysis of profilometric, clinician- and patient-reported outcomes from a two-centre RCT | C409: 2024 | D409: Article | E409: Clinical Oral Implants Research | F409: =IF($G409="",0,LEN($G409)-LEN(SUBSTITUTE($G409,"|",""))+1) -> 1 | G409: Strauss F.J. | H409: 10.1111/clr.14325 | I409: 8 | J409: =IFERROR(F409/I409,"") -> 0.125
A410: 409 | B410: Eco-Innovation in the Food Industry: Exploring Consumer Motivations in an Emerging Market | C410: 2024 | D410: Article | E410: Foods | F410: =IF($G410="",0,LEN($G410)-LEN(SUBSTITUTE($G410,"|",""))+1) -> 7 | G410: Mansilla-Obando K. | Llanos G. | Gómez-Sotta E. | Buchuk P. | Ortiz F. | Aguirre M. | Ahumada F. | H410: 10.3390/foods13010004 | I410: 7 | J410: =IFERROR(F410/I410,"") -> 1
A411: 410 | B411: Effect of In Vitro Micropropagation on the Chemical, Antioxidant, and Biological Characteristics of Senecio nutans Sch. Bip., an Endemic Plant of the Atacama Desert Andean Region | C411: 2024 | D411: Article | E411: Plants | F411: =IF($G411="",0,LEN($G411)-LEN(SUBSTITUTE($G411,"|",""))+1) -> 2 | G411: Contreras-Contreras G. | Mariotti-Celis M.S. | H411: 10.3390/plants13060755 | I411: 9 | J411: =IFERROR(F411/I411,"") -> 0.22222222
A412: 411 | B412: Effect of epicatechin consumption on the inflammatory pathway and mitochondria morphology in PBMC from a R350P desminopathy patient: A case report | C412: 2024 | D412: Article | E412: Physiological Reports | F412: =IF($G412="",0,LEN($G412)-LEN(SUBSTITUTE($G412,"|",""))+1) -> 3 | G412: Tapia-Curimil G. | Castro-Sepúlveda M. | Zbinden-Foncea H. | H412: 10.14814/phy2.16020 | I412: 3 | J412: =IFERROR(F412/I412,"") -> 1
A413: 412 | B413: Effectiveness of DASH Diet versus Other Diet Modalities in Patients with Metabolic Syndrome: A Systematic Review and Meta-Analysis | C413: 2024 | D413: Review | E413: System.Xml.XmlElement | F413: =IF($G413="",0,LEN($G413)-LEN(SUBSTITUTE($G413,"|",""))+1) -> 1 | G413: Orellana-Donoso M. | H413: 10.3390/nu16183054 | I413: 11 | J413: =IFERROR(F413/I413,"") -> 0.090909091
A414: 413 | B414: Effectiveness of Duloxetine versus Other Therapeutic Modalities in Patients with Diabetic Neuropathic Pain: A Systematic Review and Meta-Analysis | C414: 2024 | D414: Review | E414: Pharmaceuticals | F414: =IF($G414="",0,LEN($G414)-LEN(SUBSTITUTE($G414,"|",""))+1) -> 1 | G414: Orellana-Donoso M. | H414: 10.3390/ph17070856 | I414: 10 | J414: =IFERROR(F414/I414,"") -> 0.1
A415: 414 | B415: Effects of exercise, physical activity, and sports on physical fitness in adults with Down syndrome: A systematic review | C415: 2024 | D415: Review | E415: AIMS Public Health | F415: =IF($G415="",0,LEN($G415)-LEN(SUBSTITUTE($G415,"|",""))+1) -> 1 | G415: Montalva-Valenzuela F. | H415: 10.3934/publichealth.2024029 | I415: 6 | J415: =IFERROR(F415/I415,"") -> 0.16666667
A416: 415 | B416: Effects of school closure on lifestyle behaviours and health outcomes in children during the COVID-19 pandemic in Chile: A time-matched analysis | C416: 2024 | D416: Article | E416: Pediatric Obesity | F416: =IF($G416="",0,LEN($G416)-LEN(SUBSTITUTE($G416,"|",""))+1) -> 1 | G416: Fernández-Verdejo R. | H416: 10.1111/ijpo.13182 | I416: 5 | J416: =IFERROR(F416/I416,"") -> 0.2
A417: 416 | B417: Efficacy of hemoadsorptive therapy combined with high-volume hemofiltration in the management of refractory septic shock | C417: 2024 | D417: Article | E417: Revista Medica Clinica Las Condes | F417: =IF($G417="",0,LEN($G417)-LEN(SUBSTITUTE($G417,"|",""))+1) -> 6 | G417: Kemeny R. | Giglio A. | Ramos A. | Arroyo A. | Pedreros C. | Ferre A. | H417: 10.1016/j.rmclc.2023.10.003 | I417: 9 | J417: =IFERROR(F417/I417,"") -> 0.66666667
A418: 417 | B418: Embodiment and gestural realization of ergative verbs | C418: 2024 | D418: Article | E418: Psychological Research | F418: =IF($G418="",0,LEN($G418)-LEN(SUBSTITUTE($G418,"|",""))+1) -> 1 | G418: Farsani D. | H418: 10.1007/s00426-023-01887-9 | I418: 7 | J418: =IFERROR(F418/I418,"") -> 0.14285714
... A426: 425 | B426: Estimating Muscle Fiber-Type Composition in Elite Athletes: A Survey on Current Practices and Perceived Merit | C426: 2024 | D426: Article | E426: International Journal of Sports Physiology and Performance | F426: =IF($G426="",0,LEN($G426)-LEN(SUBSTITUTE($G426,"|",""))+1) -> 1 | G426: Mujika I. | H426: 10.1123/ijspp.2024-0043 | I426: 12 | J426: =IFERROR(F426/I426,"") -> 0.083333333
A427: 426 | B427: Estimation of ventilatory thresholds during exercise using respiratory wearable sensors | C427: 2024 | D427: Article | E427: npj Digital Medicine | F427: 1 | G427: Cancino J. | H427: 10.1038/s41746-024-01191-9 | I427: 6 | J427: =IFERROR(F427/I427,"") -> 0.16666667
A428: 427 | B428: Evaluation of the Effect of the Technical Guidelines for Chilean Milk Dietary Service on the Microbiological and Nutritional Quality of a Powdered Infant Formula | C428: 2024 | D428: Article | E428: Applied Sciences (Switzerland) | F428: =IF($G428="",0,LEN($G428)-LEN(SUBSTITUTE($G428,"|",""))+1) -> 2 | G428: Bustos-Arriagada E. | Mariotti-Celis M.S. | H428: 10.3390/app14209556 | I428: 3 | J428: =IFERROR(F428/I428,"") -> 0.66666667
A429: 428 | B429: Evolving demographics: a dynamic clustering approach to analyze residential segregation in Berlin | C429: 2024 | D429: Article | E429: EPJ Data Science | F429: =IF($G429="",0,LEN($G429)-LEN(SUBSTITUTE($G429,"|",""))+1) -> 1 | G429: Valle M.A. | H429: 10.1140/epjds/s13688-024-00455-4 | I429: 7 | J429: =IFERROR(F429/I429,"") -> 0.14285714
A430: 429 | B430: Exploring NADPH oxidases 2 and 4 in cardiac and skeletal muscle adaptations – A cross-tissue comparison | C430: 2024 | D430: Review | E430: Free Radical Biology and Medicine | F430: =IF($G430="",0,LEN($G430)-LEN(SUBSTITUTE($G430,"|",""))+1) -> 1 | G430: Henríquez-Olguín C. | H430: 10.1016/j.freeradbiomed.2024.07.035 | I430: 4 | J430: =IFERROR(F430/I430,"") -> 0.25
A431: 430 | B431: Exploring a Sustainable Process for Polyphenol Extraction from Olive Leaves | C431: 2024 | D431: Article | E431: Foods | F431: =IF($G431="",0,LEN($G431)-LEN(SUBSTITUTE($G431,"|",""))+1) -> 1 | G431: Mariotti-Celis M.S. | H431: 10.3390/foods13020265 | I431: 8 | J431: =IFERROR(F431/I431,"") -> 0.125
A432: 431 | B432: Exploring the adsorption of five emerging pollutants on activated carbon: A theoretical approach | C432: 2024 | D432: Article | E432: Journal of Environmental Chemical Engineering | F432: =IF($G432="",0,LEN($G432)-LEN(SUBSTITUTE($G432,"|",""))+1) -> 1 | G432: Hidalgo-Rosa Y. | H432: 10.1016/j.jece.2024.112911 | I432: 6 | J432: =IFERROR(F432/I432,"") -> 0.16666667
A433: 432 | B433: Exploring the lutein therapeutic potential in steatotic liver disease: mechanistic insights and future directions | C433: 2024 | D433: Review | E433: Frontiers in Pharmacology | F433: =IF($G433="",0,LEN($G433)-LEN(SUBSTITUTE($G433,"|",""))+1) -> 4 | G433: Balboa E. | Saud F. | De la Fuente M. | Landskron G. | H433: 10.3389/fphar.2024.1406784 | I433: 6 | J433: =IFERROR(F433/I433,"") -> 0.66666667
A434: 433 | B434: Extranei intervention in special crimes and Nagler's secondary duty as a basis for punishing participants | C434: 2024 | D434: Article | E434: Politica Criminal | F434: =IF($G434="",0,LEN($G434)-LEN(SUBSTITUTE($G434,"|",""))+1) -> 1 | G434: López A.L. | H434: - | I434: 1 | J434: =IFERROR(F434/I434,"") -> 1
A435: 434 | B435: Factors associated with prolonged mechanical ventilation in children with pulmonary failure: Cohort study from the LARed Network registry | C435: 2024 | D435: Article | E435: Medicina Intensiva | F435: =IF($G435="",0,LEN($G435)-LEN(SUBSTITUTE($G435,"|",""))+1) -> 1 | G435: Díaz F. | H435: 10.1016/j.medin.2023.06.005 | I435: 12 | J435: =IFERROR(F435/I435,"") -> 0.083333333
...

Sheet Informe Cienciométrico (2)
A1: Informe Cienciométrico — Producción Científica UFT
A2: Base de datos: hoja «Publicaciones unificadas» · Período 2024–2025 · Análisis bibliométrico de producción, fuentes, autoría y colaboración
A4: Publicaciones totales | D4: Publicaciones 2025 | G4: Publicaciones 2024 | J4: Fuentes / revistas distintas
A5: =COUNTA(PublicacionesUnicas[Título]) -> 589 | D5: =COUNTIF(PublicacionesUnicas[Año],2025) -> 317 | G5: =COUNTIF(PublicacionesUnicas[Año],2024) -> 271 | J5: {=SUMPRODUCT((PublicacionesUnicas[Revista]<>"")/COUNTIF(PublicacionesUnicas[Revista],PublicacionesUnicas[Revista]&""))} -> 368
A7: % participación UFT (promedio) | D7: Autores por publicación (prom.) | G7: Autores UFT por publicación (prom.) | J7: Investigadores UFT distintos (aprox.)
A8: =AVERAGE(PublicacionesUnicas[% part. UFT]) -> 0.38686157 | D8: =AVERAGE(PublicacionesUnicas[N° autores (total)]) -> 6.8095238 | G8: =AVERAGE(PublicacionesUnicas[N° autores UFT]) -> 1.4601019 | J8: 397
A11: 1. Producción anual
A12: Año | B12: Publicaciones | C12: % del total
A13: 2024 | B13: =COUNTIF(PublicacionesUnicas[Año],2024) -> 271 | C13: =B13/$B$15 -> 0.46088435
A14: 2025 | B14: =COUNTIF(PublicacionesUnicas[Año],2025) -> 317 | C14: =B14/$B$15 -> 0.53911565
A15: Total | B15: =SUM(B13:B14) -> 588 | C15: =B15/$B$15 -> 1
A28: 2. Tipología documental
A29: Tipo de documento | B29: Publicaciones | C29: % del total
A30: Article | B30: =COUNTIF(PublicacionesUnicas[Tipo],A30) -> 412 | C30: =B30/$B$40 -> 0.70068027
A31: Review | B31: =COUNTIF(PublicacionesUnicas[Tipo],A31) -> 103 | C31: =B31/$B$40 -> 0.17517007
A32: Letter | B32: =COUNTIF(PublicacionesUnicas[Tipo],A32) -> 21 | C32: =B32/$B$40 -> 0.035714286
A33: Conference Paper | B33: =COUNTIF(PublicacionesUnicas[Tipo],A33) -> 14 | C33: =B33/$B$40 -> 0.023809524
A34: Note | B34: =COUNTIF(PublicacionesUnicas[Tipo],A34) -> 6 | C34: =B34/$B$40 -> 0.010204082
A35: Editorial | B35: =COUNTIF(PublicacionesUnicas[Tipo],A35) -> 7 | C35: =B35/$B$40 -> 0.011904762
A36: Chapter | B36: =COUNTIF(PublicacionesUnicas[Tipo],A36) -> 17 | C36: =B36/$B$40 -> 0.028911565
A37: Short Survey | B37: =COUNTIF(PublicacionesUnicas[Tipo],A37) -> 3 | C37: =B37/$B$40 -> 0.0051020408
A38: Erratum | B38: =COUNTIF(PublicacionesUnicas[Tipo],A38) -> 4 | C38: =B38/$B$40 -> 0.0068027211
A39: Book | B39: =COUNTIF(PublicacionesUnicas[Tipo],A39) -> 1 | C39: =B39/$B$40 -> 0.0017006803
A40: Total | B40: =SUM(B30:B39) -> 588 | C40: =B40/$B$40 -> 1
A48: 3. Fuentes más productivas (Top 15 revistas)
A49: Revista | B49: Publicaciones
A50: Revista Medica Clinica Las Condes | B50: =COUNTIF(PublicacionesUnicas[Revista],A50) -> 35
A51: Diagnostics | B51: =COUNTIF(PublicacionesUnicas[Revista],A51) -> 10
A52: Revista Chilena de Nutricion | B52: =COUNTIF(PublicacionesUnicas[Revista],A52) -> 10
A53: International Journal of Sports Physiology and Performance | B53: =COUNTIF(PublicacionesUnicas[Revista],A53) -> 10
A54: Antioxidants | B54: =COUNTIF(PublicacionesUnicas[Revista],A54) -> 9
A55: Andes Pediatrica | B55: =COUNTIF(PublicacionesUnicas[Revista],A55) -> 8
A56: International Journal of Molecular Sciences | B56: =COUNTIF(PublicacionesUnicas[Revista],A56) -> 7
A57: Journal of Clinical Medicine | B57: =COUNTIF(PublicacionesUnicas[Revista],A57) -> 7
A58: Piel | B58: =COUNTIF(PublicacionesUnicas[Revista],A58) -> 6
A59: Obesity Surgery | B59: =COUNTIF(PublicacionesUnicas[Revista],A59) -> 5
A60: Critical Care | B60: =COUNTIF(PublicacionesUnicas[Revista],A60) -> 5
A61: Scientific Reports | B61: =COUNTIF(PublicacionesUnicas[Revista],A61) -> 5
... A64: Frontiers in Psychology | B64: =COUNTIF(PublicacionesUnicas[Revista],A64) -> 4
A72: 4. Investigadores UFT más productivos (Top 15)
A73: Investigador/a UFT | B73: Publicaciones | C73: Buscar en Scopus
A74: Orellana-Donoso M. | B74: =COUNTIF(PublicacionesUnicas[Autores UFT (autoría / coautoría)],"*"&A74&"*") -> 32 | C74: 🔍 Buscar autor
A75: Yanine F.F. | B75: =COUNTIF(PublicacionesUnicas[Autores UFT (autoría / coautoría)],"*"&A75&"*") -> 22 | C75: 🔍 Buscar autor
A76: Ferre A. | B76: =COUNTIF(PublicacionesUnicas[Autores UFT (autoría / coautoría)],"*"&A76&"*") -> 21 | C76: 🔍 Buscar autor
A77: Mujika I. | B77: =COUNTIF(PublicacionesUnicas[Autores UFT (autoría / coautoría)],"*"&A77&"*") -> 21 | C77: 🔍 Buscar autor
A78: Giglio A. | B78: =COUNTIF(PublicacionesUnicas[Autores UFT (autoría / coautoría)],"*"&A78&"*") -> 19 | C78: 🔍 Buscar autor
A79: Strauss F.J. | B79: =COUNTIF(PublicacionesUnicas[Autores UFT (autoría / coautoría)],"*"&A79&"*") -> 17 | C79: 🔍 Buscar autor
A80: Díaz F. | B80: =COUNTIF(PublicacionesUnicas[Autores UFT (autoría / coautoría)],"*"&A80&"*") -> 15 | C80: 🔍 Buscar autor
A81: Henríquez-Olguín C. | B81: =COUNTIF(PublicacionesUnicas[Autores UFT (autoría / coautoría)],"*"&A81&"*") -> 13 | C81: 🔍 Buscar autor
A82: López-Arana S. | B82: =COUNTIF(PublicacionesUnicas[Autores UFT (autoría / coautoría)],"*"&A82&"*") -> 13 | C82: 🔍 Buscar autor
A83: Mariotti-Celis M.S. | B83: =COUNTIF(PublicacionesUnicas[Autores UFT (autoría / coautoría)],"*"&A83&"*") -> 12 | C83: 🔍 Buscar autor
A84: Fernández-Verdejo R. | B84: =COUNTIF(PublicacionesUnicas[Autores UFT (autoría / coautoría)],"*"&A84&"*") -> 12 | C84: 🔍 Buscar autor
A85: Cancino-López J. | B85: =COUNTIF(PublicacionesUnicas[Autores UFT (autoría / coautoría)],"*"&A85&"*") -> 11 | C85: 🔍 Buscar autor
... A88: Bustos-Arriagada E. | B88: =COUNTIF(PublicacionesUnicas[Autores UFT (autoría / coautoría)],"*"&A88&"*") -> 9 | C88: 🔍 Buscar autor
A96: 5. Colaboración interna (n° de autores UFT por publicación)
A97: N° autores UFT | B97: Publicaciones | C97: % del total
A98: 1 autor | B98: =COUNTIF(PublicacionesUnicas[N° autores UFT],1) -> 451 | C98: =B98/SUM($B$98:$B$103) -> 0.76831346
A99: 2 autores | B99: =COUNTIF(PublicacionesUnicas[N° autores UFT],2) -> 68 | C99: =B99/SUM($B$98:$B$103) -> 0.11584327
A100: 3 autores | B100: =COUNTIF(PublicacionesUnicas[N° autores UFT],3) -> 31 | C100: =B100/SUM($B$98:$B$103) -> 0.052810903
A101: 4 autores | B101: =COUNTIF(PublicacionesUnicas[N° autores UFT],4) -> 21 | C101: =B101/SUM($B$98:$B$103) -> 0.035775128
A102: 5 autores | B102: =COUNTIF(PublicacionesUnicas[N° autores UFT],5) -> 4 | C102: =B102/SUM($B$98:$B$103) -> 0.0068143101
A103: 6 o más | B103: =COUNTIF(PublicacionesUnicas[N° autores UFT],">=6") -> 12 | C103: =B103/SUM($B$98:$B$103) -> 0.02044293
A114: 6. Intensidad de participación UFT (% de autores UFT sobre el total)
A115: Rango de participación | B115: Publicaciones | C115: % del total
A116: 100% (autoría íntegra UFT) | B116: =COUNTIF(PublicacionesUnicas[% part. UFT],1) -> 93 | C116: =B116/SUM($B$116:$B$120) -> 0.15870307
A117: 50% – 99% | B117: =COUNTIFS(PublicacionesUnicas[% part. UFT],">="&0.5,PublicacionesUnicas[% part. UFT],"<"&1) -> 100 | C117: =B117/SUM($B$116:$B$120) -> 0.17064846
A118: 25% – 49% | B118: =COUNTIFS(PublicacionesUnicas[% part. UFT],">="&0.25,PublicacionesUnicas[% part. UFT],"<"&0.5) -> 144 | C118: =B118/SUM($B$116:$B$120) -> 0.24573379
A119: 10% – 24% | B119: =COUNTIFS(PublicacionesUnicas[% part. UFT],">="&0.1,PublicacionesUnicas[% part. UFT],"<"&0.25) -> 169 | C119: =B119/SUM($B$116:$B$120) -> 0.2883959
A120: < 10% | B120: =COUNTIFS(PublicacionesUnicas[% part. UFT],">"&0,PublicacionesUnicas[% part. UFT],"<"&0.1) -> 80 | C120: =B120/SUM($B$116:$B$120) -> 0.13651877
A132: Nota metodológica y fuentes
A133: • Fuente de datos: hoja «Publicaciones unificadas» (tabla PublicacionesUnicas). Todas las cifras se calculan con fórmulas vinculadas a dicha tabla y se actualizan automáticamente.
A134: • Universo: 589 publicaciones únicas de 2024–2025. El conteo de investigadores UFT distintos (≈397) se deriva del análisis de la columna «Autores UFT (autoría / coautoría)» separando los nombres por «|».
A135: • «Fuentes distintas» incluye ~20 registros cuya revista no fue resuelta en el origen (aparecen como «System.Xml.XmlElement»); estos no afectan los rankings de revistas mostrados.
A136: • % participación UFT = n° de autores UFT / n° total de autores de cada publicación. Colaboración interna = n° de autores UFT firmantes por publicación.
A138: ANÁLISIS COMPLEMENTARIOS
A140: 7. Tipología documental por año
A141: Tipo de documento | B141: 2024 | C141: 2025
A142: Article | B142: =COUNTIFS(PublicacionesUnicas[Tipo],$A142,PublicacionesUnicas[Año],B$141) -> 197 | C142: =COUNTIFS(PublicacionesUnicas[Tipo],$A142,PublicacionesUnicas[Año],C$141) -> 215
A143: Review | B143: =COUNTIFS(PublicacionesUnicas[Tipo],$A143,PublicacionesUnicas[Año],B$141) -> 39 | C143: =COUNTIFS(PublicacionesUnicas[Tipo],$A143,PublicacionesUnicas[Año],C$141) -> 64
A144: Letter | B144: =COUNTIFS(PublicacionesUnicas[Tipo],$A144,PublicacionesUnicas[Año],B$141) -> 9 | C144: =COUNTIFS(PublicacionesUnicas[Tipo],$A144,PublicacionesUnicas[Año],C$141) -> 12
A145: Chapter | B145: =COUNTIFS(PublicacionesUnicas[Tipo],$A145,PublicacionesUnicas[Año],B$141) -> 14 | C145: =COUNTIFS(PublicacionesUnicas[Tipo],$A145,PublicacionesUnicas[Año],C$141) -> 3
A146: Conference Paper | B146: =COUNTIFS(PublicacionesUnicas[Tipo],$A146,PublicacionesUnicas[Año],B$141) -> 4 | C146: =COUNTIFS(PublicacionesUnicas[Tipo],$A146,PublicacionesUnicas[Año],C$141) -> 10
A147: Editorial | B147: =COUNTIFS(PublicacionesUnicas[Tipo],$A147,PublicacionesUnicas[Año],B$141) -> 1 | C147: =COUNTIFS(PublicacionesUnicas[Tipo],$A147,PublicacionesUnicas[Año],C$141) -> 6
A160: 8. Tamaño de los equipos de investigación (n° total de autores)
A161: N° total de autores | B161: Publicaciones | C161: % del total
A162: 1 (individual) | B162: =COUNTIF(PublicacionesUnicas[N° autores (total)],1) -> 49 | C162: =B162/SUM($B$162:$B$167) -> 0.083333333
A163: 2 – 3 | B163: =COUNTIFS(PublicacionesUnicas[N° autores (total)],">="&2,PublicacionesUnicas[N° autores (total)],"<="&3) -> 162 | C163: =B163/SUM($B$162:$B$167) -> 0.2755102
A164: 4 – 6 | B164: =COUNTIFS(PublicacionesUnicas[N° autores (total)],">="&4,PublicacionesUnicas[N° autores (total)],"<="&6) -> 180 | C164: =B164/SUM($B$162:$B$167) -> 0.30612245
A165: 7 – 10 | B165: =COUNTIFS(PublicacionesUnicas[N° autores (total)],">="&7,PublicacionesUnicas[N° autores (total)],"<="&10) -> 105 | C165: =B165/SUM($B$162:$B$167) -> 0.17857143
A166: 11 – 20 | B166: =COUNTIFS(PublicacionesUnicas[N° autores (total)],">="&11,PublicacionesUnicas[N° autores (total)],"<="&20) -> 74 | C166: =B166/SUM($B$162:$B$167) -> 0.12585034
A167: Más de 20 | B167: =COUNTIF(PublicacionesUnicas[N° autores (total)],">"&20) -> 18 | C167: =B167/SUM($B$162:$B$167) -> 0.030612245
A178: 9. Participación UFT media por tipo documental
A179: Tipo de documento | B179: % participación UFT (prom.)
A180: Article | B180: =AVERAGEIF(PublicacionesUnicas[Tipo],A180,PublicacionesUnicas[% part. UFT]) -> 0.3861097
A181: Review | B181: =AVERAGEIF(PublicacionesUnicas[Tipo],A181,PublicacionesUnicas[% part. UFT]) -> 0.32647644
A182: Letter | B182: =AVERAGEIF(PublicacionesUnicas[Tipo],A182,PublicacionesUnicas[% part. UFT]) -> 0.59554044
A183: Chapter | B183: =AVERAGEIF(PublicacionesUnicas[Tipo],A183,PublicacionesUnicas[% part. UFT]) -> 0.47408964
A184: Conference Paper | B184: =AVERAGEIF(PublicacionesUnicas[Tipo],A184,PublicacionesUnicas[% part. UFT]) -> 0.39234694
A185: Editorial | B185: =AVERAGEIF(PublicacionesUnicas[Tipo],A185,PublicacionesUnicas[% part. UFT]) -> 0.51262084
A196: 10. Indicadores de colaboración y visibilidad
...

Sheet Informe Cienciométrico
A1: Informe Cienciométrico — Producción Científica UFT
A2: Base de datos: hoja «Publicaciones unificadas» · Período 2024–2025 · Análisis bibliométrico de producción, fuentes, autoría y colaboración
A4: Publicaciones totales | D4: Publicaciones 2025 | G4: Publicaciones 2024 | J4: Fuentes / revistas distintas
A5: =COUNTA(PublicacionesUnicas[Título]) -> 589 | D5: =COUNTIF(PublicacionesUnicas[Año],2025) -> 317 | G5: =COUNTIF(PublicacionesUnicas[Año],2024) -> 271 | J5: {=SUMPRODUCT((PublicacionesUnicas[Revista]<>"")/COUNTIF(PublicacionesUnicas[Revista],PublicacionesUnicas[Revista]&""))} -> 368
A7: % participación UFT (promedio) | D7: Autores por publicación (prom.) | G7: Autores UFT por publicación (prom.) | J7: Investigadores UFT distintos (aprox.)
A8: =AVERAGE(PublicacionesUnicas[% part. UFT]) -> 0.38686157 | D8: =AVERAGE(PublicacionesUnicas[N° autores (total)]) -> 6.8095238 | G8: =AVERAGE(PublicacionesUnicas[N° autores UFT]) -> 1.4601019 | J8: 397
A11: 1. Producción anual
A12: Año | B12: Publicaciones | C12: % del total
A13: 2024 | B13: =COUNTIF(PublicacionesUnicas[Año],2024) -> 271 | C13: =B13/$B$15 -> 0.46088435
A14: 2025 | B14: =COUNTIF(PublicacionesUnicas[Año],2025) -> 317 | C14: =B14/$B$15 -> 0.53911565
A15: Total | B15: =SUM(B13:B14) -> 588 | C15: =B15/$B$15 -> 1
A28: 2. Tipología documental
A29: Tipo de documento | B29: Publicaciones | C29: % del total
A30: Article | B30: =COUNTIF(PublicacionesUnicas[Tipo],A30) -> 412 | C30: =B30/$B$40 -> 0.70068027
A31: Review | B31: =COUNTIF(PublicacionesUnicas[Tipo],A31) -> 103 | C31: =B31/$B$40 -> 0.17517007
A32: Letter | B32: =COUNTIF(PublicacionesUnicas[Tipo],A32) -> 21 | C32: =B32/$B$40 -> 0.035714286
A33: Conference Paper | B33: =COUNTIF(PublicacionesUnicas[Tipo],A33) -> 14 | C33: =B33/$B$40 -> 0.023809524
A34: Note | B34: =COUNTIF(PublicacionesUnicas[Tipo],A34) -> 6 | C34: =B34/$B$40 -> 0.010204082
A35: Editorial | B35: =COUNTIF(PublicacionesUnicas[Tipo],A35) -> 7 | C35: =B35/$B$40 -> 0.011904762
A36: Chapter | B36: =COUNTIF(PublicacionesUnicas[Tipo],A36) -> 17 | C36: =B36/$B$40 -> 0.028911565
A37: Short Survey | B37: =COUNTIF(PublicacionesUnicas[Tipo],A37) -> 3 | C37: =B37/$B$40 -> 0.0051020408
A38: Erratum | B38: =COUNTIF(PublicacionesUnicas[Tipo],A38) -> 4 | C38: =B38/$B$40 -> 0.0068027211
A39: Book | B39: =COUNTIF(PublicacionesUnicas[Tipo],A39) -> 1 | C39: =B39/$B$40 -> 0.0017006803
A40: Total | B40: =SUM(B30:B39) -> 588 | C40: =B40/$B$40 -> 1
A48: 3. Fuentes más productivas (Top 15 revistas)
A49: Revista | B49: Publicaciones
A50: Revista Medica Clinica Las Condes | B50: =COUNTIF(PublicacionesUnicas[Revista],A50) -> 35
A51: Diagnostics | B51: =COUNTIF(PublicacionesUnicas[Revista],A51) -> 10
A52: Revista Chilena de Nutricion | B52: =COUNTIF(PublicacionesUnicas[Revista],A52) -> 10
A53: International Journal of Sports Physiology and Performance | B53: =COUNTIF(PublicacionesUnicas[Revista],A53) -> 10
A54: Antioxidants | B54: =COUNTIF(PublicacionesUnicas[Revista],A54) -> 9
A55: Andes Pediatrica | B55: =COUNTIF(PublicacionesUnicas[Revista],A55) -> 8
A56: International Journal of Molecular Sciences | B56: =COUNTIF(PublicacionesUnicas[Revista],A56) -> 7
A57: Journal of Clinical Medicine | B57: =COUNTIF(PublicacionesUnicas[Revista],A57) -> 7
A58: Piel | B58: =COUNTIF(PublicacionesUnicas[Revista],A58) -> 6
A59: Obesity Surgery | B59: =COUNTIF(PublicacionesUnicas[Revista],A59) -> 5
A60: Critical Care | B60: =COUNTIF(PublicacionesUnicas[Revista],A60) -> 5
A61: Scientific Reports | B61: =COUNTIF(PublicacionesUnicas[Revista],A61) -> 5
... A64: Frontiers in Psychology | B64: =COUNTIF(PublicacionesUnicas[Revista],A64) -> 4
A72: 4. Investigadores UFT más productivos (Top 15)
A73: Investigador/a UFT | B73: Publicaciones | C73: Buscar en Scopus
A74: Orellana-Donoso M. | B74: =COUNTIF(PublicacionesUnicas[Autores UFT (autoría / coautoría)],"*"&A74&"*") -> 32 | C74: 🔍 Buscar autor
A75: Yanine F.F. | B75: =COUNTIF(PublicacionesUnicas[Autores UFT (autoría / coautoría)],"*"&A75&"*") -> 22 | C75: 🔍 Buscar autor
A76: Ferre A. | B76: =COUNTIF(PublicacionesUnicas[Autores UFT (autoría / coautoría)],"*"&A76&"*") -> 21 | C76: 🔍 Buscar autor
A77: Mujika I. | B77: =COUNTIF(PublicacionesUnicas[Autores UFT (autoría / coautoría)],"*"&A77&"*") -> 21 | C77: 🔍 Buscar autor
A78: Giglio A. | B78: =COUNTIF(PublicacionesUnicas[Autores UFT (autoría / coautoría)],"*"&A78&"*") -> 19 | C78: 🔍 Buscar autor
A79: Strauss F.J. | B79: =COUNTIF(PublicacionesUnicas[Autores UFT (autoría / coautoría)],"*"&A79&"*") -> 17 | C79: 🔍 Buscar autor
A80: Díaz F. | B80: =COUNTIF(PublicacionesUnicas[Autores UFT (autoría / coautoría)],"*"&A80&"*") -> 15 | C80: 🔍 Buscar autor
A81: Henríquez-Olguín C. | B81: =COUNTIF(PublicacionesUnicas[Autores UFT (autoría / coautoría)],"*"&A81&"*") -> 13 | C81: 🔍 Buscar autor
A82: López-Arana S. | B82: =COUNTIF(PublicacionesUnicas[Autores UFT (autoría / coautoría)],"*"&A82&"*") -> 13 | C82: 🔍 Buscar autor
A83: Mariotti-Celis M.S. | B83: =COUNTIF(PublicacionesUnicas[Autores UFT (autoría / coautoría)],"*"&A83&"*") -> 12 | C83: 🔍 Buscar autor
A84: Fernández-Verdejo R. | B84: =COUNTIF(PublicacionesUnicas[Autores UFT (autoría / coautoría)],"*"&A84&"*") -> 12 | C84: 🔍 Buscar autor
A85: Cancino-López J. | B85: =COUNTIF(PublicacionesUnicas[Autores UFT (autoría / coautoría)],"*"&A85&"*") -> 11 | C85: 🔍 Buscar autor
... A88: Bustos-Arriagada E. | B88: =COUNTIF(PublicacionesUnicas[Autores UFT (autoría / coautoría)],"*"&A88&"*") -> 9 | C88: 🔍 Buscar autor
A96: 5. Colaboración interna (n° de autores UFT por publicación)
A97: N° autores UFT | B97: Publicaciones | C97: % del total
A98: 1 autor | B98: =COUNTIF(PublicacionesUnicas[N° autores UFT],1) -> 451 | C98: =B98/SUM($B$98:$B$103) -> 0.76831346
A99: 2 autores | B99: =COUNTIF(PublicacionesUnicas[N° autores UFT],2) -> 68 | C99: =B99/SUM($B$98:$B$103) -> 0.11584327
A100: 3 autores | B100: =COUNTIF(PublicacionesUnicas[N° autores UFT],3) -> 31 | C100: =B100/SUM($B$98:$B$103) -> 0.052810903
A101: 4 autores | B101: =COUNTIF(PublicacionesUnicas[N° autores UFT],4) -> 21 | C101: =B101/SUM($B$98:$B$103) -> 0.035775128
A102: 5 autores | B102: =COUNTIF(PublicacionesUnicas[N° autores UFT],5) -> 4 | C102: =B102/SUM($B$98:$B$103) -> 0.0068143101
A103: 6 o más | B103: =COUNTIF(PublicacionesUnicas[N° autores UFT],">=6") -> 12 | C103: =B103/SUM($B$98:$B$103) -> 0.02044293
A114: 6. Intensidad de participación UFT (% de autores UFT sobre el total)
A115: Rango de participación | B115: Publicaciones | C115: % del total
A116: 100% (autoría íntegra UFT) | B116: =COUNTIF(PublicacionesUnicas[% part. UFT],1) -> 93 | C116: =B116/SUM($B$116:$B$120) -> 0.15870307
A117: 50% – 99% | B117: =COUNTIFS(PublicacionesUnicas[% part. UFT],">="&0.5,PublicacionesUnicas[% part. UFT],"<"&1) -> 100 | C117: =B117/SUM($B$116:$B$120) -> 0.17064846
A118: 25% – 49% | B118: =COUNTIFS(PublicacionesUnicas[% part. UFT],">="&0.25,PublicacionesUnicas[% part. UFT],"<"&0.5) -> 144 | C118: =B118/SUM($B$116:$B$120) -> 0.24573379
A119: 10% – 24% | B119: =COUNTIFS(PublicacionesUnicas[% part. UFT],">="&0.1,PublicacionesUnicas[% part. UFT],"<"&0.25) -> 169 | C119: =B119/SUM($B$116:$B$120) -> 0.2883959
A120: < 10% | B120: =COUNTIFS(PublicacionesUnicas[% part. UFT],">"&0,PublicacionesUnicas[% part. UFT],"<"&0.1) -> 80 | C120: =B120/SUM($B$116:$B$120) -> 0.13651877
A132: Nota metodológica y fuentes
A133: • Fuente de datos: hoja «Publicaciones unificadas» (tabla PublicacionesUnicas). Todas las cifras se calculan con fórmulas vinculadas a dicha tabla y se actualizan automáticamente.
A134: • Universo: 589 publicaciones únicas de 2024–2025. El conteo de investigadores UFT distintos (≈397) se deriva del análisis de la columna «Autores UFT (autoría / coautoría)» separando los nombres por «|».
A135: • «Fuentes distintas» incluye ~20 registros cuya revista no fue resuelta en el origen (aparecen como «System.Xml.XmlElement»); estos no afectan los rankings de revistas mostrados.
A136: • % participación UFT = n° de autores UFT / n° total de autores de cada publicación. Colaboración interna = n° de autores UFT firmantes por publicación.
A138: ANÁLISIS COMPLEMENTARIOS
A140: 7. Tipología documental por año
A141: Tipo de documento | B141: 2024 | C141: 2025
A142: Article | B142: =COUNTIFS(PublicacionesUnicas[Tipo],$A142,PublicacionesUnicas[Año],B$141) -> 197 | C142: =COUNTIFS(PublicacionesUnicas[Tipo],$A142,PublicacionesUnicas[Año],C$141) -> 215
A143: Review | B143: =COUNTIFS(PublicacionesUnicas[Tipo],$A143,PublicacionesUnicas[Año],B$141) -> 39 | C143: =COUNTIFS(PublicacionesUnicas[Tipo],$A143,PublicacionesUnicas[Año],C$141) -> 64
A144: Letter | B144: =COUNTIFS(PublicacionesUnicas[Tipo],$A144,PublicacionesUnicas[Año],B$141) -> 9 | C144: =COUNTIFS(PublicacionesUnicas[Tipo],$A144,PublicacionesUnicas[Año],C$141) -> 12
A145: Chapter | B145: =COUNTIFS(PublicacionesUnicas[Tipo],$A145,PublicacionesUnicas[Año],B$141) -> 14 | C145: =COUNTIFS(PublicacionesUnicas[Tipo],$A145,PublicacionesUnicas[Año],C$141) -> 3
A146: Conference Paper | B146: =COUNTIFS(PublicacionesUnicas[Tipo],$A146,PublicacionesUnicas[Año],B$141) -> 4 | C146: =COUNTIFS(PublicacionesUnicas[Tipo],$A146,PublicacionesUnicas[Año],C$141) -> 10
A147: Editorial | B147: =COUNTIFS(PublicacionesUnicas[Tipo],$A147,PublicacionesUnicas[Año],B$141) -> 1 | C147: =COUNTIFS(PublicacionesUnicas[Tipo],$A147,PublicacionesUnicas[Año],C$141) -> 6
A160: 8. Tamaño de los equipos de investigación (n° total de autores)
A161: N° total de autores | B161: Publicaciones | C161: % del total
A162: 1 (individual) | B162: =COUNTIF(PublicacionesUnicas[N° autores (total)],1) -> 49 | C162: =B162/SUM($B$162:$B$167) -> 0.083333333
A163: 2 – 3 | B163: =COUNTIFS(PublicacionesUnicas[N° autores (total)],">="&2,PublicacionesUnicas[N° autores (total)],"<="&3) -> 162 | C163: =B163/SUM($B$162:$B$167) -> 0.2755102
A164: 4 – 6 | B164: =COUNTIFS(PublicacionesUnicas[N° autores (total)],">="&4,PublicacionesUnicas[N° autores (total)],"<="&6) -> 180 | C164: =B164/SUM($B$162:$B$167) -> 0.30612245
A165: 7 – 10 | B165: =COUNTIFS(PublicacionesUnicas[N° autores (total)],">="&7,PublicacionesUnicas[N° autores (total)],"<="&10) -> 105 | C165: =B165/SUM($B$162:$B$167) -> 0.17857143
A166: 11 – 20 | B166: =COUNTIFS(PublicacionesUnicas[N° autores (total)],">="&11,PublicacionesUnicas[N° autores (total)],"<="&20) -> 74 | C166: =B166/SUM($B$162:$B$167) -> 0.12585034
A167: Más de 20 | B167: =COUNTIF(PublicacionesUnicas[N° autores (total)],">"&20) -> 18 | C167: =B167/SUM($B$162:$B$167) -> 0.030612245
A178: 9. Participación UFT media por tipo documental
A179: Tipo de documento | B179: % participación UFT (prom.)
A180: Article | B180: =AVERAGEIF(PublicacionesUnicas[Tipo],A180,PublicacionesUnicas[% part. UFT]) -> 0.3861097
A181: Review | B181: =AVERAGEIF(PublicacionesUnicas[Tipo],A181,PublicacionesUnicas[% part. UFT]) -> 0.32647644
A182: Letter | B182: =AVERAGEIF(PublicacionesUnicas[Tipo],A182,PublicacionesUnicas[% part. UFT]) -> 0.59554044
A183: Chapter | B183: =AVERAGEIF(PublicacionesUnicas[Tipo],A183,PublicacionesUnicas[% part. UFT]) -> 0.47408964
A184: Conference Paper | B184: =AVERAGEIF(PublicacionesUnicas[Tipo],A184,PublicacionesUnicas[% part. UFT]) -> 0.39234694
A185: Editorial | B185: =AVERAGEIF(PublicacionesUnicas[Tipo],A185,PublicacionesUnicas[% part. UFT]) -> 0.51262084
A196: 10. Indicadores de colaboración y visibilidad
...

Sheet Publicaciones_UFT_detalle (2)
A1: Autores finis terrae afiliados | B1: Título | C1: Authors | D1: Year | E1: Full date | F1: Scopus Source title | G1: Volume | H1: Issue | I1: Pages | J1: ISSN | K1: Publisher | L1: Language | M1: CiteScore (publication year) | N1: CiteScore percentile (publication year) * | O1: SJR (publication year) | P1: DOI | Q1: Publication type | R1: EID | S1: Institutions | T1: Scopus Affiliation IDs | U1: Scopus Affiliation names | V1: Country/Region
A2: Mujika I. | B2: Using artificial intelligence for exercise prescription in personalised health promotion: A critical evaluation of OpenAI’s GPT-4 model | C2: Dergaa, I.| Saad, H.B.| El Omri, A.| Glenn, J.M.| Clark, C.C.T.| Washif, J.A.| Guelmami, N.| Hammouda, O.| Al-Horani, R.A.| Reynoso-Sánchez, L.F.| Romdhani, M.| Paineiras-Domingos, L.L.| Vancini, R.L.| Taheri, M.| Mataruna-Dos-Santos, L.J.| Trabelsi, K.| Chtourou, H.| Zghibi, M.| Eken, Ö.| Swed, S.| Aissa, M.B.| Shawki, H.H.| El-Seedi, H.R.| Mujika, I.| Seiler, S.| Zmijewski, P.| Pyne, D.B.| Knechtle, B.| Asif, I.M.| Drezner, J.A.| Sandbakk, Ø.| Chamari, K. | D2: 2024 | E2: 45292 | F2: Biology of Sport | G2: 42 | H2: 2 | I2: 221-241 | J2: ISSN-0860021X | K2: Institute of Sport | L2: English | M2: 9.4 | N2: 3.0 | O2: 1645 | P2: 10.5114/biolsport.2024.133661 | Q2: Article | R2: 2-s2.0-85188146191 | S2: Hamad Medical Corporation| Jiangsu University| University of Canberra| University of Aleppo| University of Zurich| Universidad Finis Terrae| University of Genoa| Jozef Pilsudski University of Physical Education in Warsaw| University of Alabama at Birmingham| University of Manouba| Islamic University of Madinah| University of Agder| Birmingham City University| University of Sousse| Canadian University Dubai| Nagoya City University| University of Tehran| Université Paris Nanterre| Yarmouk University| Norwegian University of Science and Technology| Coventry University| Universidade Federal da Bahia| Inonu University| University of the Basque Country| University of Jendouba| University of Sfax| Universidade Federal do Espírito Santo| University of Washington | T2: 60264454| 60064746| 60091664| 60279855| 60044627| 60058071| 60060593| 60072743| 60330445| 60100434| 60017326| 60090678| 60025153| 60017338| 60206635| 60042547| 60044065| 122712524| 60013710| 60028426| 60022927| 60105484| 60015585| 60072763| 60072762| 60004321| 60105081| 60017482| 60027856| 60105368| 60080184| 60010960| 60022193| 60012614| 60027086| 60119065| 60028548| 60015481| 60013141| 60070316| 60274653 | U2: Primary Health Care Corporation| University of Sfax| Institut Supérieur du Sport et de l'Education Physique de Sfax| Institut Supérieur de Sport et de l´Education Physique du Kef| Hopital Farhat Hached Sousse| Université de Sousse| Faculty of Medicine sousse| Hamad Medical Corporation| Neurotrack Technologies, Inc.| Birmingham City University| Coventry University| Institut Sukan Negara Malaysia| Università degli Studi di Genova| Université Paris Nanterre| Laboratoire Interdisciplinaire en Neurosciences, Physiologie et Psychologie : Activité Physique, Santé et Apprentissages - LINP2| Faculty of Medicine of Sfax| Yarmouk University| Autonomous University of Occident| Universidade Federal da Bahia| Universidade Federal do Espírito Santo| University of Tehran| Canadian University Dubai| Inönü Üniversitesi| Aleppo Faculty of Medicine| University of Aleppo| Nagoya City University Graduate School of Medical Sciences| Islamic University of Madinah| Jiangsu University| Universidad del Pais Vasco| Universidad Finis Terrae| Universitetet i Agder| Akademia Wychowania Fizycznego Józefa Piłsudskiego w Warszawie| University of Canberra| Universität Zürich| The University of Alabama at Birmingham| UAB Department of Family and Community Medicine| University of Washington School of Medicine| University of Washington| Norges Teknisk-Naturvitenskapelige Universitet| Université de la Manouba| Institut Supérieur du Sport et de l'Education Physique de Ksar-Saïd | V2: United Arab Emirates| Chile| United Kingdom| Mexico| Spain| Japan| Syrian Arab Republic| Italy| France| Brazil| Qatar| Norway| China| Tunisia| Poland| Jordan| United States| Saudi Arabia| Turkey| Switzerland| Australia| Malaysia| Iran
A3: Fernández-Verdejo R. | B3: Fibro-adipogenic progenitors in physiological adipogenesis and intermuscular adipose tissue remodeling | C3: Flores-Opazo, M.| Kopinke, D.| Helmbacher, F.| Fernández-Verdejo, R.| Tuñón-Suárez, M.| Lynch, G.S.| Contreras, O. | D3: 2024 | E3: 45444 | F3: Molecular Aspects of Medicine | G3: 97 | H3: - | I3: - | J3: ISSN-00982997 | K3: Elsevier Ltd | L3: English | M3: 18.2 | N3: 1.0 | O3: 2947 | P3: 10.1016/j.mam.2024.101277 | Q3: Review | R3: 2-s2.0-85193826870 | S3: Louisiana State University| Universidad de O'Higgins| University of Florida| LSU Pennington Biomedical Research Center| Aix-Marseille Université| CNRS| University of Melbourne| Universidad Finis Terrae| University of New South Wales| Victor Chang Cardiac Research Institute | T3: 60157974| 60013959| 60007567| 60034123| 60102127| 60008134| 60021235| 60007566| 60105368| 60343000| 60343038| 60026553| 60028061| 60028333 | U3: Universidad de O’Higgins| University of Florida| University of Florida College of Medicine| Institut de Biologie du Développement de Marseille| Aix Marseille Université| CNRS Centre National de la Recherche Scientifique| Pennington Biomedical Research Center| Louisiana State University| Universidad Finis Terrae| Department of Anatomy and Physiology| Centre for Muscle Research| University of Melbourne| Victor Chang Cardiac Research Institute| UNSW Sydney | V3: Chile| United States| Australia| France
A4: Tuñón-Suárez M. | B4: Fibro-adipogenic progenitors in physiological adipogenesis and intermuscular adipose tissue remodeling | C4: Flores-Opazo, M.| Kopinke, D.| Helmbacher, F.| Fernández-Verdejo, R.| Tuñón-Suárez, M.| Lynch, G.S.| Contreras, O. | D4: 2024 | E4: 45444 | F4: Molecular Aspects of Medicine | G4: 97 | H4: - | I4: - | J4: ISSN-00982997 | K4: Elsevier Ltd | L4: English | M4: 18.2 | N4: 1.0 | O4: 2947 | P4: 10.1016/j.mam.2024.101277 | Q4: Review | R4: 2-s2.0-85193826870 | S4: Louisiana State University| Universidad de O'Higgins| University of Florida| LSU Pennington Biomedical Research Center| Aix-Marseille Université| CNRS| University of Melbourne| Universidad Finis Terrae| University of New South Wales| Victor Chang Cardiac Research Institute | T4: 60157974| 60013959| 60007567| 60034123| 60102127| 60008134| 60021235| 60007566| 60105368| 60343000| 60343038| 60026553| 60028061| 60028333 | U4: Universidad de O’Higgins| University of Florida| University of Florida College of Medicine| Institut de Biologie du Développement de Marseille| Aix Marseille Université| CNRS Centre National de la Recherche Scientifique| Pennington Biomedical Research Center| Louisiana State University| Universidad Finis Terrae| Department of Anatomy and Physiology| Centre for Muscle Research| University of Melbourne| Victor Chang Cardiac Research Institute| UNSW Sydney | V4: Chile| United States| Australia| France
A5: Chavez-Reyes A. | B5: Therapeutic Antisense Oligonucleotides in Oncology: From Bench to Bedside | C5: Çakan, E.| Lara, O.D.| Szymanowska, A.| Bayraktar, E.| Chavez-Reyes, A.| Lopez-Berestein, G.| Amero, P.| Rodriguez-Aguayo, C. | D5: 2024 | E5: 45536 | F5: Cancers | G5: 16 | H5: 17 | I5: - | J5: ISSN-20726694 | K5: Multidisciplinary Digital Publishing Institute (MDPI) | L5: English | M5: 8.8 | N5: 17.0 | O5: 1462 | P5: 10.3390/cancers16172940 | Q5: Review | R5: 2-s2.0-85203665259 | S5: University of Texas MD Anderson Cancer Center| Hacettepe University| University of North Carolina at Chapel Hill| Gaziantep University| Universidad Finis Terrae | T5: 60015023| 60020484| 60025111| 60017595| 60105368 | U5: The University of Texas MD Anderson Cancer Center| Hacettepe Üniversitesi| The University of North Carolina at Chapel Hill| Gaziantep Üniversitesi| Universidad Finis Terrae | V5: Chile| United States| Turkey
A6: Mayo B. | B6: Curcumin Administration Routes in Breast Cancer Treatment | C6: Mayo, B.| Penroz, S.| Torres, K.| Simón, L. | D6: 2024 | E6: 45597 | F6: International Journal of Molecular Sciences | G6: 25 | H6: 21 | I6: - | J6: ISSN-16616596 | K6: Multidisciplinary Digital Publishing Institute (MDPI) | L6: English | M6: 9.0 | N6: 10.0 | O6: 1273 | P6: 10.3390/ijms252111492 | Q6: Review | R6: 2-s2.0-85208575143 | S6: Universidad Finis Terrae | T6: 601053680000000 | U6: Universidad Finis Terrae | V6: Chile
A7: Penroz S. | B7: Curcumin Administration Routes in Breast Cancer Treatment | C7: Mayo, B.| Penroz, S.| Torres, K.| Simón, L. | D7: 2024 | E7: 45597 | F7: International Journal of Molecular Sciences | G7: 25 | H7: 21 | I7: - | J7: ISSN-16616596 | K7: Multidisciplinary Digital Publishing Institute (MDPI) | L7: English | M7: 9.0 | N7: 10.0 | O7: 1273 | P7: 10.3390/ijms252111492 | Q7: Review | R7: 2-s2.0-85208575143 | S7: Universidad Finis Terrae | T7: 601053680000000 | U7: Universidad Finis Terrae | V7: Chile
A8: Torres K. | B8: Curcumin Administration Routes in Breast Cancer Treatment | C8: Mayo, B.| Penroz, S.| Torres, K.| Simón, L. | D8: 2024 | E8: 45597 | F8: International Journal of Molecular Sciences | G8: 25 | H8: 21 | I8: - | J8: ISSN-16616596 | K8: Multidisciplinary Digital Publishing Institute (MDPI) | L8: English | M8: 9.0 | N8: 10.0 | O8: 1273 | P8: 10.3390/ijms252111492 | Q8: Review | R8: 2-s2.0-85208575143 | S8: Universidad Finis Terrae | T8: 601053680000000 | U8: Universidad Finis Terrae | V8: Chile
A9: Simón L. | B9: Curcumin Administration Routes in Breast Cancer Treatment | C9: Mayo, B.| Penroz, S.| Torres, K.| Simón, L. | D9: 2024 | E9: 45597 | F9: International Journal of Molecular Sciences | G9: 25 | H9: 21 | I9: - | J9: ISSN-16616596 | K9: Multidisciplinary Digital Publishing Institute (MDPI) | L9: English | M9: 9.0 | N9: 10.0 | O9: 1273 | P9: 10.3390/ijms252111492 | Q9: Review | R9: 2-s2.0-85208575143 | S9: Universidad Finis Terrae | T9: 601053680000000 | U9: Universidad Finis Terrae | V9: Chile
A10: Fuentealba J.M. | B10: Management of alcohol use disorder: a gastroenterology and hepatology-focused perspective | C10: Díaz, L.A.| König, D.| Weber, S.| Ayares, G.| Fuentealba, J.M.| Vázquez, V.| Bataller, R.| Kamath, P.S.| Winder, G.S.| Leggio, L.| Arab, J.P. | D10: 2025 | E10: 45778 | F10: The Lancet Gastroenterology and Hepatology | G10: 10 | H10: 5 | I10: 475-490 | J10: ISSN-24681253 | K10: Elsevier Ltd | L10: English | M10: 64.3 | N10: 1.0 | O10: 13113 | P10: 10.1016/S2468-1253(24)00380-7 | Q10: Review | R10: 2-s2.0-86000364846 | S10: National Institutes of Health| Medical University of Vienna| Mayo Clinic Rochester, MN| Centro de Investigación Biomédica en Red| Virginia Commonwealth University| Universidad Finis Terrae| University of Michigan, Ann Arbor| University of California at San Diego| Instituto de Salud Carlos III| Pontificia Universidad Católica de Chile| August Pi i Sunyer Biomedical Research Institute| Instituto Tecnologico de Estudios Superiores de Monterrey | T10: 60029681| 60088718| 60030612| 60011394| 60105368| 60007966| 60001285| 60078879| 60010814| 60030315| 60005558| 60025778| 60033182| 60006577| 60020468| 60016730| 60010966 | U10: Pontificia Universidad Católica de Chile| Escuela de Medicina| University of California, San Diego| Medizinische Universität Wien| Universidad Finis Terrae| Tecnológico de Monterrey| Escuela de Medicina y Ciencias de la Salud TecSalud| Centro de Investigación Biomédica en Red de Enfermedades Hepáticas y Digestivas| Institut d'Investigacions Biomèdiques August Pi i Sunyer - IDIBAPS| Hospital Clínic de Barcelona| Mayo Clinic| University of Michigan, Ann Arbor| University of Michigan Medical School| National Institutes of Health (NIH)| National Institute on Drug Abuse (NIDA)| National Institute on Alcohol Abuse and Alcoholism (NIAAA)| VCU School of Medicine | V10: Chile| Austria| Mexico| Spain| United States
A11: Hidalgo-Rosa Y. | B11: UiO-66(Zr) as drug delivery system for non-steroidal anti-inflammatory drugs | C11: Salazar, J.| Hidalgo-Rosa, Y.| Burboa, P.C.| Wu, Y.-N.| Escalona, N.| Leiva, A.| Zarate, X.| Schott, E. | D11: 2024 | E11: 45444 | F11: Journal of Controlled Release | G11: 370 | H11: - | I11: 392-404 | J11: ISSN-01683659 | K11: Elsevier B.V. | L11: English | M11: 19.4 | N11: 2.0 | O11: 2.47 | P11: 10.1016/j.jconrel.2024.04.035 | Q11: Article | R11: 2-s2.0-85192014123 | S11: Universidad Autónoma de Chile| Ministerio de Planificación, Chile| Universidad Finis Terrae| Rutgers - The State University of New Jersey, New Brunswick| Pontificia Universidad Católica de Chile| Tongji University | T11: 60029681| 60005208| 60073652| 60105371| 60281487| 60105368 | U11: Pontificia Universidad Católica de Chile| Rutgers New Jersey Medical School| Tongji University| Universidad Autónoma de Chile| Núcleo Milenio en Procesos Catalíticos hacia la Química Sustentable| Universidad Finis Terrae | V11: Chile| China| United States
A12: Strauss F.J. | B12: Impact of keratinized mucosa on implant-health related parameters: A 10-year prospective re-analysis study | C12: Mancini, L.| Strauss, F.J.| Lim, H.-C.| Tavelli, L.| Jung, R.E.| Naenni, N.| Thoma, D.S. | D12: 2024 | E12: 45444 | F12: Clinical Implant Dentistry and Related Research | G12: 26 | H12: 3 | I12: 554-563 | J12: ISSN-15230899 | K12: John Wiley and Sons Inc | L12: English | M12: 6.4 | N12: 7.0 | O12: 1315 | P12: 10.1111/cid.13314 | Q12: Article | R12: 2-s2.0-85186625457 | S12: Kyung Hee University| University of L'Aquila| Harvard University| University of Zurich| Universidad Finis Terrae| Yonsei University| Universidad de Chile | T12: 60012614| 60018783| 127992824| 60105368| 60012464| 60001873| 60005856| 60115878 | U12: Universität Zürich| Università degli Studi dell'Aquila| Center for Clinical Research and Evidence Synthesis in Oral Tissue Regeneration (CRITERION)| Universidad Finis Terrae| Universidad de Chile| Kyung Hee University| Harvard School of Dental Medicine| Yonsei University College of Dentistry | V12: Chile| South Korea| United States| Switzerland| Italy
A13: Yanine F.F. | B13: A comprehensive review of smart energy management systems for photovoltaic power generation utilizing the internet of things | C13: Rao, C.K.| Sahoo, S.K.| Yanine, F.F. | D13: 2025 | E13: 45839 | F13: Unconventional Resources | G13: 7 | H13: - | I13: - | J13: ISSN-26665190 | K13: KeAi Communications Co. | L13: English | M13: 6.4 | N13: 25.0 | O13: 0.864 | P13: 10.1016/j.uncres.2025.100197 | Q13: Review | R13: 2-s2.0-105004998221 | S13: Biju Patnaik University of Technology| Universidad Finis Terrae| Aditya Institute of Technology and Management | T13: 60077979| 60114758| 60114662| 60105368 | U13: Biju Patnaik University of Technology| BPUT, Parala Maharaja Engineering College| Aditya Institute of Technology and Management| Universidad Finis Terrae | V13: Chile| India
A14: Yanine F.F. | B14: IoT enabled Intelligent Energy Management System employing advanced forecasting algorithms and load optimization strategies to enhance renewable energy generation | C14: Krishna Rao, C.| Sahoo, S.K.| Yanine, F.F. | D14: 2024 | E14: 45292 | F14: Unconventional Resources | G14: 4 | H14: - | I14: - | J14: ISSN-26665190 | K14: KeAi Communications Co. | L14: English | M14: 5.3 | N14: 29.0 | O14: 0.828 | P14: 10.1016/j.uncres.2024.100101 | Q14: Article | R14: 2-s2.0-85200812969 | S14: Biju Patnaik University of Technology| Universidad Finis Terrae| Aditya Institute of Technology and Management | T14: 60114758| 60077979| 60114662| 60105368 | U14: BPUT, Parala Maharaja Engineering College| Biju Patnaik University of Technology| Aditya Institute of Technology and Management| Universidad Finis Terrae | V14: Chile| India
A15: Fernández-Verdejo R. | B15: Energy Expenditure in Humans: Principles, Methods, and Changes Throughout the Life Course | C15: Fernández-Verdejo, R.| Sanchez-Delgado, G.| Ravussin, E. | D15: 2024 | E15: 45533 | F15: Annual Review of Nutrition | G15: 44 | H15: 1 | I15: 51-76 | J15: ISSN-01999885 | K15: Annual Reviews Inc. | L15: English | M15: 22.3 | N15: 1.0 | O15: 4435 | P15: 10.1146/annurev-nutr-062122-031443 | Q15: Review | R15: 2-s2.0-85202905959 | S15: Louisiana State University| LSU Pennington Biomedical Research Center| Centro de Investigación Biomédica en Red| Université de Sherbrooke| Universidad Finis Terrae| Instituto de Salud Carlos III| University of Granada | T15: 60021235| 60007566| 60105368| 60027844| 60001602| 60104562| 60104563| 60011832| 60004772| 114245405 | U15: Pennington Biomedical Research Center| Louisiana State University| Universidad Finis Terrae| Universidad de Granada| Instituto de Salud Carlos III| Centro de Investigación Biomédica en Red| Centro de Investigación Biomédica en Red-Fisiopatología de la Obesidad y Nutrición| Université de Sherbrooke| Centre Hospitalier Universitaire de Sherbrooke| Instituto de Investigación Biosanitaria ibs.GRANADA | V15: Chile| Spain| United States| Canada
A16: Henríquez-Olguín C. | B16: Reducing the mitochondrial oxidative burden alleviates lipid-induced muscle insulin resistance in humans | C16: Fiorenza, M.| Onslev, J.| Henríquez-Olguín, C.| Persson, K.W.| Hesselager, S.A.| Jensen, T.E.| Wojtaszewski, J.F.P.| Hostrup, M.| Bangsbo, J. | D16: 2024 | E16: 45597 | F16: System.Xml.XmlElement | G16: 10 | H16: 44 | I16: - | J16: ISSN-23752548 | K16: American Association for the Advancement of Science | L16: English | M16: 19.6 | N16: 4.0 | O16: 4324 | P16: 10.1126/sciadv.adq4461 | Q16: Article | R16: 2-s2.0-85208163795 | S16: University of Copenhagen| Universidad Finis Terrae | T16: 60030840| 60105368 | U16: Københavns Universitet| Universidad Finis Terrae | V16: Chile| Denmark
A17: Salas-Guzmán N. | B17: STEM and gender gap: a systematic review in WoS, Scopus, and ERIC databases (2012–2022) | C17: Beroíza-Valenzuela, F.| Salas-Guzmán, N. | D17: 2024 | E17: 45292 | F17: Frontiers in Education | G17: 9 | H17: - | I17: - | J17: ISSN-2504284X | K17: Frontiers Media SA | L17: English | M17: 3.7 | N17: 29.0 | O17: 0.65 | P17: 10.3389/feduc.2024.1378640 | Q17: Review | R17: 2-s2.0-85193689500 | S17: Universidad Finis Terrae| Universidad de Chile| Universidad Metropolitana de Ciencias de la Educación | T17: 60003126| 60012464| 60105368 | U17: Universidad Metropolitana de Ciencias de la Educación| Universidad de Chile| Universidad Finis Terrae | V17: Chile
A18: Yanine F.F. | B18: An IoT-based intelligent smart energy monitoring system for solar PV power generation | C18: Rao, C.K.| Sahoo, S.K.| Yanine, F.F. | D18: 2024 | E18: 45292 | F18: Energy Harvesting and Systems | G18: 11 | H18: 1 | I18: - | J18: ISSN-23298774 | K18: Walter de Gruyter GmbH | L18: English | M18: 3.8 | N18: 40.0 | O18: 0.358 | P18: 10.1515/ehs-2023-0015 | Q18: Article | R18: 2-s2.0-85175966754 | S18: Biju Patnaik University of Technology| Universidad Finis Terrae| Aditya Institute of Technology and Management | T18: 60114758| 60077979| 60114662| 60105368 | U18: BPUT, Parala Maharaja Engineering College| Biju Patnaik University of Technology| Aditya Institute of Technology and Management| Universidad Finis Terrae | V18: Chile| India
A19: Morales J.-P. | B19: Interoceptive awareness in a clinical setting: the need to bring interoceptive perspectives into clinical evaluation | C19: Solano Durán, P.| Morales, J.-P.| Huepe, D. | D19: 2024 | E19: 45292 | F19: Frontiers in Psychology | G19: 15 | H19: - | I19: - | J19: ISSN-16641078 | K19: Frontiers Media SA | L19: English | M19: 6.3 | N19: 17.0 | O19: 0.872 | P19: 10.3389/fpsyg.2024.1244701 | Q19: Short Survey | R19: 2-s2.0-85196854825 | S19: The University of Sydney| Costa Rica Institute of Technology| Universidad Adolfo Ibáñez| Universidad Finis Terrae | T19: 60003942| 60099123| 60105368| 60212023 | U19: Universidad Adolfo Ibáñez| Instituto Tecnológico de Costa Rica| Universidad Finis Terrae| The University of Sydney Business School | V19: Chile| Costa Rica| Australia
A20: De la Fuente M. | B20: Liver X receptor unlinks intestinal regeneration and tumorigenesis | C20: Das, S.| Parigi, S.M.| Luo, X.| Fransson, J.| Kern, B.C.| Okhovat, A.| Diaz, O.E.| Sorini, C.| Czarnewski, P.| Webb, A.T.| Morales, R.A.| Lebon, S.| Monasterio, G.| Castillo, F.| Tripathi, K.P.| He, N.| Pelczar, P.| Schaltenberg, N.| De la Fuente, M.| López-Köstner, F.| Nylén, S.| Larsen, H.L.| Kuiper, R.| Antonson, P.| Hermoso, M.A.| Huber, S.| Biton, M.| Scharaw, S.| Gustafsson, J.-Å.| Katajisto, P.| Villablanca, E.J. | D20: 2025 | E20: 45687 | F20: Nature | G20: 637 | H20: 8048 | I20: 1198-1206 | J20: ISSN-00280836 | K20: Nature Research | L20: English | M20: 77.7 | N20: 1.0 | O20: 19713 | P20: 10.1038/s41586-024-08247-6 | Q20: Article | R20: 2-s2.0-85209738764 | S20: Uppsala University| Karolinska Institutet| Novo Nordisk Foundation| Max Planck Institute of Molecular Cell Biology and Genetics| Universidad Finis Terrae| KTH Royal Institute of Technology| University of Helsinki| University of Houston| Clínica Las Condes| National Veterinary Institute Norway| Weizmann Institute of Science| Stockholm University| University of Copenhagen| University of Hamburg| Rockefeller University| Universidad de los Andes Mérida| Universidad de Chile | T20: 60012311| 100803701| 60028378| 60237270| 60017563| 60005036| 60017912| 60105368| 60002946| 60012464| 60002439| 60030840| 60006179| 60022237| 60151391| 60005837| 60002952| 60022076| 60019295| 60026827| 60000456 | U20: Karolinska Institutet| Center of Molecular Medicine| Stockholms universitet| Science for Life Laboratory| Weizmann Institute of Science Israel| Universitätsklinikum Hamburg-Eppendorf| Clínica Las Condes| Universidad Finis Terrae| Facultad de Medicina de la Universidad de Chile| Universidad de Chile| Universidad De Los Andes, Merida| Københavns Universitet| Novo Nordisk A/S| Veterinærinstituttet| College of Natural Sciences and Mathematics| University of Houston| Helsingin Yliopisto| Institute of Biotechnology| Karolinska Universitetssjukhuset| Rockefeller University| Max Planck Institute of Molecular Cell Biology and Genetics | V20: Chile| Norway| Israel| Finland| United States| Germany| Denmark| Venezuela| Sweden
A21: Benites M.H. | B21: Ventilation-induced acute kidney injury in acute respiratory failure: Do PEEP levels matter? | C21: Benites, M.H.| Suarez-Sipmann, F.| Kattan, E.| Cruces, P.| Retamal, J. | D21: 2025 | E21: 45992 | F21: Critical Care | G21: 29 | H21: 1 | I21: - | J21: ISSN-13648535 | K21: BioMed Central Ltd | L21: English | M21: 16.0 | N21: 3.0 | O21: 3002 | P21: 10.1186/s13054-025-05343-5 | Q21: Review | R21: 2-s2.0-105000547419 | S21: Uppsala University| Hospital Universitario de la Princesa| Universidad Andrés Bello| Centro de Investigación Biomédica en Red| Universidad Finis Terrae| Clínica Las Condes| Instituto de Salud Carlos III| Pontificia Universidad Católica de Chile | T21: 60017912| 60105368| 60088718| 60029681| 60102756| 60001602| 60024257| 60003858| 60002636| 60281764| 60281394 | U21: Clínica Las Condes| Universidad Finis Terrae| Escuela de Medicina| Pontificia Universidad Católica de Chile| Centro de Investigación Biomédica en Red de Enfermedades Respiratorias| Instituto de Salud Carlos III| Hospital Universitario de la Princesa| Uppsala Universitet| Universidad Andrés Bello| Facultad de Ciencias de la Vida| Hospital El Carmen Dr. Luis Valentín Ferrada | V21: Chile| Spain| Sweden
A22: Mujika I. | B22: Is all work the same? Performance after accumulated work of differing intensities in male professional cyclists | C22: Mateo-March, M.| Leo, P.| Muriel, X.| Javaloyes, A.| Mujika, I.| Barranco-Gil, D.| Pallarés, J.G.| Lucia, A.| Valenzuela, P.L. | D22: 2024 | E22: 45444 | F22: Journal of Science and Medicine in Sport | G22: 27 | H22: 6 | I22: 430-434 | J22: ISSN-14402440 | K22: Elsevier Ltd | L22: English | M22: 6.9 | N22: 8.0 | O22: 1319 | P22: 10.1016/j.jsams.2024.03.005 | Q22: Article | R22: 2-s2.0-85189967168 | S22: Miguel Hernández University| University of Alcalá| Universidad Finis Terrae| University of Innsbruck| Universidad Europea de Madrid| Hospital Universitario 12 de Octubre| University of the Basque Country| University of Murcia| Universidad Europea | T22: 60029767| 60028356| 60009999| 60000130| 60027856| 60105368| 60004024| 60027800 | U22: Universidad Miguel Hernández de Elche| Universidad Europea de Madrid| Universität Innsbruck| Universidad de Murcia| Universidad del Pais Vasco| Universidad Finis Terrae| Hospital Universitario 12 de Octubre| Universidad de Alcalá | V22: Chile| Austria| Spain
A23: Ayares G. | B23: MetALD: New Perspectives on an Old Overlooked Disease | C23: Ayares, G.| Diaz, L.A.| Idalsoaga, F.| Alkhouri, N.| Noureddin, M.| Bataller, R.| Loomba, R.| Arab, J.P.| Arrese, M. | D23: 2025 | E23: 45778 | F23: Liver International | G23: 45 | H23: 5 | I23: - | J23: ISSN-14783223 | K23: John Wiley and Sons Inc | L23: English | M23: 10.3 | N23: 16.0 | O23: 2218 | P23: 10.1111/liv.70017 | Q23: Review | R23: 2-s2.0-105002132315 | S23: Houston Methodist| Virginia Commonwealth University| Universidad Finis Terrae| University of California at San Diego| Pontificia Universidad Católica de Chile| August Pi i Sunyer Biomedical Research Institute| Western University | T23: 60088718| 60029681| 60105368| 60030612| 60031619| 60010884| 60310400| 125289235| 60014933| 60010814| 60030315| 60002476 | U23: Escuela de Medicina| Pontificia Universidad Católica de Chile| Universidad Finis Terrae| University of California, San Diego| Schulich School of Medicine & Dentistry| Western University| London Health Sciences Centre Research Institute| Arizona Liver Health| Houston Methodist Hospital| Institut d'Investigacions Biomèdiques August Pi i Sunyer - IDIBAPS| Hospital Clínic de Barcelona| Virginia Commonwealth University | V23: Chile| Spain| United States| Canada
A24: Mariotti-Celis M.S. | B24: Exploring a Sustainable Process for Polyphenol Extraction from Olive Leaves | C24: Huamán-Castilla, N.L.| Díaz Huamaní, K.S.| Palomino Villegas, Y.C.| Allcca-Alca, E.E.| León-Calvo, N.C.| Colque Ayma, E.J.| Zirena Vilca, F.| Mariotti-Celis, M.S. | D24: 2024 | E24: 45292 | F24: Foods | G24: 13 | H24: 2 | I24: - | J24: ISSN-23048158 | K24: Multidisciplinary Digital Publishing Institute (MDPI) | L24: English | M24: 8.7 | N24: 1.0 | O24: 1021 | P24: 10.3390/foods13020265 | Q24: Article | R24: 2-s2.0-85183352428 | S24: Universidad Nacional de Moquegua| Universidad Finis Terrae | T24: 60122402| 60105368 | U24: Universidad Nacional de Moquegua| Universidad Finis Terrae | V24: Chile| Peru
A25: Orellana-Donoso M. | B25: Effectiveness of DASH Diet versus Other Diet Modalities in Patients with Metabolic Syndrome: A Systematic Review and Meta-Analysis | C25: Valenzuela-Fuenzalida, J.J.| Bravo, V.S.| Valarezo, L.M.| Delgado Retamal, M.F.| Leiva, J.M.| Bruna-Mejías, A.| Nova-Baeza, P.| Orellana-Donoso, M.| Suazo-Santibañez, A.| Oyanedel-Amaro, G.| Gutierrez-Espinoza, H. | D25: 2024 | E25: 45536 | F25: System.Xml.XmlElement | G25: 16 | H25: 18 | I25: - | J25: ISSN-20726643 | K25: Multidisciplinary Digital Publishing Institute (MDPI) | L25: English | M25: 9.1 | N25: 12.0 | O25: 1473 | P25: 10.3390/nu16183054 | Q25: Review | R25: 2-s2.0-85205078698 | S25: Universidad de las Américas - Chile| Universidad de las Américas - Ecuador| Universidad Andrés Bello| Universidad Autónoma de Chile| Universidad Finis Terrae| Universidad Bernardo O'Higgins | T25: 60002636| 60105370| 60105368| 60105362| 60105371| 60104441 | U25: Universidad Andrés Bello| Universidad Bernardo O'Higgins| Universidad Finis Terrae| Universidad de Las Américas Chile| Universidad Autónoma de Chile| Universidad de las Americas - Ecuador | V25: Chile| Ecuador
A26: Yanine F.F. | B26: Design and deployment of a novel decisive algorithm to enable real-time optimal load scheduling within an intelligent smart energy management system based on IoT | C26: Rao, C.K.| Sahoo, S.K.| Yanine, F.F. | D26: 2024 | E26: 45627 | F26: Energy Reports | G26: 12 | H26: - | I26: 579-592 | J26: ISSN-23524847 | K26: Elsevier Ltd | L26: English | M26: 11.7 | N26: 19.0 | O26: 1172 | P26: 10.1016/j.egyr.2024.06.030 | Q26: Article | R26: 2-s2.0-85196976775 | S26: Biju Patnaik University of Technology| Universidad Finis Terrae| Aditya Institute of Technology and Management | T26: 60077979| 60114758| 60114662| 60105368 | U26: Biju Patnaik University of Technology| BPUT, Parala Maharaja Engineering College| Aditya Institute of Technology and Management| Universidad Finis Terrae | V26: Chile| India
A27: Santos M. | B27: Subversive affordances as a form of digital transnational activism: The case of Telegram’s native proxy | C27: Santos, M.| Saldaña, M.| Tsyganova, K. | D27: 2024 | E27: 45292 | F27: New Media and Society | G27: 26 | H27: 1 | I27: 131-153 | J27: ISSN-14614448 | K27: SAGE Publications Ltd | L27: English | M27: 13.7 | N27: 1.0 | O27: 2.4 | P27: 10.1177/14614448211054830 | Q27: Article | R27: 2-s2.0-85118540330 | S27: St. Petersburg State University| Ministerio de Planificación, Chile| Universidad Finis Terrae| Pontificia Universidad Católica de Chile | T27: 60105368| 60029681| 60031888| 60281481 | U27: Universidad Finis Terrae| Pontificia Universidad Católica de Chile| Saint Petersburg State University| Instituto Milenio Fundamentos de los Datos | V27: Chile| Russian Federation
A28: Henriquez-Olguín C. | B28: NAD depletion in skeletal muscle does not compromise muscle function or accelerate aging | C28: Chubanava, S.| Karavaeva, I.| Ehrlich, A.M.| Justicia, R.M.| Basse, A.L.| Kulik, I.| Dalbram, E.| Ahwazi, D.| Heaselgrave, S.R.| Trošt, K.| Stocks, B.| Hodek, O.| Rodrigues, R.N.| Havelund, J.F.| Schlabs, F.L.| Larsen, S.| Yonamine, C.Y.| Henriquez-Olguín, C.| Giustarini, D.| Rossi, R.| Gerhart-Hines, Z.| Moritz, T.| Zierath, J.R.| Sakamoto, K.| Jensen, T.E.| Færgeman, N.J.| Lavery, G.G.| Deshmukh, A.S.| Treebak, J.T. | D28: 2025 | E28: 45839 | F28: Cell Metabolism | G28: 37 | H28: 7 | I28: 1460-1481.e17 | J28: ISSN-15504131 | K28: Cell Press | L28: English | M28: 54.1 | N28: 1.0 | O28: 15978 | P28: 10.1016/j.cmet.2025.04.002 | Q28: Article | R28: 2-s2.0-105005519883 | S28: University of Birmingham| Medical University of Białystok| University of Siena| University of Copenhagen| University of Southern Denmark| Karolinska Institutet| Nottingham Trent University| Universidad Finis Terrae| Swedish University of Agricultural Sciences | T28: 60030840| 60013332| 60253102| 100491300| 60019702| 60027152| 60019160| 60026724| 60105368| 60002838| 60012311| 60006029 | U28: Københavns Universitet| Det Sundhedsvidenskabelige Fakultet| Novo Nordisk Foundation Center for Basic Metabolic Research| Diabetes Center| University of Birmingham| Sveriges lantbruksuniversitet| Syddansk Universitet| Uniwersytet Medyczny w Bialymstoku| Universidad Finis Terrae| Università degli Studi di Siena| Karolinska Institutet| Nottingham Trent University | V28: Chile| United Kingdom| Poland| Germany| Denmark| Italy| Sweden
A29: Lucero-Mora J. | B29: Antimicrobial Effect of Copper Nanoparticles on Relevant Supragingival Oral Bacteria | C29: Oetiker, N.| Salinas, D.| Lucero-Mora, J.| Orellana, R.| Quiroz-Muñoz, M.| Bravo, D.| Pérez-Donoso, J.M. | D29: 2024 | E29: 45352 | F29: Microorganisms | G29: 12 | H29: 3 | I29: - | J29: ISSN-20762607 | K29: Multidisciplinary Digital Publishing Institute (MDPI) | L29: English | M29: 7.7 | N29: 22.0 | O29: 1009 | P29: 10.3390/microorganisms12030624 | Q29: Article | R29: 2-s2.0-85189080106 | S29: Universidad de Santiago de Chile| Universidad Andrés Bello| Universidad Finis Terrae| Universidad de Chile | T29: 60281764| 60002636| 60012464| 60105368| 60023383 | U29: Facultad de Ciencias de la Vida| Universidad Andrés Bello| Universidad de Chile| Universidad Finis Terrae| Universidad de Santiago de Chile | V29: Chile
A30: Yanine F.F. | B30: Development of a smart cloud-based monitoring system for solar photovoltaic energy generation | C30: Rao, C.K.| Sahoo, S.K.| Yanine, F.F. | D30: 2025 | E30: 45748 | F30: Unconventional Resources | G30: 6 | H30: - | I30: - | J30: ISSN-26665190 | K30: KeAi Communications Co. | L30: English | M30: 6.4 | N30: 25.0 | O30: 0.864 | P30: 10.1016/j.uncres.2025.100173 | Q30: Article | R30: 2-s2.0-105001709998 | S30: Biju Patnaik University of Technology| Universidad Finis Terrae| Aditya Institute of Technology and Management | T30: 60114662| 60114758| 60077979| 60105368 | U30: Aditya Institute of Technology and Management| BPUT, Parala Maharaja Engineering College| Biju Patnaik University of Technology| Universidad Finis Terrae | V30: Chile| India
A31: Morales-Guevara R. | B31: Synthesis, Physicochemical Characterization, and Antimicrobial Evaluation of Halogen-Substituted Non-Metal Pyridine Schiff Bases | C31: Carreño, A.| Morales-Guevara, R.| Cepeda-Plaza, M.| Páez-Hernández, D.| Preite, M.| Polanco, R.| Barrera, B.| Fuentes, I.| Marchant, P.| Fuentes, J.A. | D31: 2024 | E31: 45566 | F31: Molecules | G31: 29 | H31: 19 | I31: - | J31: ISSN-14203049 | K31: Multidisciplinary Digital Publishing Institute (MDPI) | L31: English | M31: 8.6 | N31: 13.0 | O31: 0.865 | P31: 10.3390/molecules29194726 | Q31: Article | R31: 2-s2.0-85206501956 | S31: Universidad de Santiago de Chile| Universidad Santo Tomás, Santiago| Universidad Andrés Bello| Universidad Finis Terrae| Pontificia Universidad Católica de Chile | T31: 60002636| 60023383| 60105368| 60029681| 60281764| 60009128 | U31: Universidad Andrés Bello| Universidad de Santiago de Chile| Universidad Finis Terrae| Pontificia Universidad Católica de Chile| Facultad de Ciencias de la Vida| Universidad Santo Tomas, Santiago | V31: Chile
A32: Mujika I. | B32: What Is “Zone 2 Training”?: Experts’ Viewpoint on Definition, Training Methods, and Expected Adaptations | C32: Sitko, S.| Artetxe, X.| Bonnevie-Svendsen, M.| Galán-Rioja, M.Á.| Gallo, G.| Grappe, F.| Leo, P.| Mateo, M.| Mujika, I.| Sanders, D.| Seiler, S.| Zabala, M.| Valenzuela, P.L.| Viribay, A. | D32: 2025 | E32: 45962 | F32: International Journal of Sports Physiology and Performance | G32: 20 | H32: 11 | I32: 1614-1617 | J32: ISSN-15550265 | K32: Human Kinetics Publishers Inc. | L32: English | M32: 7.5 | N32: 7.0 | O32: 1833 | P32: 10.1123/ijspp.2024-0303 | Q32: Article | R32: 2-s2.0-105019666650 | S32: University of Oslo| University of Leon| Groupama| Maastricht University| Adelaide University| University of Alcalá| University of Genoa| University of Innsbruck| Universidad Finis Terrae| University of Zaragoza| University of Granada| University of the Basque Country| Hospital Universitario 12 de Octubre| University of Agder| Miguel Hernández University| Universidad Europea de Madrid| University of Castilla-La Mancha| Universidad Internacional de La Rioja| Universidad Europea | T32: 60016809| 60027856| 60010348| 60003938| 60000823| 60104175| 60025153| 60025532| 60009999| 60031846| 60028356| 60029767| 60105368| 60018869| 60080184| 60027844| 60004024| 60027800| 131511690| 60020657 | U32: Universidad de Zaragoza| Universidad del Pais Vasco| Universitetet i Oslo| Medisinske Fakultet| Universidad de Castilla-La Mancha| International University of La Rioja| Università degli Studi di Genova| Groupama| Universität Innsbruck| University of South Australia| Universidad Europea de Madrid| Universidad Miguel Hernández de Elche| Universidad Finis Terrae| Universiteit Maastricht| Universitetet i Agder| Universidad de Granada| Hospital Universitario 12 de Octubre| Universidad de Alcalá| Glut4Science| Universidad de León | V32: Austria| Chile| Norway| Spain| Australia| France| Italy| Netherlands
A33: Díaz-Castro F. | B33: A single bout of resistance exercise triggers mitophagy, potentially involving the ejection of mitochondria in human skeletal muscle | C33: Díaz-Castro, F.| Tuñón-Suárez, M.| Rivera, P.| Botella, J.| Cancino, J.| Figueroa, A.M.| Gutiérrez, J.| Cantin, C.| Deldicque, L.| Zbinden-Foncea, H.| Nielsen, J.| Henríquez-Olguín, C.| Morselli, E.| Castro-Sepúlveda, M. | D33: 2024 | E33: 45536 | F33: Acta Physiologica | G33: 240 | H33: 9 | I33: - | J33: ISSN-17481708 | K33: John Wiley and Sons Inc | L33: English | M33: 9.5 | N33: 11.0 | O33: 1528 | P33: 10.1111/apha.14203 | Q33: Article | R33: 2-s2.0-85198729088 | S33: Université catholique de Louvain| University of Lausanne| University of Copenhagen| Francisco de Vitoria University| University of Southern Denmark| Universidad San Sebastián| Universidad Finis Terrae| Pontificia Universidad Católica de Chile | T33: 60105368| 60029681| 60000636| 60023561| 60000874| 60108692| 60019160| 60030840 | U33: Universidad Finis Terrae| Pontificia Universidad Católica de Chile| Universidad San Sebastián| Centre Hospitalier Universitaire Vaudois| UCLouvain| Universidad Francisco de Vitoria| Syddansk Universitet| Københavns Universitet | V33: Belgium| Chile| Spain| Switzerland| Denmark
A34: Tuñón-Suárez M. | B34: A single bout of resistance exercise triggers mitophagy, potentially involving the ejection of mitochondria in human skeletal muscle | C34: Díaz-Castro, F.| Tuñón-Suárez, M.| Rivera, P.| Botella, J.| Cancino, J.| Figueroa, A.M.| Gutiérrez, J.| Cantin, C.| Deldicque, L.| Zbinden-Foncea, H.| Nielsen, J.| Henríquez-Olguín, C.| Morselli, E.| Castro-Sepúlveda, M. | D34: 2024 | E34: 45536 | F34: Acta Physiologica | G34: 240 | H34: 9 | I34: - | J34: ISSN-17481708 | K34: John Wiley and Sons Inc | L34: English | M34: 9.5 | N34: 11.0 | O34: 1528 | P34: 10.1111/apha.14203 | Q34: Article | R34: 2-s2.0-85198729088 | S34: Université catholique de Louvain| University of Lausanne| University of Copenhagen| Francisco de Vitoria University| University of Southern Denmark| Universidad San Sebastián| Universidad Finis Terrae| Pontificia Universidad Católica de Chile | T34: 60105368| 60029681| 60000636| 60023561| 60000874| 60108692| 60019160| 60030840 | U34: Universidad Finis Terrae| Pontificia Universidad Católica de Chile| Universidad San Sebastián| Centre Hospitalier Universitaire Vaudois| UCLouvain| Universidad Francisco de Vitoria| Syddansk Universitet| Københavns Universitet | V34: Belgium| Chile| Spain| Switzerland| Denmark
A35: Cancino J. | B35: A single bout of resistance exercise triggers mitophagy, potentially involving the ejection of mitochondria in human skeletal muscle | C35: Díaz-Castro, F.| Tuñón-Suárez, M.| Rivera, P.| Botella, J.| Cancino, J.| Figueroa, A.M.| Gutiérrez, J.| Cantin, C.| Deldicque, L.| Zbinden-Foncea, H.| Nielsen, J.| Henríquez-Olguín, C.| Morselli, E.| Castro-Sepúlveda, M. | D35: 2024 | E35: 45536 | F35: Acta Physiologica | G35: 240 | H35: 9 | I35: - | J35: ISSN-17481708 | K35: John Wiley and Sons Inc | L35: English | M35: 9.5 | N35: 11.0 | O35: 1528 | P35: 10.1111/apha.14203 | Q35: Article | R35: 2-s2.0-85198729088 | S35: Université catholique de Louvain| University of Lausanne| University of Copenhagen| Francisco de Vitoria University| University of Southern Denmark| Universidad San Sebastián| Universidad Finis Terrae| Pontificia Universidad Católica de Chile | T35: 60105368| 60029681| 60000636| 60023561| 60000874| 60108692| 60019160| 60030840 | U35: Universidad Finis Terrae| Pontificia Universidad Católica de Chile| Universidad San Sebastián| Centre Hospitalier Universitaire Vaudois| UCLouvain| Universidad Francisco de Vitoria| Syddansk Universitet| Københavns Universitet | V35: Belgium| Chile| Spain| Switzerland| Denmark
A36: Figueroa A.M. | B36: A single bout of resistance exercise triggers mitophagy, potentially involving the ejection of mitochondria in human skeletal muscle | C36: Díaz-Castro, F.| Tuñón-Suárez, M.| Rivera, P.| Botella, J.| Cancino, J.| Figueroa, A.M.| Gutiérrez, J.| Cantin, C.| Deldicque, L.| Zbinden-Foncea, H.| Nielsen, J.| Henríquez-Olguín, C.| Morselli, E.| Castro-Sepúlveda, M. | D36: 2024 | E36: 45536 | F36: Acta Physiologica | G36: 240 | H36: 9 | I36: - | J36: ISSN-17481708 | K36: John Wiley and Sons Inc | L36: English | M36: 9.5 | N36: 11.0 | O36: 1528 | P36: 10.1111/apha.14203 | Q36: Article | R36: 2-s2.0-85198729088 | S36: Université catholique de Louvain| University of Lausanne| University of Copenhagen| Francisco de Vitoria University| University of Southern Denmark| Universidad San Sebastián| Universidad Finis Terrae| Pontificia Universidad Católica de Chile | T36: 60105368| 60029681| 60000636| 60023561| 60000874| 60108692| 60019160| 60030840 | U36: Universidad Finis Terrae| Pontificia Universidad Católica de Chile| Universidad San Sebastián| Centre Hospitalier Universitaire Vaudois| UCLouvain| Universidad Francisco de Vitoria| Syddansk Universitet| Københavns Universitet | V36: Belgium| Chile| Spain| Switzerland| Denmark
A37: Gutiérrez J. | B37: A single bout of resistance exercise triggers mitophagy, potentially involving the ejection of mitochondria in human skeletal muscle | C37: Díaz-Castro, F.| Tuñón-Suárez, M.| Rivera, P.| Botella, J.| Cancino, J.| Figueroa, A.M.| Gutiérrez, J.| Cantin, C.| Deldicque, L.| Zbinden-Foncea, H.| Nielsen, J.| Henríquez-Olguín, C.| Morselli, E.| Castro-Sepúlveda, M. | D37: 2024 | E37: 45536 | F37: Acta Physiologica | G37: 240 | H37: 9 | I37: - | J37: ISSN-17481708 | K37: John Wiley and Sons Inc | L37: English | M37: 9.5 | N37: 11.0 | O37: 1528 | P37: 10.1111/apha.14203 | Q37: Article | R37: 2-s2.0-85198729088 | S37: Université catholique de Louvain| University of Lausanne| University of Copenhagen| Francisco de Vitoria University| University of Southern Denmark| Universidad San Sebastián| Universidad Finis Terrae| Pontificia Universidad Católica de Chile | T37: 60105368| 60029681| 60000636| 60023561| 60000874| 60108692| 60019160| 60030840 | U37: Universidad Finis Terrae| Pontificia Universidad Católica de Chile| Universidad San Sebastián| Centre Hospitalier Universitaire Vaudois| UCLouvain| Universidad Francisco de Vitoria| Syddansk Universitet| Københavns Universitet | V37: Belgium| Chile| Spain| Switzerland| Denmark
A38: Zbinden-Foncea H. | B38: A single bout of resistance exercise triggers mitophagy, potentially involving the ejection of mitochondria in human skeletal muscle | C38: Díaz-Castro, F.| Tuñón-Suárez, M.| Rivera, P.| Botella, J.| Cancino, J.| Figueroa, A.M.| Gutiérrez, J.| Cantin, C.| Deldicque, L.| Zbinden-Foncea, H.| Nielsen, J.| Henríquez-Olguín, C.| Morselli, E.| Castro-Sepúlveda, M. | D38: 2024 | E38: 45536 | F38: Acta Physiologica | G38: 240 | H38: 9 | I38: - | J38: ISSN-17481708 | K38: John Wiley and Sons Inc | L38: English | M38: 9.5 | N38: 11.0 | O38: 1528 | P38: 10.1111/apha.14203 | Q38: Article | R38: 2-s2.0-85198729088 | S38: Université catholique de Louvain| University of Lausanne| University of Copenhagen| Francisco de Vitoria University| University of Southern Denmark| Universidad San Sebastián| Universidad Finis Terrae| Pontificia Universidad Católica de Chile | T38: 60105368| 60029681| 60000636| 60023561| 60000874| 60108692| 60019160| 60030840 | U38: Universidad Finis Terrae| Pontificia Universidad Católica de Chile| Universidad San Sebastián| Centre Hospitalier Universitaire Vaudois| UCLouvain| Universidad Francisco de Vitoria| Syddansk Universitet| Københavns Universitet | V38: Belgium| Chile| Spain| Switzerland| Denmark
A39: Henríquez-Olguín C. | B39: A single bout of resistance exercise triggers mitophagy, potentially involving the ejection of mitochondria in human skeletal muscle | C39: Díaz-Castro, F.| Tuñón-Suárez, M.| Rivera, P.| Botella, J.| Cancino, J.| Figueroa, A.M.| Gutiérrez, J.| Cantin, C.| Deldicque, L.| Zbinden-Foncea, H.| Nielsen, J.| Henríquez-Olguín, C.| Morselli, E.| Castro-Sepúlveda, M. | D39: 2024 | E39: 45536 | F39: Acta Physiologica | G39: 240 | H39: 9 | I39: - | J39: ISSN-17481708 | K39: John Wiley and Sons Inc | L39: English | M39: 9.5 | N39: 11.0 | O39: 1528 | P39: 10.1111/apha.14203 | Q39: Article | R39: 2-s2.0-85198729088 | S39: Université catholique de Louvain| University of Lausanne| University of Copenhagen| Francisco de Vitoria University| University of Southern Denmark| Universidad San Sebastián| Universidad Finis Terrae| Pontificia Universidad Católica de Chile | T39: 60105368| 60029681| 60000636| 60023561| 60000874| 60108692| 60019160| 60030840 | U39: Universidad Finis Terrae| Pontificia Universidad Católica de Chile| Universidad San Sebastián| Centre Hospitalier Universitaire Vaudois| UCLouvain| Universidad Francisco de Vitoria| Syddansk Universitet| Københavns Universitet | V39: Belgium| Chile| Spain| Switzerland| Denmark
A40: Castro-Sepúlveda M. | B40: A single bout of resistance exercise triggers mitophagy, potentially involving the ejection of mitochondria in human skeletal muscle | C40: Díaz-Castro, F.| Tuñón-Suárez, M.| Rivera, P.| Botella, J.| Cancino, J.| Figueroa, A.M.| Gutiérrez, J.| Cantin, C.| Deldicque, L.| Zbinden-Foncea, H.| Nielsen, J.| Henríquez-Olguín, C.| Morselli, E.| Castro-Sepúlveda, M. | D40: 2024 | E40: 45536 | F40: Acta Physiologica | G40: 240 | H40: 9 | I40: - | J40: ISSN-17481708 | K40: John Wiley and Sons Inc | L40: English | M40: 9.5 | N40: 11.0 | O40: 1528 | P40: 10.1111/apha.14203 | Q40: Article | R40: 2-s2.0-85198729088 | S40: Université catholique de Louvain| University of Lausanne| University of Copenhagen| Francisco de Vitoria University| University of Southern Denmark| Universidad San Sebastián| Universidad Finis Terrae| Pontificia Universidad Católica de Chile | T40: 60105368| 60029681| 60000636| 60023561| 60000874| 60108692| 60019160| 60030840 | U40: Universidad Finis Terrae| Pontificia Universidad Católica de Chile| Universidad San Sebastián| Centre Hospitalier Universitaire Vaudois| UCLouvain| Universidad Francisco de Vitoria| Syddansk Universitet| Københavns Universitet | V40: Belgium| Chile| Spain| Switzerland| Denmark
A41: Hartmann Schatloff D. | B41: The role of excimer light in dermatology: a review | C41: Hartmann Schatloff, D.| Retamal Altbir, C.| Valenzuela, F. | D41: 2024 | E41: 45597 | F41: Anais Brasileiros de Dermatologia | G41: 99 | H41: 6 | I41: 887-894 | J41: ISSN-03650596 | K41: Elsevier Espana S.L.U | L41: English | M41: 2.5 | N41: 48.0 | O41: 0.585 | P41: 10.1016/j.abd.2023.12.007 | Q41: Review | R41: 2-s2.0-85200534575 | S41: Universidad Finis Terrae| Universidad de Chile | T41: 60105368| 60012464| 60002946| 60011682 | U41: Universidad Finis Terrae| Universidad de Chile| Facultad de Medicina de la Universidad de Chile| Hospital Clínico Universidad De Chile | V41: Chile
A42: Lucero-Mora J. | B42: Reduced C-reactive protein levels after root canal treatment in clinically healthy young apical periodontitis individuals at cardiovascular risk. A prospective study | C42: Garrido, M.| Bordagaray, M.J.| Schweitzer, C.| Lucero-Mora, J.| Reyes, M.| Pellegrini, E.| Hernández-Ríos, P.| Fernández, A.| Hernández, M. | D42: 2024 | E42: 45383 | F42: International Endodontic Journal | G42: 57 | H42: 4 | I42: 406-415 | J42: ISSN-01432885 | K42: John Wiley and Sons Inc | L42: English | M42: 12.3 | N42: 2.0 | O42: 2335 | P42: 10.1111/iej.14029 | Q42: Article | R42: 2-s2.0-85182858698 | S42: Universidad Andrés Bello| Universidad Finis Terrae| Universidad de Chile | T42: 60012464| 60105368| 60002636 | U42: Universidad de Chile| Universidad Finis Terrae| Universidad Andrés Bello | V42: Chile
A43: Henriquez-Olguín C. | B43: The mitochondrial mRNA-stabilizing protein SLIRP regulates skeletal muscle mitochondrial structure and respiration by exercise-recoverable mechanisms | C43: Pham, T.C.P.| Raun, S.H.| Havula, E.| Henriquez-Olguín, C.| Rubalcava-Gracia, D.| Frank, E.| Fritzen, A.M.| Jannig, P.R.| Andersen, N.R.| Kruse, R.| Ali, M.S.| Irazoki, A.| Halling, J.F.| Ringholm, S.| Needham, E.J.| Hansen, S.| Lemminger, A.K.| Schjerling, P.| Petersen, M.H.| de Almeida, M.E.| Jensen, T.E.| Kiens, B.| Hostrup, M.| Larsen, S.| Ørtenblad, N.| Højlund, K.| Kjær, M.| Ruas, J.L.| Trifunovic, A.| Wojtaszewski, J.F.P.| Nielsen, J.| Qvortrup, K.| Pilegaard, H.| Richter, E.A.| Sylow, L. | D43: 2024 | E43: 45627 | F43: System.Xml.XmlElement | G43: 15 | H43: 1 | I43: - | J43: ISSN-20411723 | K43: Nature Research | L43: English | M43: 23.4 | N43: 3.0 | O43: 4761 | P43: 10.1038/s41467-024-54183-4 | Q43: Article | R43: 2-s2.0-85209230270 | S43: The University of Sydney| University of Cologne| Medical University of Białystok| University of Copenhagen| University of Southern Denmark| Karolinska Institutet| Novo Nordisk Foundation| Universidad Finis Terrae| Max Planck Institute for Metabolism Research| University of Helsinki | T43: 60030840| 60013332| 60029080| 60002952| 60105368| 60012311| 60015591| 60016428| 60025709| 60010710| 60025840| 60019160| 60026724| 60204358| 60024025| 60122634 | U43: Københavns Universitet| Det Sundhedsvidenskabelige Fakultet| Lääketieteellinen Tiedekunta| Helsingin Yliopisto| Universidad Finis Terrae| Karolinska Institutet| Odense Universitetshospital| Steno Diabetes Center Copenhagen| The University of Sydney| Faculty of Medicine and Health| Bispebjerg Hospital| Syddansk Universitet| Uniwersytet Medyczny w Bialymstoku| Medizinische Fakultät| Universität zu Köln| CECAD Exzellant in Alternsforschung | V43: Chile| Finland| Poland| Germany| Australia| Denmark| Sweden
A44: Murray N.P. | B44: The role of matrix metalloproteinase-2 in the metastatic cascade: a review | C44: Murray, N.P. | D44: 2024 | E44: 45292 | F44: Oncologie | G44: 26 | H44: 1 | I44: 27-40 | J44: ISSN-12923818 | K44: Walter de Gruyter GmbH | L44: English | M44: 2.4 | N44: 64.0 | O44: 0.358 | P44: 10.1515/oncologie-2023-0368 | Q44: Review | R44: 2-s2.0-85183026431 | S44: Universidad Finis Terrae | T44: 60105368| 60281395 | U44: Universidad Finis Terrae| Hospital de Carabineros de Chile | V44: Chile
A45: Dreyse J. | B45: Rate of severe exacerbations, healthcare resource utilisation and clinical outcomes in patients with COPD in low-income and middle-income countries: results from the EXACOS International Study | C45: Athanazio, R.A.| Villada, L.B.| Avdeev, S.N.| Wang, H.-C.| Ramírez-Venegas, A.| Sivori, M.| Dreyse, J.| Pacheco, M.| Man, S.K.| Noriega-Aguirre, L.| Farouk, H. | D45: 2024 | E45: 45400 | F45: BMJ Open Respiratory Research | G45: 11 | H45: 1 | I45: - | J45: ISSN-20524439 | K45: BMJ Publishing Group | L45: English | M45: 5.7 | N45: 27.0 | O45: 1106 | P45: 10.1136/bmjresp-2023-002101 | Q45: Article | R45: 2-s2.0-85191103643 | S45: Sechenov First Moscow State Medical University| AstraZeneca| Universidad Tecnológica de Pereira| Universidad Finis Terrae| Universidade de São Paulo| Instituto Nacional de Enfermedades Respiratorias| Clínica Las Condes| Fundación Universitaria Autónoma de las Américas| National Taiwan University| Universidad de Buenos Aires| Tuen Mun Hospital | T45: 60008088| 60386097| 60010188| 60005429| 60025370| 60073385| 60008205| 60001563| 60017912| 60105368| 60077377| 60112679| 60000139| 131184358 | U45: Universidade de São Paulo| AstraZeneca Colombia S.A.S.| Sechenov First Moscow State Medical University| National Taiwan University| National Taiwan University College of Medicine| National Taiwan University Hospital| Instituto Nacional de Enfermedades Respiratorias| Universidad de Buenos Aires| Clínica Las Condes| Universidad Finis Terrae| Universidad Tecnológica de Pereira| Fundación Universitaria Autónoma de las Américas| Tuen Mun Hospital| Center for Diagnosis and Treatment of Respiratory Diseases (CEDITER) | V45: Taiwan| Chile| Mexico| Hong Kong| Colombia| Panama| Russian Federation| Brazil| Argentina
A46: Strauss F.J. | B46: Association of Peri-Implant Mucosa Dimensions With Emergence Profile Angles of the Implant Prosthesis | C46: Rungtanakiat, P.| Thitaphanich, N.| Janda, M.| Strauss, F.J.| Arksornnukit, M.| Mattheos, N. | D46: 2024 | E46: 45505 | F46: Clinical and Experimental Dental Research | G46: 10 | H46: 4 | I46: - | J46: ISSN-20574347 | K46: John Wiley and Sons Inc | L46: English | M46: 3.8 | N46: 33.0 | O46: 0.64 | P46: 10.1002/cre2.939 | Q46: Article | R46: 2-s2.0-85199151490 | S46: Chulalongkorn University| Karolinska Institutet| University of Zurich| Universidad Finis Terrae| Malmö University | T46: 60028190| 60063782| 60007905| 60012614| 60105368| 60012311 | U46: Chulalongkorn University| Malmo University Faculty of Odontology| Malmö Universitet| Universität Zürich| Universidad Finis Terrae| Karolinska Institutet | V46: Chile| Switzerland| Thailand| Sweden
A47: Hidalgo-Rosa Y. | B47: Exploring the adsorption of five emerging pollutants on activated carbon: A theoretical approach | C47: González-Rodríguez, L.| Yáñez, O.| Mena- Ulecia, K.| Hidalgo-Rosa, Y.| García- Carmona, X.| Ulloa- Tesser, C. | D47: 2024 | E47: 45444 | F47: Journal of Environmental Chemical Engineering | G47: 12 | H47: 3 | I47: - | J47: ISSN-22133437 | K47: Elsevier Ltd | L47: English | M47: 12.5 | N47: 5.0 | O47: 1454 | P47: 10.1016/j.jece.2024.112911 | Q47: Article | R47: 2-s2.0-85191660176 | S47: Universidad de las Américas - Chile| Universidad Finis Terrae| Universidad Católica de Temuco| Pontificia Universidad Católica de Chile| Universidad de Concepción | T47: 60105362| 60025749| 60029681| 60105368| 60001282 | U47: Universidad de Las Américas Chile| Universidad Católica de Temuco| Pontificia Universidad Católica de Chile| Universidad Finis Terrae| Universidad de Concepcion | V47: Chile
A48: Hevia D. | B48: Role of innate immune cells in multiple sclerosis | C48: Prado, C.| Herrada, A.A.| Hevia, D.| Goiry, L.G.| Escobedo, N. | D48: 2025 | E48: 45658 | F48: Frontiers in Immunology | G48: 16 | H48: - | I48: - | J48: ISSN-16643224 | K48: Frontiers Media SA | L48: English | M48: 11.3 | N48: 14.0 | O48: 1964 | P48: 10.3389/fimmu.2025.1540263 | Q48: Short Survey | R48: 2-s2.0-85219409688 | S48: Universidad Autónoma de Chile| Universidad San Sebastián| Universidad Finis Terrae| Clínica Alemana de Santiago | T48: 60012442| 60000636| 60105371| 60105368| 60000146| 60105896 | U48: Fundación Ciencia & Vida| Universidad San Sebastián| Universidad Autónoma de Chile| Universidad Finis Terrae| Clinica Alemana| Clínica Dávila | V48: Chile
A49: Mujika I. | B49: The Influence of High-Intensity Work on the Record Power Profile of Under-23, Pro Team, and World Tour Cyclists | C49: Leo, P.| Mateo-March, M.| Giorgi, A.| Muriel, X.| Javaloyes, A.| Barranco-Gil, D.| Pallarés, J.G.| Lucia, A.| Mujika, I.| Valenzuela, P.L. | D49: 2024 | E49: 45444 | F49: International Journal of Sports Physiology and Performance | G49: 19 | H49: 6 | I49: 545-549 | J49: ISSN-15550265 | K49: Human Kinetics Publishers Inc. | L49: English | M49: 6.6 | N49: 10.0 | O49: 1.61 | P49: 10.1123/ijspp.2023-0451 | Q49: Article | R49: 2-s2.0-85193712105 | S49: Miguel Hernández University| University of Alcalá| Adelaide University| University of Innsbruck| Universidad Finis Terrae| Universidad Europea de Madrid| Hospital Universitario 12 de Octubre| University of the Basque Country| University of Murcia| Universidad Europea | T49: 60009999| 60031846| 60028356| 60029767| 128383384| 121067127| 60000130| 60004024| 60027856| 60105368| 60027800 | U49: Universität Innsbruck| University of South Australia| Universidad Europea de Madrid| Universidad Miguel Hernández de Elche| Androni Giocattoli-Sidermec Professional Cycling Team| Azienda USL Toscana Sud Est| Universidad de Murcia| Hospital Universitario 12 de Octubre| Universidad del Pais Vasco| Universidad Finis Terrae| Universidad de Alcalá | V49: Chile| Austria| Spain| Australia| Italy
A50: Rojas-Costa G.M. | B50: Neurocognitive correlates of semantic memory navigation in Parkinson’s disease | C50: Toro-Hernández, F.D.| Migeot, J.| Marchant, N.| Olivares, D.| Ferrante, F.| González-Gómez, R.| González Campo, C.| Fittipaldi, S.| Rojas-Costa, G.M.| Moguilner, S.| Slachevsky, A.| Chaná Cuevas, P.| Ibáñez, A.| Chaigneau, S.| García, A.M. | D50: 2024 | E50: 45627 | F50: npj Parkinson's Disease | G50: 10 | H50: 1 | I50: - | J50: ISSN-23738057 | K50: Nature Research | L50: English | M50: 11.3 | N50: 6.0 | O50: 2914 | P50: 10.1038/s41531-024-00630-4 | Q50: Article | R50: 2-s2.0-85181891137 | S50: Universidad Mayor| Consejo Nacional de Investigaciones Científicas y Técnicas| Universidad de Santiago de Chile| University of California at San Francisco| Universidad de San Andrés| Universidad Adolfo Ibáñez| Universidad Finis Terrae| Clínica Las Condes| Clínica Alemana de Santiago| Universidad de Buenos Aires| Universidade Federal do ABC| Trinity College Dublin| Universidad del Desarrollo| Hospital del Salvador| Universidad de Chile | T50: 60001430| 60003942| 60012464| 60008314| 60004518| 60001563| 60023691| 60011149| 60017912| 130689163| 60105368| 60006634| 60002946| 60281340| 60006469| 60000146| 60023383 | U50: Universidade Federal do ABC| Universidad Adolfo Ibáñez| Universidad de Chile| Universidad de San Andres| Consejo Nacional de Investigaciones Científicas y Técnicas| Universidad de Buenos Aires| University of California, San Francisco| Trinity College Dublin| Clínica Las Condes| Join Unit FISABIO-CIPF| Universidad Finis Terrae| Hospital del Salvador| Facultad de Medicina de la Universidad de Chile| Centro de Gerociencia, Salud Mental y Metabolismo| Universidad del Desarrollo| Clinica Alemana| Universidad de Santiago de Chile | V50: Chile| Spain| Ireland| Brazil| Argentina
A51: Trautmann D. | B51: Antitumor Effects of Resveratrol Opposing Mechanisms of Helicobacter pylori in Gastric Cancer | C51: Trautmann, D.| Suazo, F.| Torres, K.| Simón, L. | D51: 2024 | E51: 45474 | F51: Nutrients | G51: 16 | H51: 13 | I51: - | J51: ISSN-20726643 | K51: Multidisciplinary Digital Publishing Institute (MDPI) | L51: English | M51: 9.1 | N51: 12.0 | O51: 1473 | P51: 10.3390/nu16132141 | Q51: Review | R51: 2-s2.0-85198416544 | S51: Universidad Finis Terrae| Pontificia Universidad Católica de Chile | T51: 60105368| 60029681 | U51: Universidad Finis Terrae| Pontificia Universidad Católica de Chile | V51: Chile
A52: Suazo F. | B52: Antitumor Effects of Resveratrol Opposing Mechanisms of Helicobacter pylori in Gastric Cancer | C52: Trautmann, D.| Suazo, F.| Torres, K.| Simón, L. | D52: 2024 | E52: 45474 | F52: Nutrients | G52: 16 | H52: 13 | I52: - | J52: ISSN-20726643 | K52: Multidisciplinary Digital Publishing Institute (MDPI) | L52: English | M52: 9.1 | N52: 12.0 | O52: 1473 | P52: 10.3390/nu16132141 | Q52: Review | R52: 2-s2.0-85198416544 | S52: Universidad Finis Terrae| Pontificia Universidad Católica de Chile | T52: 60105368| 60029681 | U52: Universidad Finis Terrae| Pontificia Universidad Católica de Chile | V52: Chile
A53: Torres K. | B53: Antitumor Effects of Resveratrol Opposing Mechanisms of Helicobacter pylori in Gastric Cancer | C53: Trautmann, D.| Suazo, F.| Torres, K.| Simón, L. | D53: 2024 | E53: 45474 | F53: Nutrients | G53: 16 | H53: 13 | I53: - | J53: ISSN-20726643 | K53: Multidisciplinary Digital Publishing Institute (MDPI) | L53: English | M53: 9.1 | N53: 12.0 | O53: 1473 | P53: 10.3390/nu16132141 | Q53: Review | R53: 2-s2.0-85198416544 | S53: Universidad Finis Terrae| Pontificia Universidad Católica de Chile | T53: 60105368| 60029681 | U53: Universidad Finis Terrae| Pontificia Universidad Católica de Chile | V53: Chile
A54: Simón L. | B54: Antitumor Effects of Resveratrol Opposing Mechanisms of Helicobacter pylori in Gastric Cancer | C54: Trautmann, D.| Suazo, F.| Torres, K.| Simón, L. | D54: 2024 | E54: 45474 | F54: Nutrients | G54: 16 | H54: 13 | I54: - | J54: ISSN-20726643 | K54: Multidisciplinary Digital Publishing Institute (MDPI) | L54: English | M54: 9.1 | N54: 12.0 | O54: 1473 | P54: 10.3390/nu16132141 | Q54: Review | R54: 2-s2.0-85198416544 | S54: Universidad Finis Terrae| Pontificia Universidad Católica de Chile | T54: 60105368| 60029681 | U54: Universidad Finis Terrae| Pontificia Universidad Católica de Chile | V54: Chile
A55: Pizarro S. | B55: Placing engineering in the earthquake response and the survival chain | C55: Ceferino, L.| Merino, Y.| Pizarro, S.| Moya, L.| Ozturk, B. | D55: 2024 | E55: 45627 | F55: Nature Communications | G55: 15 | H55: 1 | I55: - | J55: ISSN-20411723 | K55: Nature Research | L55: English | M55: 23.4 | N55: 3.0 | O55: 4761 | P55: 10.1038/s41467-024-48624-3 | Q55: Article | R55: 2-s2.0-85193789492 | S55: University of California at Berkeley| Universidad Finis Terrae| Pontificia Universidad Católica del Perú| Pontificia Universidad Católica de Chile| New York University | T55: 60025038| 60021784| 60029681| 117063452| 60105368| 60071236 | U55: University of California, Berkeley| New York University| Pontificia Universidad Católica de Chile| Servicio de Atención Médica de Urgencia (SAMU)| Universidad Finis Terrae| Pontificia Universidad Catolica del Peru | V55: Chile| United States| Peru
A56: Salas-Guzmán N. | B56: Redefining academic trajectories: A comprehensive analysis of the factors and impacts of the gender gap in STEM higher education | C56: Beroíza-Valenzuela, F.| Salas-Guzmán, N. | D56: 2025 | E56: 45768 | F56: International Journal of Sustainability in Higher Education | G56: 26 | H56: 4 | I56: 928-947 | J56: ISSN-14676370 | K56: Emerald Publishing | L56: English | M56: 9.8 | N56: 5.0 | O56: 1014 | P56: 10.1108/IJSHE-02-2024-0129 | Q56: Article | R56: 2-s2.0-105003413370 | S56: Universidad Finis Terrae| Universidad Metropolitana de Ciencias de la Educación | T56: 60003126| 60105368 | U56: Universidad Metropolitana de Ciencias de la Educación| Universidad Finis Terrae | V56: Chile
A57: Strauss F.J. | B57: Alveolar ridge changes 1-year after early implant placement, with or without alveolar ridge preservation at single-implant sites in the aesthetic region: A secondary analysis of radiographic and profilometric outcomes from a randomized controlled trial | C57: Strauss, F.J.| Fukuba, S.| Naenni, N.| Jung, R.| Jonker, B.| Wolvius, E.| Pijpe, J. | D57: 2024 | E57: 45383 | F57: Clinical Implant Dentistry and Related Research | G57: 26 | H57: 2 | I57: 356-368 | J57: ISSN-15230899 | K57: John Wiley and Sons Inc | L57: English | M57: 6.4 | N57: 7.0 | O57: 1315 | P57: 10.1111/cid.13297 | Q57: Article | R57: 2-s2.0-85179989770 | S57: University of Zurich| Universidad Finis Terrae| Erasmus University Rotterdam| Universidad de Chile| Institute of Science Tokyo| Catharina Hospital | T57: 60012614| 60012464| 60105368| 60172570| 60283164| 60032114| 60031750 | U57: Universität Zürich| Universidad de Chile| Universidad Finis Terrae| Graduate School of Medical and Dental Sciences| Institute of Science Tokyo| Erasmus MC| Catharina Ziekenhuis | V57: Chile| Japan| Switzerland| Netherlands
B58: Cognitive, emotional, and social factors promoting psychosocial adaptation: a study of latent profiles in people living in socially vulnerable contexts | C58: Carriedo, N.| Rodríguez-Villagra, O.A.| Moguilner, S.| Morales-Sepulveda, J.P.| Huepe-Artigas, D.| Soto, V.| Franco-O’Byrne, D.| Ibáñez, A.| Bekinschtein, T.A.| Huepe, D. | D58: 2024 | E58: 45292 | F58: Frontiers in Psychology | G58: 15 | H58: - | I58: - | J58: ISSN-16641078 | K58: Frontiers Media SA | L58: English | M58: 6.3 | N58: 17.0 | O58: 0.872 | P58: 10.3389/fpsyg.2024.1321242 | Q58: Article | R58: 2-s2.0-85191374190 | S58: Consejo Nacional de Investigaciones Científicas y Técnicas| The University of Sydney| Trinity College Dublin| University of Cambridge| Universidad de San Andrés| University of Costa Rica| Universidad Adolfo Ibáñez| Universidad Finis Terrae| National Distance Education University | T58: 60028711| 60071929| 60011149| 60008314| 60003942| 60212023| 60105368| 60004518| 60031101 | U58: Universidad Nacional de Educacion a Distancia| Universidad de Costa Rica| Trinity College Dublin| Universidad de San Andres| Universidad Adolfo Ibáñez| The University of Sydney Business School| Universidad Finis Terrae| Consejo Nacional de Investigaciones Científicas y Técnicas| University of Cambridge | V58: Chile| United Kingdom| Spain| Costa Rica| Ireland| Australia| Argentina
A59: Orellana-Donoso M. | B59: Comparison of the Mediterranean Diet and Other Therapeutic Strategies in Metabolic Syndrome: A Systematic Review and Meta-Analysis | C59: Bruna-Mejias, A.| San Martin, J.| Arciniegas-Diaz, D.| Meneses-Caroca, T.| Salamanca-Cerda, A.| Beas-Gambi, A.| Paola-Loaiza-Giraldo, J.| Ortiz-Ahumada, C.| Nova-Baeza, P.| Oyanedel-Amaro, G.| Orellana-Donoso, M.| Suazo-Santibáñez, A.| Sanchis-Gimeno, J.| Valenzuela-Fuenzalida, J.J. | D59: 2025 | E59: 45809 | F59: International Journal of Molecular Sciences | G59: 26 | H59: 12 | I59: - | J59: ISSN-16616596 | K59: Multidisciplinary Digital Publishing Institute (MDPI) | L59: English | M59: 10.0 | N59: 10.0 | O59: 1316 | P59: 10.3390/ijms26125887 | Q59: Review | R59: 2-s2.0-105009012247 | S59: Unidad Central Del Valle Del Cauca| Universidad de las Américas - Chile| Universidad Andrés Bello| Universidad Autónoma de Chile| Universidad San Sebastián| University of Valencia| Universidad Finis Terrae| Universidad de Playa Ancha de Ciencias de la Educación| Universidad Bernardo O'Higgins | T59: 60019586| 60002636| 60190577| 60105371| 60105368| 60000636| 60105362| 60002644| 60105370 | U59: Universidad de Playa Ancha| Universidad Andrés Bello| Unidad Central del Valle del Cauca| Universidad Autónoma de Chile| Universidad Finis Terrae| Universidad San Sebastián| Universidad de Las Américas Chile| Universitat de València| Universidad Bernardo O'Higgins | V59: Chile| Spain| Colombia
A60: Diaz F. | B60: Prevalence of Bacterial Codetection and Outcomes for Infants Intubated for Respiratory Infections* | C60: Karsies, T.| Shein, S.L.| Diaz, F.| Vasquez-Hoyos, P.| Alexander, R.| Pon, S.| González-Dambrauskas, S.| Yock-Corrales, A.| Rotta, A.| Prout, A.| Wen, A.| Camporesi, A.| Vargas, A.F.| Coates, B.| Piñeres-Olave, B.E.| Stulce, C.| Watson, C.| Francoeur, C.| Cantillano, E.M.| Zemanete, E.| Castro, F.| Yague, G.P.| Ozdemir, G.| Chandnani, H.| Harwayne-Gidansky, I.| Cinquegrani, K.| Izquierdo, L.| Polikoff, L.| Valero, L.| Gaspers, M.| Maamari, M.| Kangin, M.| Rodriguez, N.C.| Ozturk, N.| Castellani, P.| Khandhar, P.| Jabornisky, R.| Arana, R.| Pardo, R.| Palomino, R.L.| Nofziger, R.| Torales, S.A.| Ambati, S.| Gertz, S.| Jeyapalan, S.| Murthy, S.| Muisyo, T.| Lillitwat, W.| Lopez-Alarcon, Y. | D60: 2024 | E60: 45474 | F60: Pediatric Critical Care Medicine | G60: 25 | H60: 7 | I60: 609-620 | J60: ISSN-15297535 | K60: Lippincott Williams and Wilkins | L60: English | M60: 7.2 | N60: 6.0 | O60: 1028 | P60: 10.1097/PCC.0000000000003500 | Q60: Article | R60: 2-s2.0-85197570653 | S60: Hospital Militar Central| Children's Memorial Hospital| University of Miami| Universidad Finis Terrae| Hospital Pablo Tobon Uribe| Women and Children's Hospital of Buffalo| Caja Costarricense de Seguro Social| Ospedale dei Bambini Vittore Buzzi | Banner Health| Augusta University| Provincial Health Services Authority| Loma Linda University Health| Stony Brook University| Hospital Nacional Cayetano Heredia| Lucille Packard Children's Hospital| Stanford University| The University of Chicago| Saint Barnabas Medical Center| Cornell University| Ministerio de Salud del Perú| University of Texas Southwestern Medical Center| Lifespan| Nationwide Children’s Hospital| Hasbro Children's Hospital| Hospital San José| Fundación Valle del Lili| Universidad de la República| Akron Children's Hospital | Texas Tech University| Hospital General Universitario Gregorio Marañon| Marmara University| Dokuz Eylul University| Albany Medical College| Duke University| Case Western Reserve University| University of Oklahoma | T60: 60080012| 60031833| 123764794| 60281394| 60105368| 60110407| 60007997| 60071613| 60071612| 60071617| 60071915| 60122469| 60016631| 60032063| 60083540| 125429552| 60017031| 60058437| 60020643| 60105348| 60024399| 60079127| 126950835| 117723547| 60006484| 60033237| 60014930| 60028659| 60122662| 60281830| 60087081| 60032446| 100905006| 60003259| 60026695| 131546688| 127604237| 60027981| 60022460| 112583111| 100560611| 60071230| 101517523| 60109272| 60027342| 60092302| 60021390| 60009665| 60029251| 60008667| 60029833| 60021285| 60087080 | U60: Nationwide Children’s Hospital| University Hospitals Rainbow Babies & Children's Hospital| Red Colaborativa Pediátrica de Latinoamérica (LARed Network)| Hospital El Carmen Dr. Luis Valentín Ferrada| Universidad Finis Terrae| Hospital De San José, Bogotá, Colombia| Weill Cornell Medicine| Universidad de la Republica Facultad de Medicina| Universidad de la Republica| Centro Hospitalario Pereira Rossell| Hospital Nacional de Niños Dr. Carlos Sáenz Herrera| Duke Children’s Hospital & Health Center| Women and Children's Hospital of Buffalo| Lucile Packard Children's Hospital Stanford| Ospedale dei Bambini Vittore Buzzi| Fundación Clínica Infantil Club Noel| Children's Memorial Hospital| Hospital Pablo Tobon Uribe| Comer Children's Hospital - Hyde Park| Augusta University| Medical College of Georgia| CHU de Québec-Université Laval| Hospital del Norte| Hospital Susana López de Valencia| Hospital Padre Hurtado| Hospital General Universitario Gregorio Marañón| Dokuz Eylül Üniversitesi| Loma Linda University Children's Hospital| Stony Brook Children's Hospital| Hospital El Cruce| Hospital Militar Central, Bogota| Hasbro Children's Hospital| Hospital Universitario San Jorge| Banner - University Medical Center Phoenix| UT Southwestern Medical Center| Saglik Bilimleri University Gazi Yasargil Training and Research Hospital| Hospital San Juan de Dios| Marmara Üniversitesi| Hospital de Ninos Sor Maria Ludovica| Beaumont Children's Hospital| Hospital Juan Pablo II| Hospital Nacional Cayetano Heredia| Clínica Infantil Colsubsidio| Fundación Valle del Lili| Akron Children's Hospital| Hospital Materno Infantil de Salta| Albany Medical Center| Saint Barnabas Medical Center| University of Miami| BC​ Children​'​​s Hospital| University of Oklahoma Health Sciences Center| Texas Tech University| Hospital General de Medellin Luz Castro de Gutiérrez - E.S.E | V60: Canada| Chile| Uruguay| Spain| Costa Rica| United States| Colombia| Turkey| Italy| Bolivia| Peru| Argentina| Honduras
A61: Strauss F.J. | B61: Early implant placement versus ridge preservation and delayed implant placement: Analysis of profilometric, clinician- and patient-reported outcomes from a two-centre RCT | C61: Thoma, D.| Gil, A.| de Bruyckere, T.| Jung, R.E.| Fukuba, S.| Ickroth, A.| Strauss, F.J.| Cosyn, J. | D61: 2024 | E61: 45597 | F61: Clinical Oral Implants Research | G61: 35 | H61: 11 | I61: 1382-1393 | J61: ISSN-09057161 | K61: John Wiley and Sons Inc | L61: English | M61: 8.5 | N61: 1.0 | O61: 1839 | P61: 10.1111/clr.14325 | Q61: Article | R61: 2-s2.0-85197494682 | S61: University of Zurich| Universidad Finis Terrae| Ghent University| Institute of Science Tokyo | T61: 60012614| 60033316| 60283164| 60172570| 60105368 | U61: Universität Zürich| Universiteit Gent| Institute of Science Tokyo| Graduate School of Medical and Dental Sciences| Universidad Finis Terrae | V61: Belgium| Chile| Japan| Switzerland
A62: Catalán C. | B62: Pharmacogenomics in Solid Tumors: A Comprehensive Review of Genetic Variability and Its Clinical Implications | C62: Sánchez-Bayona, R.| Catalán, C.| Cobos, M.A.| Bergamino, M. | D62: 2025 | E62: 45717 | F62: Cancers | G62: 17 | H62: 6 | I62: - | J62: ISSN-20726694 | K62: Multidisciplinary Digital Publishing Institute (MDPI) | L62: English | M62: 9.0 | N62: 16.0 | O62: 1.41 | P62: 10.3390/cancers17060913 | Q62: Review | R62: 2-s2.0-105001299109 | S62: Universidad Finis Terrae | T62: 100310930| 60105368| 60030315 | U62: Hospital Universitario| Universidad Finis Terrae| Hospital Clínic de Barcelona | V62: Chile| Spain
B63: Severe menopausal symptoms linked to cognitive impairment: An exploratory study | C63: Calle, A.| Blümel, J.E.| Chedraui, P.| Vallejo, M.S.| Belardo, A.| Dextre, M.| Elizalde-Cremonte, A.| Escalante, C.| Espinoza, M.T.| Gómez-Tabares, G.| Monterrosa-Castro, Á.| Ñañez, M.| Ojeda, E.| Rey, C.| Rodríguez, D.| Rodrigues, M.A.| Salinas, C.| Tserotas, K.| Aedo, S. | D63: 2024 | E63: 45597 | F63: Menopause | G63: 31 | H63: 11 | I63: 959-965 | J63: ISSN-10723714 | K63: Wolters Kluwer Health | L63: English | M63: 5.6 | N63: 17.0 | O63: 1139 | P63: 10.1097/GME.0000000000002422 | Q63: Article | R63: 2-s2.0-85201395771 | S63: Universidad Nacional de Córdoba| Universidad Espíritu Santo, Ecuador| Universidad de Cartagena| Universidad Tecnológica Indoamérica| Universidade Federal de Minas Gerais| University of Costa Rica| Universidad Finis Terrae| Universidad Andina del Cusco| Hospital Italiano de Buenos Aires| Universidad de Chile| Universidad del Valle| Universidad de Buenos Aires| Universidad Nacional del Nordeste | T63: 60110777| 60012464| 60002946| 60104602| 60008557| 60120511| 60003542| 60019006| 60195990| 60071929| 126710413| 60066812| 60055678| 60000658| 60112686| 101550488| 60009065| 60001563| 60030074| 105888846| 125551913| 60105368 | U63: Universidad Tecnológica Indoamérica| Universidad de Chile| Facultad de Medicina de la Universidad de Chile| Universidad Espíritu Santo| Hospital Italiano de Buenos Aires| Clínica Javier Prado| Universidad Nacional del Nordeste| Fundacion Barcelo, Facultad de Medicina| Universidad de Costa Rica, Facultad de Medicina| Universidad de Costa Rica| Clínica Los Ángeles| Universidad del Valle, Cali| Universidad de Cartagena| Universidad Nacional de Córdoba| Universidad Andina del Cusco| Asociación Argentina para el Estudio del Climaterio| Hospital de Clínicas "José de San Martín"| Universidad de Buenos Aires| Universidade Federal de Minas Gerais| Hospital Ángeles| Clínica Tserotas| Universidad Finis Terrae | V63: Chile| Mexico| Ecuador| Costa Rica| Colombia| Panama| Bolivia| Peru| Brazil| Argentina
A64: Fernández-Verdejo R. | B64: Resting energy metabolism and sweet taste preference during the menstrual cycle in healthy women | C64: Malo-Vintimilla, L.| Aguirre, C.| Vergara, A.| Fernández-Verdejo, R.| Galgani, J.E. | D64: 2024 | E64: 45336 | F64: British Journal of Nutrition | G64: 131 | H64: 3 | I64: 384-390 | J64: ISSN-00071145 | K64: Cambridge University Press | L64: English | M64: 6.7 | N64: 17.0 | O64: 0.896 | P64: 10.1017/S0007114523001927 | Q64: Article | R64: 2-s2.0-85170255103 | S64: LSU Pennington Biomedical Research Center| Universidad Finis Terrae| Pontificia Universidad Católica de Chile | T64: 60009418| 60029681| 60105368| 60021235 | U64: Facultad de Medicina| Pontificia Universidad Católica de Chile| Universidad Finis Terrae| Pennington Biomedical Research Center | V64: Chile| United States
A65: Montalva-Valenzuela F. | B65: Effects of exercise, physical activity, and sports on physical fitness in adults with Down syndrome: A systematic review | C65: Montalva-Valenzuela, F.| Castillo-Paredes, A.| Farias-Valenzuela, C.| Andrades-Ramirez, O.| Concha-Cisternas, Y.| Guzmán-Muñoz, E. | D65: 2024 | E65: 45292 | F65: AIMS Public Health | G65: 11 | H65: 2 | I65: 577-600 | J65: ISSN-23278994 | K65: American Institute of Mathematical Sciences | L65: English | M65: 5.3 | N65: 25.0 | O65: 0.878 | P65: 10.3934/publichealth.2024029 | Q65: Review | R65: 2-s2.0-85192374380 | S65: Universidad de las Américas - Chile| Universidad Santo Tomás, Santiago| Universidad Andrés Bello| Universidad Autónoma de Chile| Universidad San Sebastián| Universidad Finis Terrae| Universidad Arturo Prat | T65: 60105368| 60105362| 60000636| 60002636| 60105371| 60010144| 60009128 | U65: Universidad Finis Terrae| Universidad de Las Américas Chile| Universidad San Sebastián| Universidad Andrés Bello| Universidad Autónoma de Chile| Universidad Arturo Prat| Universidad Santo Tomas, Santiago | V65: Chile
A66: Díaz F. | B66: Noninvasive Continuous Positive Airway Pressure Is a Lung- and Diaphragm-protective Approach in Self-inflicted Lung Injury | C66: Cruces, P.| Erranz, B.| Pérez, A.| Reveco, S.| González, C.| Retamal, J.| Poblete, D.| Hurtado, D.E.| Díaz, F. | D66: 2024 | E66: 45397 | F66: American Journal of Respiratory and Critical Care Medicine | G66: 209 | H66: 8 | I66: 1022-1025 | J66: ISSN-1073449X | K66: American Thoracic Society | L66: English | M66: 23.8 | N66: 2.0 | O66: 5076 | P66: 10.1164/rccm.202309-1629LE | Q66: Letter | R66: 2-s2.0-85190753267 | S66: Universidad Andrés Bello| Universidad Finis Terrae| Universidad de Chile| Pontificia Universidad Católica de Chile | T66: 60281764| 60002636| 60281394| 60029681| 60012464| 60105368 | U66: Facultad de Ciencias de la Vida| Universidad Andrés Bello| Hospital El Carmen Dr. Luis Valentín Ferrada| Pontificia Universidad Católica de Chile| Universidad de Chile| Universidad Finis Terrae | V66: Chile
A67: Orellana-Donoso M. | B67: Association between the Anatomical Location of Glioblastoma and Its Evaluation with Clinical Considerations: A Systematic Review and Meta-Analysis | C67: Valenzuela-Fuenzalida, J.J.| Moyano-Valarezo, L.| Silva-Bravo, V.| Milos-Brandenberg, D.| Orellana-Donoso, M.| Nova-Baeza, P.| Suazo-Santibáñez, A.| Rodríguez-Luengo, M.| Oyanedel-Amaro, G.| Sanchis-Gimeno, J.| Gutiérrez Espinoza, H. | D67: 2024 | E67: 45444 | F67: Journal of Clinical Medicine | G67: 13 | H67: 12 | I67: - | J67: ISSN-20770383 | K67: Multidisciplinary Digital Publishing Institute (MDPI) | L67: English | M67: 5.2 | N67: 14.0 | O67: 0.919 | P67: 10.3390/jcm13123460 | Q67: Review | R67: 2-s2.0-85197149301 | S67: Universidad de las Américas - Chile| Universidad de las Américas - Ecuador| Universidad Andrés Bello| Universidad Autónoma de Chile| Universidad San Sebastián| University of Valencia| Universidad Finis Terrae| Universidad Pedro de Valdivia| Universidad Bernardo O'Higgins | T67: 60105370| 60002636| 60086395| 60105368| 60000636| 60105362| 60105371| 60002644| 60104441 | U67: Universidad Bernardo O'Higgins| Universidad Andrés Bello| Universidad del Alba| Universidad Finis Terrae| Universidad San Sebastián| Universidad de Las Américas Chile| Universidad Autónoma de Chile| Universitat de València| Universidad de las Americas - Ecuador | V67: Chile| Spain| Ecuador
A68: Mujika I. | B68: Analysis of pacing and kinematics in 3000 m freestyle in elite level swimmers | C68: López-Belmonte, Ó.| Ruiz-Navarro, J.J.| Gay, A.| Cuenca-Fernández, F.| Mujika, I.| Arellano, R. | D68: 2025 | E68: 45658 | F68: Sports Biomechanics | G68: 24 | H68: 4 | I68: 921-937 | J68: ISSN-14763141 | K68: Routledge | L68: English | M68: 6.1 | N68: 13.0 | O68: 0.835 | P68: 10.1080/14763141.2023.2184418 | Q68: Article | R68: 2-s2.0-85149541629 | S68: Universidad Finis Terrae| University of Granada| University of the Basque Country | T68: 60027844| 60027856| 60105368 | U68: Universidad de Granada| Universidad del Pais Vasco| Universidad Finis Terrae | V68: Chile| Spain
A69: Simón L. | B69: Inhibition of glycolysis and Src/Akt signaling reduces Caveolin-1-enhanced metastasis | C69: Simón, L.| Torres, K.| Contreras, P.| Díaz-Valdivia, N.| Leyton, L.| Quest, A.F.G. | D69: 2024 | E69: 45474 | F69: Biomedicine and Pharmacotherapy | G69: 176 | H69: - | I69: - | J69: ISSN-07533322 | K69: Elsevier Masson s.r.l. | L69: English | M69: 12.8 | N69: 6.0 | O69: 1775 | P69: 10.1016/j.biopha.2024.116841 | Q69: Article | R69: 2-s2.0-85194821198 | S69: Universidad Finis Terrae| Universidad de Chile| Pontificia Universidad Católica de Chile | T69: 60105368| 60002946| 60012464| 60281366| 60029681 | U69: Universidad Finis Terrae| Facultad de Medicina de la Universidad de Chile| Universidad de Chile| Centro Avanzado de Enfermedades Crónicas| Pontificia Universidad Católica de Chile | V69: Chile
A70: Mansilla-Obando K. | B70: Eco-Innovation in the Food Industry: Exploring Consumer Motivations in an Emerging Market | C70: Mansilla-Obando, K.| Llanos, G.| Gómez-Sotta, E.| Buchuk, P.| Ortiz, F.| Aguirre, M.| Ahumada, F. | D70: 2024 | E70: 45292 | F70: Foods | G70: 13 | H70: 1 | I70: - | J70: ISSN-23048158 | K70: Multidisciplinary Digital Publishing Institute (MDPI) | L70: English | M70: 8.7 | N70: 1.0 | O70: 1021 | P70: 10.3390/foods13010004 | Q70: Article | R70: 2-s2.0-85181896730 | S70: University of Vechta| Universidad Finis Terrae | T70: 60105368| 60017703 | U70: Universidad Finis Terrae| Universität Vechta | V70: Chile| Germany
A71: Llanos G. | B71: Eco-Innovation in the Food Industry: Exploring Consumer Motivations in an Emerging Market | C71: Mansilla-Obando, K.| Llanos, G.| Gómez-Sotta, E.| Buchuk, P.| Ortiz, F.| Aguirre, M.| Ahumada, F. | D71: 2024 | E71: 45292 | F71: Foods | G71: 13 | H71: 1 | I71: - | J71: ISSN-23048158 | K71: Multidisciplinary Digital Publishing Institute (MDPI) | L71: English | M71: 8.7 | N71: 1.0 | O71: 1021 | P71: 10.3390/foods13010004 | Q71: Article | R71: 2-s2.0-85181896730 | S71: University of Vechta| Universidad Finis Terrae | T71: 60105368| 60017703 | U71: Universidad Finis Terrae| Universität Vechta | V71: Chile| Germany
A72: Gómez-Sotta E. | B72: Eco-Innovation in the Food Industry: Exploring Consumer Motivations in an Emerging Market | C72: Mansilla-Obando, K.| Llanos, G.| Gómez-Sotta, E.| Buchuk, P.| Ortiz, F.| Aguirre, M.| Ahumada, F. | D72: 2024 | E72: 45292 | F72: Foods | G72: 13 | H72: 1 | I72: - | J72: ISSN-23048158 | K72: Multidisciplinary Digital Publishing Institute (MDPI) | L72: English | M72: 8.7 | N72: 1.0 | O72: 1021 | P72: 10.3390/foods13010004 | Q72: Article | R72: 2-s2.0-85181896730 | S72: University of Vechta| Universidad Finis Terrae | T72: 60105368| 60017703 | U72: Universidad Finis Terrae| Universität Vechta | V72: Chile| Germany
A73: Buchuk P. | B73: Eco-Innovation in the Food Industry: Exploring Consumer Motivations in an Emerging Market | C73: Mansilla-Obando, K.| Llanos, G.| Gómez-Sotta, E.| Buchuk, P.| Ortiz, F.| Aguirre, M.| Ahumada, F. | D73: 2024 | E73: 45292 | F73: Foods | G73: 13 | H73: 1 | I73: - | J73: ISSN-23048158 | K73: Multidisciplinary Digital Publishing Institute (MDPI) | L73: English | M73: 8.7 | N73: 1.0 | O73: 1021 | P73: 10.3390/foods13010004 | Q73: Article | R73: 2-s2.0-85181896730 | S73: University of Vechta| Universidad Finis Terrae | T73: 60105368| 60017703 | U73: Universidad Finis Terrae| Universität Vechta | V73: Chile| Germany
A74: Ortiz F. | B74: Eco-Innovation in the Food Industry: Exploring Consumer Motivations in an Emerging Market | C74: Mansilla-Obando, K.| Llanos, G.| Gómez-Sotta, E.| Buchuk, P.| Ortiz, F.| Aguirre, M.| Ahumada, F. | D74: 2024 | E74: 45292 | F74: Foods | G74: 13 | H74: 1 | I74: - | J74: ISSN-23048158 | K74: Multidisciplinary Digital Publishing Institute (MDPI) | L74: English | M74: 8.7 | N74: 1.0 | O74: 1021 | P74: 10.3390/foods13010004 | Q74: Article | R74: 2-s2.0-85181896730 | S74: University of Vechta| Universidad Finis Terrae | T74: 60105368| 60017703 | U74: Universidad Finis Terrae| Universität Vechta | V74: Chile| Germany
A75: Aguirre M. | B75: Eco-Innovation in the Food Industry: Exploring Consumer Motivations in an Emerging Market | C75: Mansilla-Obando, K.| Llanos, G.| Gómez-Sotta, E.| Buchuk, P.| Ortiz, F.| Aguirre, M.| Ahumada, F. | D75: 2024 | E75: 45292 | F75: Foods | G75: 13 | H75: 1 | I75: - | J75: ISSN-23048158 | K75: Multidisciplinary Digital Publishing Institute (MDPI) | L75: English | M75: 8.7 | N75: 1.0 | O75: 1021 | P75: 10.3390/foods13010004 | Q75: Article | R75: 2-s2.0-85181896730 | S75: University of Vechta| Universidad Finis Terrae | T75: 60105368| 60017703 | U75: Universidad Finis Terrae| Universität Vechta | V75: Chile| Germany
A76: Ahumada F. | B76: Eco-Innovation in the Food Industry: Exploring Consumer Motivations in an Emerging Market | C76: Mansilla-Obando, K.| Llanos, G.| Gómez-Sotta, E.| Buchuk, P.| Ortiz, F.| Aguirre, M.| Ahumada, F. | D76: 2024 | E76: 45292 | F76: Foods | G76: 13 | H76: 1 | I76: - | J76: ISSN-23048158 | K76: Multidisciplinary Digital Publishing Institute (MDPI) | L76: English | M76: 8.7 | N76: 1.0 | O76: 1021 | P76: 10.3390/foods13010004 | Q76: Article | R76: 2-s2.0-85181896730 | S76: University of Vechta| Universidad Finis Terrae | T76: 60105368| 60017703 | U76: Universidad Finis Terrae| Universität Vechta | V76: Chile| Germany
A77: Rojas-Costa G.M. | B77: Automated and Interpretable Detection of Hippocampal Sclerosis in Temporal Lobe Epilepsy: AID-HS | C77: Ripart, M.| DeKraker, J.| Eriksson, M.H.| Piper, R.J.| Gopinath, S.| Parasuram, H.| Mo, J.| Likeman, M.| Ciobotaru, G.| Sequeiros-Peggs, P.| Hamandi, K.| Xie, H.| Cohen, N.T.| Su, T.-Y.| Kochi, R.| Wang, I.| Rojas-Costa, G.M.| Gálvez, M.| Parodi, C.| Riva, A.| D'Arco, F.| Mankad, K.| Clark, C.A.| Carbó, A.V.| Toledano, R.| Taylor, P.| Napolitano, A.| Rossi-Espagnet, M.C.| Willard, A.| Sinclair, B.| Pepper, J.| Seri, S.| Devinsky, O.| Pardoe, H.R.| Winston, G.P.| Duncan, J.S.| Yasuda, C.L.| Scárdua-Silva, L.| Walger, L.| Rüber, T.| Khan, A.R.| Baldeweg, T.| Adler, S.| Wagstyl, K.| Zhang, K.| Bari, S.M.S.| Galea, J.| Illapani, V.S.P.| Gaillard, W.D.| Ibáñez, A.| Faure, E.| Campos, M.| Severino, M.| Tortora, D.| Nobile, G.| Consales, A.| Chari, A.| Tisdall, M.| Cross, J.H.| Simpson, C.M.| Wang, Y.| De Palma, L.| De Benedictis, A.| Vivash, L.| O'Brien, T.J.| De Tisdi, J.| Alvim, M.K.M.| Cendes, F. | D77: 2025 | E77: 45658 | F77: Annals of Neurology | G77: 97 | H77: 1 | I77: 62-75 | J77: ISSN-03645134 | K77: John Wiley and Sons Inc | L77: English | M77: 13.5 | N77: 3.0 | O77: 3247 | P77: 10.1002/ana.27089 | Q77: Article | R77: 2-s2.0-85209077922 | S77: Aston University| Queen's University Kingston| Birmingham Women's and Children's NHS Foundation Trust| Cleveland Clinic Foundation| Newcastle University| IRCCS Ospedale pediatrico Bambino Gesù - Roma| Great Ormond Street Hospital for Children NHS Foundation Trust| University College London| University of Genoa| Universidad Finis Terrae| Florey Institute of Neuroscience and Mental Health| University College London Hospitals NHS Foundation Trust| Cardiff & Vale University Health Board| Clínica Las Condes| University of Bonn| New York University| King's College London| McGill University| Western University| University Hospitals Bristol and Weston NHS Foundation Trust| Universidade Estadual de Campinas| Amrita Vishwa Vidyapeetham| Monash University| University of Toronto| Case Western Reserve University| IRCCS Istituto Giannina Gaslini - Genova| Capital Medical University | T77: 60012662| 60002494| 60030319| 60018207| 60007898| 60076781| 60073452| 60015756| 60056592| 60000020| 129009176| 60021160| 60280631| 60000305| 60017912| 60105368| 60016041| 60025153| 100375709| 60006222| 60017905| 60019578| 112663508| 60170285| 60014551| 60024541| 60021784| 60110201| 60019953| 60016005| 60020736| 60029570| 119743401| 60030465| 60031619| 60011520 | U77: UCL Great Ormond Street Institute of Child Health| Université McGill| The Hospital for Sick Children| Great Ormond Street Hospital for Children NHS Foundation Trust| Amrita Institute of Medical Sciences India| Amrita Vishwa Vidyapeetham| Beijing Tiantan Hospital, Capital Medical University| Bristol Royal Hospital for Children| Central Military Hospital, Bucharest| University Hospital of Wales| Children's National Hospital| Cleveland Clinic Foundation| Department of Biomedical Engineering| Case Western Reserve University| Clínica Las Condes| Universidad Finis Terrae| Istituto Giannina Gaslini| Università degli Studi di Genova| Ruber International Hospital| Newcastle University| IRCCS Ospedale Pediatrico Bambino Gesù| Monash University| Alfred Health| Birmingham Women’s and Children’s NHS Foundation Trust| Aston University| NYU Grossman School of Medicine| New York University| The Florey| UCL Queen Square Institute of Neurology| Queen’s University| National Hospital for Neurology and Neurosurgery| Universidade Estadual de Campinas| Brazilian Institute of Neuroscience and Neurotechnology| Universitätsklinikum Bonn| Schulich School of Medicine & Dentistry| King's College London | V77: Chile| India| United Kingdom| China| Spain| United States| Germany| Australia| Italy| Romania| Brazil| Canada
A78: Gálvez M. | B78: Automated and Interpretable Detection of Hippocampal Sclerosis in Temporal Lobe Epilepsy: AID-HS | C78: Ripart, M.| DeKraker, J.| Eriksson, M.H.| Piper, R.J.| Gopinath, S.| Parasuram, H.| Mo, J.| Likeman, M.| Ciobotaru, G.| Sequeiros-Peggs, P.| Hamandi, K.| Xie, H.| Cohen, N.T.| Su, T.-Y.| Kochi, R.| Wang, I.| Rojas-Costa, G.M.| Gálvez, M.| Parodi, C.| Riva, A.| D'Arco, F.| Mankad, K.| Clark, C.A.| Carbó, A.V.| Toledano, R.| Taylor, P.| Napolitano, A.| Rossi-Espagnet, M.C.| Willard, A.| Sinclair, B.| Pepper, J.| Seri, S.| Devinsky, O.| Pardoe, H.R.| Winston, G.P.| Duncan, J.S.| Yasuda, C.L.| Scárdua-Silva, L.| Walger, L.| Rüber, T.| Khan, A.R.| Baldeweg, T.| Adler, S.| Wagstyl, K.| Zhang, K.| Bari, S.M.S.| Galea, J.| Illapani, V.S.P.| Gaillard, W.D.| Ibáñez, A.| Faure, E.| Campos, M.| Severino, M.| Tortora, D.| Nobile, G.| Consales, A.| Chari, A.| Tisdall, M.| Cross, J.H.| Simpson, C.M.| Wang, Y.| De Palma, L.| De Benedictis, A.| Vivash, L.| O'Brien, T.J.| De Tisdi, J.| Alvim, M.K.M.| Cendes, F. | D78: 2025 | E78: 45658 | F78: Annals of Neurology | G78: 97 | H78: 1 | I78: 62-75 | J78: ISSN-03645134 | K78: John Wiley and Sons Inc | L78: English | M78: 13.5 | N78: 3.0 | O78: 3247 | P78: 10.1002/ana.27089 | Q78: Article | R78: 2-s2.0-85209077922 | S78: Aston University| Queen's University Kingston| Birmingham Women's and Children's NHS Foundation Trust| Cleveland Clinic Foundation| Newcastle University| IRCCS Ospedale pediatrico Bambino Gesù - Roma| Great Ormond Street Hospital for Children NHS Foundation Trust| University College London| University of Genoa| Universidad Finis Terrae| Florey Institute of Neuroscience and Mental Health| University College London Hospitals NHS Foundation Trust| Cardiff & Vale University Health Board| Clínica Las Condes| University of Bonn| New York University| King's College London| McGill University| Western University| University Hospitals Bristol and Weston NHS Foundation Trust| Universidade Estadual de Campinas| Amrita Vishwa Vidyapeetham| Monash University| University of Toronto| Case Western Reserve University| IRCCS Istituto Giannina Gaslini - Genova| Capital Medical University | T78: 60012662| 60002494| 60030319| 60018207| 60007898| 60076781| 60073452| 60015756| 60056592| 60000020| 129009176| 60021160| 60280631| 60000305| 60017912| 60105368| 60016041| 60025153| 100375709| 60006222| 60017905| 60019578| 112663508| 60170285| 60014551| 60024541| 60021784| 60110201| 60019953| 60016005| 60020736| 60029570| 119743401| 60030465| 60031619| 60011520 | U78: UCL Great Ormond Street Institute of Child Health| Université McGill| The Hospital for Sick Children| Great Ormond Street Hospital for Children NHS Foundation Trust| Amrita Institute of Medical Sciences India| Amrita Vishwa Vidyapeetham| Beijing Tiantan Hospital, Capital Medical University| Bristol Royal Hospital for Children| Central Military Hospital, Bucharest| University Hospital of Wales| Children's National Hospital| Cleveland Clinic Foundation| Department of Biomedical Engineering| Case Western Reserve University| Clínica Las Condes| Universidad Finis Terrae| Istituto Giannina Gaslini| Università degli Studi di Genova| Ruber International Hospital| Newcastle University| IRCCS Ospedale Pediatrico Bambino Gesù| Monash University| Alfred Health| Birmingham Women’s and Children’s NHS Foundation Trust| Aston University| NYU Grossman School of Medicine| New York University| The Florey| UCL Queen Square Institute of Neurology| Queen’s University| National Hospital for Neurology and Neurosurgery| Universidade Estadual de Campinas| Brazilian Institute of Neuroscience and Neurotechnology| Universitätsklinikum Bonn| Schulich School of Medicine & Dentistry| King's College London | V78: Chile| India| United Kingdom| China| Spain| United States| Germany| Australia| Italy| Romania| Brazil| Canada
A79: Dreyse J. | B79: Is the time below 90% of SpO2 during sleep (T90%) a metric of good health? A longitudinal analysis of two cohorts | C79: Henríquez-Beltrán, M.| Dreyse, J.| Jorquera, J.| Weissglas, B.| del Rio, J.| Cendoya, M.| Jorquera-Diaz, J.| Salas, C.| Fernandez-Bussy, I.| Labarca, G. | D79: 2024 | E79: 45352 | F79: Sleep and Breathing | G79: 28 | H79: 1 | I79: 281-289 | J79: ISSN-15209512 | K79: Springer Science and Business Media Deutschland GmbH | L79: English | M79: 4.7 | N79: 17.0 | O79: 0.731 | P79: 10.1007/s11325-023-02909-x | Q79: Article | R79: 2-s2.0-85169302917 | S79: Harvard University| Brigham and Women’s Hospital| Universidad Finis Terrae| Pontificia Universidad Católica Argentina Santa María de los Buenos Aires - UCA| Clínica Las Condes| Universidad Adventista de Chile| Universidad de Concepción | T79: 60105372| 60017912| 60105368| 60001282| 130066629| 60032487| 60002746| 60016782 | U79: Universidad Adventista de Chile| Clínica Las Condes| Universidad Finis Terrae| Universidad de Concepcion| Universidad Favarolo| Pontificia Universidad Catolica Argentina| Harvard Medical School| Brigham and Women's Hospital | V79: Chile| United States| Argentina
A80: Jorquera J. | B80: Is the time below 90% of SpO2 during sleep (T90%) a metric of good health? A longitudinal analysis of two cohorts | C80: Henríquez-Beltrán, M.| Dreyse, J.| Jorquera, J.| Weissglas, B.| del Rio, J.| Cendoya, M.| Jorquera-Diaz, J.| Salas, C.| Fernandez-Bussy, I.| Labarca, G. | D80: 2024 | E80: 45352 | F80: Sleep and Breathing | G80: 28 | H80: 1 | I80: 281-289 | J80: ISSN-15209512 | K80: Springer Science and Business Media Deutschland GmbH | L80: English | M80: 4.7 | N80: 17.0 | O80: 0.731 | P80: 10.1007/s11325-023-02909-x | Q80: Article | R80: 2-s2.0-85169302917 | S80: Harvard University| Brigham and Women’s Hospital| Universidad Finis Terrae| Pontificia Universidad Católica Argentina Santa María de los Buenos Aires - UCA| Clínica Las Condes| Universidad Adventista de Chile| Universidad de Concepción | T80: 60105372| 60017912| 60105368| 60001282| 130066629| 60032487| 60002746| 60016782 | U80: Universidad Adventista de Chile| Clínica Las Condes| Universidad Finis Terrae| Universidad de Concepcion| Universidad Favarolo| Pontificia Universidad Catolica Argentina| Harvard Medical School| Brigham and Women's Hospital | V80: Chile| United States| Argentina
A81: Salas C. | B81: Is the time below 90% of SpO2 during sleep (T90%) a metric of good health? A longitudinal analysis of two cohorts | C81: Henríquez-Beltrán, M.| Dreyse, J.| Jorquera, J.| Weissglas, B.| del Rio, J.| Cendoya, M.| Jorquera-Diaz, J.| Salas, C.| Fernandez-Bussy, I.| Labarca, G. | D81: 2024 | E81: 45352 | F81: Sleep and Breathing | G81: 28 | H81: 1 | I81: 281-289 | J81: ISSN-15209512 | K81: Springer Science and Business Media Deutschland GmbH | L81: English | M81: 4.7 | N81: 17.0 | O81: 0.731 | P81: 10.1007/s11325-023-02909-x | Q81: Article | R81: 2-s2.0-85169302917 | S81: Harvard University| Brigham and Women’s Hospital| Universidad Finis Terrae| Pontificia Universidad Católica Argentina Santa María de los Buenos Aires - UCA| Clínica Las Condes| Universidad Adventista de Chile| Universidad de Concepción | T81: 60105372| 60017912| 60105368| 60001282| 130066629| 60032487| 60002746| 60016782 | U81: Universidad Adventista de Chile| Clínica Las Condes| Universidad Finis Terrae| Universidad de Concepcion| Universidad Favarolo| Pontificia Universidad Catolica Argentina| Harvard Medical School| Brigham and Women's Hospital | V81: Chile| United States| Argentina
A82: Henríquez-Olguín C. | B82: Exploring NADPH oxidases 2 and 4 in cardiac and skeletal muscle adaptations – A cross-tissue comparison | C82: Meneses-Valdés, R.| Gallero, S.| Henríquez-Olguín, C.| Jensen, T.E. | D82: 2024 | E82: 45566 | F82: Free Radical Biology and Medicine | G82: 223 | H82: - | I82: 296-305 | J82: ISSN-08915849 | K82: Elsevier Inc. | L82: English | M82: 13.6 | N82: 7.0 | O82: 2065 | P82: 10.1016/j.freeradbiomed.2024.07.035 | Q82: Review | R82: 2-s2.0-85201146042 | S82: University of Copenhagen| Universidad Finis Terrae| Universidad de Chile | T82: 60030840| 60012464| 60281366| 60105368 | U82: Københavns Universitet| Universidad de Chile| Centro Avanzado de Enfermedades Crónicas| Universidad Finis Terrae | V82: Chile| Denmark
A83: Mujika I. | B83: Hematological and performance adaptations to altitude training (2,320 m) in elite middle-distance and distance swimmers | C83: Mujika, I.| Bourdillon, N.| Zelenkova, I.| Vergnoux, F.| Millet, G.P. | D83: 2024 | E83: 45292 | F83: Frontiers in Physiology | G83: 15 | H83: - | I83: - | J83: ISSN-1664042X | K83: Frontiers Media SA | L83: English | M83: 7.3 | N83: 22.0 | O83: 1023 | P83: 10.3389/fphys.2024.1474479 | Q83: Article | R83: 2-s2.0-85206076775 | S83: University of Lausanne| Universidad Finis Terrae| University of Zaragoza| University of the Basque Country | T83: 60027856| 60105368| 60000239| 60016809| 131775198 | U83: Universidad del Pais Vasco| Universidad Finis Terrae| Université de Lausanne (UNIL)| Universidad de Zaragoza| Cercle des Nageurs d’Antibes | V83: Chile| Spain| Switzerland| France
A84: Yanine F.F. | B84: A systematic review of recent developments in IoT-based demand side management for PV power generation | C84: Rao, C.K.| Sahoo, S.K.| Yanine, F.F. | D84: 2024 | E84: 45292 | F84: Energy Harvesting and Systems | G84: 11 | H84: 1 | I84: - | J84: ISSN-23298774 | K84: Walter de Gruyter GmbH | L84: English | M84: 3.8 | N84: 40.0 | O84: 0.358 | P84: 10.1515/ehs-2023-0124 | Q84: Review | R84: 2-s2.0-85200832851 | S84: Biju Patnaik University of Technology| Universidad Finis Terrae| Aditya Institute of Technology and Management | T84: 60077979| 60114758| 60114662| 60105368 | U84: Biju Patnaik University of Technology| BPUT, Parala Maharaja Engineering College| Aditya Institute of Technology and Management| Universidad Finis Terrae | V84: Chile| India
A85: Núñez-Lisboa M.N. | B85: The role of physical activity in mitigating age-related changes in the neuromuscular control of gait | C85: Núñez-Lisboa, M.N.| Dewolf, A.H. | D85: 2025 | E85: 45992 | F85: npj Aging | G85: 11 | H85: 1 | I85: - | J85: ISSN-27316068 | K85: Nature Research | L85: English | M85: 7.9 | N85: 10.0 | O85: 3126 | P85: 10.1038/s41514-025-00239-8 | Q85: Article | R85: 2-s2.0-105007725331 | S85: Université catholique de Louvain| Universidad Finis Terrae | T85: 60000874| 60105368 | U85: UCLouvain| Universidad Finis Terrae | V85: Belgium| Chile
A86: Díaz F. | B86: Factors associated with prolonged mechanical ventilation in children with pulmonary failure: Cohort study from the LARed Network registry | C86: Barajas-Romero, J.S.| Vásquez-Hoyos, P.| Pardo, R.| Jaramillo-Bustamante, J.C.| Grigolli, R.| Monteverde-Fernández, N.| Gonzalez-Dambrauskas, S.| Jabornisky, R.| Cruces, P.| Wegner, A.| Díaz, F.| Pietroboni, P. | D86: 2024 | E86: 45292 | F86: Medicina Intensiva | G86: 48 | H86: 1 | I86: 23-36 | J86: ISSN-02105691 | K86: Ediciones Doyma, S.L. | L86: English| Spanish | M86: 2.3 | N86: 45.0 | O86: 0.353 | P86: 10.1016/j.medin.2023.06.005 | Q86: Article | R86: 2-s2.0-85166301280 | S86: Universidad Andrés Bello| Universidad de la República| Universidad Nacional de Colombia| Universidad Finis Terrae| Hospital San José | T86: 130011114| 60055696| 60110407| 101517523| 60087080| 60341654| 127089474| 60071612| 60071617| 60071613| 100560611| 130011694| 60002636| 60281764| 60025321| 60281394| 60105368| 60105883 | U86: Red Colaborativa Pediátrica de Latinoamérica (LARed Network)| Universidad Nacional de Colombia| Hospital De San José, Bogotá, Colombia| Clínica Infantil Colsubsidio| Hospital General de Medellin Luz Castro de Gutiérrez - E.S.E| Sabará Hospital Infantil| Mutualista Médica Uruguaya (MUCAM)| Universidad de la Republica| Centro Hospitalario Pereira Rossell| Universidad de la Republica Facultad de Medicina| Hospital Juan Pablo II| Hospital Central Reconquista Olga Stucky De Rizzi| Universidad Andrés Bello| Facultad de Ciencias de la Vida| Hospital Dr. Sotero del Rio| Hospital El Carmen Dr. Luis Valentín Ferrada| Universidad Finis Terrae| Hospital Regional Dr. Leonardo Guzmán de Antofagasta | V86: Chile| Uruguay| Colombia| Brazil| Argentina
A87: Murray N.P. | B87: Managing a Burning Face: Clinical Manifestations and Therapeutic Approaches for Neurogenic Rosacea | C87: Aedo, G.| Chahuán, M.| Gatica, E.| Herrera, I.| Parada, L.F.| Seguel, A.| Murray, N.P.| Aedo, S.| Aragón-Caqueo, D. | D87: 2025 | E87: 45717 | F87: International Journal of Molecular Sciences | G87: 26 | H87: 5 | I87: - | J87: ISSN-16616596 | K87: Multidisciplinary Digital Publishing Institute (MDPI) | L87: English | M87: 10.0 | N87: 10.0 | O87: 1316 | P87: 10.3390/ijms26052366 | Q87: Review | R87: 2-s2.0-86000546568 | S87: Universidad de Santiago de Chile| Universidad Finis Terrae| Universidad de Tarapacá | T87: 60023383| 60105368| 60030782 | U87: Universidad de Santiago de Chile| Universidad Finis Terrae| Universidad de Tarapacá | V87: Chile
A88: Aedo S. | B88: Managing a Burning Face: Clinical Manifestations and Therapeutic Approaches for Neurogenic Rosacea | C88: Aedo, G.| Chahuán, M.| Gatica, E.| Herrera, I.| Parada, L.F.| Seguel, A.| Murray, N.P.| Aedo, S.| Aragón-Caqueo, D. | D88: 2025 | E88: 45717 | F88: International Journal of Molecular Sciences | G88: 26 | H88: 5 | I88: - | J88: ISSN-16616596 | K88: Multidisciplinary Digital Publishing Institute (MDPI) | L88: English | M88: 10.0 | N88: 10.0 | O88: 1316 | P88: 10.3390/ijms26052366 | Q88: Review | R88: 2-s2.0-86000546568 | S88: Universidad de Santiago de Chile| Universidad Finis Terrae| Universidad de Tarapacá | T88: 60023383| 60105368| 60030782 | U88: Universidad de Santiago de Chile| Universidad Finis Terrae| Universidad de Tarapacá | V88: Chile
A89: Puyol F. | B89: New Public Management and Internationalization in Latin American Top-Tier Universities: A Multiple Case Study | C89: Labraña, J.| Henríquez, A.| LaTorre, P.| Puyol, F.| Gómez, M.R.| López, N. | D89: 2024 | E89: 45536 | F89: Journal of Studies in International Education | G89: 28 | H89: 4 | I89: 568-587 | J89: ISSN-10283153 | K89: SAGE Publications Inc. | L89: English | M89: 7.3 | N89: 8.0 | O89: 1067 | P89: 10.1177/10283153231221652 | Q89: Article | R89: 2-s2.0-85180257668 | S89: Catholic University of the Sacred Heart| Universidad Finis Terrae| Universidad de Tarapacá| Universidad de Chile | T89: 60030782| 60024053| 60105368| 60012464 | U89: Universidad de Tarapacá| Università Cattolica del Sacro Cuore| Universidad Finis Terrae| Universidad de Chile | V89: Chile| Italy
A90: Yanine F.F. | B90: Intelligent power management system for optimizing load strategies in renewable generation | C90: Rao, C.K.| Sahoo, S.K.| Yanine, F.F. | D90: 2025 | E90: 45717 | F90: Electrical Engineering | G90: 107 | H90: 3 | I90: 3039-3061 | J90: ISSN-09487921 | K90: Springer Science and Business Media Deutschland GmbH | L90: English | M90: 4.7 | N90: 18.0 | O90: 0.534 | P90: 10.1007/s00202-024-02674-4 | Q90: Article | R90: 2-s2.0-105001585427 | S90: Biju Patnaik University of Technology| Universidad Finis Terrae| Aditya Institute of Technology and Management | T90: 60114758| 60077979| 60114662| 60105368 | U90: BPUT, Parala Maharaja Engineering College| Biju Patnaik University of Technology| Aditya Institute of Technology and Management| Universidad Finis Terrae | V90: Chile| India
A91: Guevara Ó.J. | B91: Strengthening secured creditors: Implications on debt financing and investment | C91: Guevara, Ó.J.| Riutort, J. | D91: 2024 | E91: 45323 | F91: Journal of Corporate Finance | G91: 84 | H91: - | I91: - | J91: ISSN-09291199 | K91: Elsevier B.V. | L91: English | M91: 14.2 | N91: 3.0 | O91: 3246 | P91: 10.1016/j.jcorpfin.2023.102537 | Q91: Article | R91: 2-s2.0-85183561640 | S91: Universidad Adolfo Ibáñez| Universidad Finis Terrae | T91: 60105368| 60003942 | U91: Universidad Finis Terrae| Universidad Adolfo Ibáñez | V91: Chile
A92: Muzard A. | B92: Guided web app intervention for reducing symptoms of depression in postpartum women: Results of a feasibility randomized controlled trial | C92: Franco, P.| Olhaberry, M.| Kelders, S.| Muzard, A.| Cuijpers, P. | D92: 2024 | E92: 45444 | F92: Internet Interventions | G92: 36 | H92: - | I92: - | J92: ISSN-22147829 | K92: Elsevier B.V. | L92: English | M92: 7.3 | N92: 24.0 | O92: 1336 | P92: 10.1016/j.invent.2024.100744 | Q92: Article | R92: 2-s2.0-85191358580 | S92: Babes-Bolyai University| Ministerio de Planificación, Chile| Universidad Finis Terrae| University of Twente| North West University| Pontificia Universidad Católica de Chile| Amsterdam UMC| Vrije Universiteit Amsterdam | T92: 60029681| 60281485| 60020599| 60029714| 60105368| 60008734| 60117142| 60024417 | U92: Pontificia Universidad Católica de Chile| Instituto Milenio para la Investigación en Depresión y Personalidad| Universiteit Twente| North-West University| Universidad Finis Terrae| Vrije Universiteit Amsterdam| Amsterdam Public Health| Universitatea Babeș-Bolyai | V92: Chile| South Africa| Netherlands| Romania
A93: Hartmann D. | B93: Sunproofing from within: A deep dive into oral photoprotection strategies in dermatology | C93: Hartmann, D.| Valenzuela, F. | D93: 2024 | E93: 45474 | F93: Photodermatology Photoimmunology and Photomedicine | G93: 40 | H93: 4 | I93: - | J93: ISSN-09054383 | K93: John Wiley and Sons Inc | L93: English | M93: 4.4 | N93: 26.0 | O93: 0.685 | P93: 10.1111/phpp.12985 | Q93: Review | R93: 2-s2.0-85195414523 | S93: Universidad de los Andes Chile| Universidad Finis Terrae| Universidad de Chile | T93: 60105368| 128923672| 60012464| 60011284 | U93: Universidad Finis Terrae| Probity Medical Research| Universidad de Chile| Universidad de los Andes, Chile | V93: Chile
A94: Orellana-Donoso M. | B94: Infraorbital canal variants and its clinical and surgical implications. A systematic review | C94: Orellana-Donoso, M.| Romero-Zucchino, D.| Fuentes-Abarca, A.| Aravena-Ríos, P.| Sanchis-Gimeno, J.| Konschake, M.| Nova-Baeza, P.| Valenzuela-Fuenzalida, J.J. | D94: 2024 | E94: 45474 | F94: Surgical and Radiologic Anatomy | G94: 46 | H94: 7 | I94: 1027-1046 | J94: ISSN-09301038 | K94: Springer-Verlag Italia s.r.l. | L94: English | M94: 2.7 | N94: 39.0 | O94: 0.472 | P94: 10.1007/s00276-024-03348-3 | Q94: Review | R94: 2-s2.0-85191716936 | S94: Innsbruck Medical University| Universidad de las Américas - Chile| Universidad Andrés Bello| University of Valencia| Universidad Finis Terrae| Universidad Bernardo O'Higgins | T94: 60105368| 60105362| 60105370| 60002644| 60008222| 60002636 | U94: Universidad Finis Terrae| Universidad de Las Américas Chile| Universidad Bernardo O'Higgins| Universitat de València| Medizinische Universitat Innsbruck| Universidad Andrés Bello | V94: Chile| Austria| Spain
A95: Romero-Zucchino D. | B95: Infraorbital canal variants and its clinical and surgical implications. A systematic review | C95: Orellana-Donoso, M.| Romero-Zucchino, D.| Fuentes-Abarca, A.| Aravena-Ríos, P.| Sanchis-Gimeno, J.| Konschake, M.| Nova-Baeza, P.| Valenzuela-Fuenzalida, J.J. | D95: 2024 | E95: 45474 | F95: Surgical and Radiologic Anatomy | G95: 46 | H95: 7 | I95: 1027-1046 | J95: ISSN-09301038 | K95: Springer-Verlag Italia s.r.l. | L95: English | M95: 2.7 | N95: 39.0 | O95: 0.472 | P95: 10.1007/s00276-024-03348-3 | Q95: Review | R95: 2-s2.0-85191716936 | S95: Innsbruck Medical University| Universidad de las Américas - Chile| Universidad Andrés Bello| University of Valencia| Universidad Finis Terrae| Universidad Bernardo O'Higgins | T95: 60105368| 60105362| 60105370| 60002644| 60008222| 60002636 | U95: Universidad Finis Terrae| Universidad de Las Américas Chile| Universidad Bernardo O'Higgins| Universitat de València| Medizinische Universitat Innsbruck| Universidad Andrés Bello | V95: Chile| Austria| Spain
A96: Fuentes-Abarca A. | B96: Infraorbital canal variants and its clinical and surgical implications. A systematic review | C96: Orellana-Donoso, M.| Romero-Zucchino, D.| Fuentes-Abarca, A.| Aravena-Ríos, P.| Sanchis-Gimeno, J.| Konschake, M.| Nova-Baeza, P.| Valenzuela-Fuenzalida, J.J. | D96: 2024 | E96: 45474 | F96: Surgical and Radiologic Anatomy | G96: 46 | H96: 7 | I96: 1027-1046 | J96: ISSN-09301038 | K96: Springer-Verlag Italia s.r.l. | L96: English | M96: 2.7 | N96: 39.0 | O96: 0.472 | P96: 10.1007/s00276-024-03348-3 | Q96: Review | R96: 2-s2.0-85191716936 | S96: Innsbruck Medical University| Universidad de las Américas - Chile| Universidad Andrés Bello| University of Valencia| Universidad Finis Terrae| Universidad Bernardo O'Higgins | T96: 60105368| 60105362| 60105370| 60002644| 60008222| 60002636 | U96: Universidad Finis Terrae| Universidad de Las Américas Chile| Universidad Bernardo O'Higgins| Universitat de València| Medizinische Universitat Innsbruck| Universidad Andrés Bello | V96: Chile| Austria| Spain
A97: Aravena-Ríos P. | B97: Infraorbital canal variants and its clinical and surgical implications. A systematic review | C97: Orellana-Donoso, M.| Romero-Zucchino, D.| Fuentes-Abarca, A.| Aravena-Ríos, P.| Sanchis-Gimeno, J.| Konschake, M.| Nova-Baeza, P.| Valenzuela-Fuenzalida, J.J. | D97: 2024 | E97: 45474 | F97: Surgical and Radiologic Anatomy | G97: 46 | H97: 7 | I97: 1027-1046 | J97: ISSN-09301038 | K97: Springer-Verlag Italia s.r.l. | L97: English | M97: 2.7 | N97: 39.0 | O97: 0.472 | P97: 10.1007/s00276-024-03348-3 | Q97: Review | R97: 2-s2.0-85191716936 | S97: Innsbruck Medical University| Universidad de las Américas - Chile| Universidad Andrés Bello| University of Valencia| Universidad Finis Terrae| Universidad Bernardo O'Higgins | T97: 60105368| 60105362| 60105370| 60002644| 60008222| 60002636 | U97: Universidad Finis Terrae| Universidad de Las Américas Chile| Universidad Bernardo O'Higgins| Universitat de València| Medizinische Universitat Innsbruck| Universidad Andrés Bello | V97: Chile| Austria| Spain
A98: Figueroa D. | B98: Caring leadership in early childhood education in Chile: tensions from a highly gendered context | C98: Guerra, P.| Poblete, X.| Rodriguez, M.| Figueroa, D. | D98: 2024 | E98: 45292 | F98: School Leadership and Management | G98: 44 | H98: 2 | I98: 102-119 | J98: ISSN-13632434 | K98: Routledge | L98: English | M98: 4.5 | N98: 13.0 | O98: 0.876 | P98: 10.1080/13632434.2024.2317787 | Q98: Article | R98: 2-s2.0-85186548748 | S98: Universidad de las Américas - Chile| Universidad Católica Silva Henríquez| Universidad Finis Terrae| Universidad Alberto Hurtado | T98: 60105381| 60088733| 60105362| 60105368 | U98: Universidad Católica Silva Henríquez| Universidad Alberto Hurtado| Universidad de Las Américas Chile| Universidad Finis Terrae | V98: Chile
A99: Mariotti-Celis M.S. | B99: 3G extruded snacks enriched with catechin for high antioxidant capacity | C99: Zambrano, Y.| Mariotti-Celis, M.S.| Bouchon, P. | D99: 2024 | E99: 45306 | F99: LWT | G99: 192 | H99: - | I99: - | J99: ISSN-00236438 | K99: Academic Press | L99: English | M99: 13.6 | N99: 4.0 | O99: 1.48 | P99: 10.1016/j.lwt.2023.115674 | Q99: Article | R99: 2-s2.0-85182507728 | S99: Universidad Finis Terrae| Pontificia Universidad Católica de Chile | T99: 60029681| 60105368 | U99: Pontificia Universidad Católica de Chile| Universidad Finis Terrae | V99: Chile
A100: Mariotti-Celis M.S. | B100: Comparative Analysis of Sustainable Extraction Methods and Green Solvents for Olive Leaf Extracts with Antioxidant and Antihyperglycemic Activities | C100: Huamán-Castilla, N.L.| Mamani Apaza, L.O.| Zirena Vilca, F.| Saldaña, E.| Diaz-Valencia, Y.K.| Mariotti-Celis, M.S. | D100: 2024 | E100: 45627 | F100: Antioxidants | G100: 13 | H100: 12 | I100: - | J100: ISSN-20763921 | K100: Multidisciplinary Digital Publishing Institute (MDPI) | L100: English | M100: 12.4 | N100: 6.0 | O100: 1484 | P100: 10.3390/antiox13121523 | Q100: Article | R100: 2-s2.0-85213252656 | S100: Universidad Nacional de Moquegua| Universidad Finis Terrae| Universidad Nacional San Agustín de Arequipa | T100: 60122402| 60089535| 60105368 | U100: Universidad Nacional de Moquegua| Universidad Nacional de San Agustin de Arequipa| Universidad Finis Terrae | V100: Chile| Peru
...

Sheet Publicaciones_UFT_detalle
A1: Autores finis terrae afiliados | B1: Título | C1: Authors | D1: Year | E1: Full date | F1: Scopus Source title | G1: Volume | H1: Issue | I1: Pages | J1: ISSN | K1: Publisher | L1: Language | M1: CiteScore (publication year) | N1: CiteScore percentile (publication year) * | O1: SJR (publication year) | P1: DOI | Q1: Publication type | R1: EID | S1: Institutions | T1: Scopus Affiliation IDs | U1: Scopus Affiliation names | V1: Country/Region
A2: Mujika I. | B2: Using artificial intelligence for exercise prescription in personalised health promotion: A critical evaluation of OpenAI’s GPT-4 model | C2: Dergaa, I.| Saad, H.B.| El Omri, A.| Glenn, J.M.| Clark, C.C.T.| Washif, J.A.| Guelmami, N.| Hammouda, O.| Al-Horani, R.A.| Reynoso-Sánchez, L.F.| Romdhani, M.| Paineiras-Domingos, L.L.| Vancini, R.L.| Taheri, M.| Mataruna-Dos-Santos, L.J.| Trabelsi, K.| Chtourou, H.| Zghibi, M.| Eken, Ö.| Swed, S.| Aissa, M.B.| Shawki, H.H.| El-Seedi, H.R.| Mujika, I.| Seiler, S.| Zmijewski, P.| Pyne, D.B.| Knechtle, B.| Asif, I.M.| Drezner, J.A.| Sandbakk, Ø.| Chamari, K. | D2: 2024 | E2: 45292 | F2: Biology of Sport | G2: 42 | H2: 2 | I2: 221-241 | J2: ISSN-0860021X | K2: Institute of Sport | L2: English | M2: 9.4 | N2: 3.0 | O2: 1645 | P2: 10.5114/biolsport.2024.133661 | Q2: Article | R2: 2-s2.0-85188146191 | S2: Hamad Medical Corporation| Jiangsu University| University of Canberra| University of Aleppo| University of Zurich| Universidad Finis Terrae| University of Genoa| Jozef Pilsudski University of Physical Education in Warsaw| University of Alabama at Birmingham| University of Manouba| Islamic University of Madinah| University of Agder| Birmingham City University| University of Sousse| Canadian University Dubai| Nagoya City University| University of Tehran| Université Paris Nanterre| Yarmouk University| Norwegian University of Science and Technology| Coventry University| Universidade Federal da Bahia| Inonu University| University of the Basque Country| University of Jendouba| University of Sfax| Universidade Federal do Espírito Santo| University of Washington | T2: 60264454| 60064746| 60091664| 60279855| 60044627| 60058071| 60060593| 60072743| 60330445| 60100434| 60017326| 60090678| 60025153| 60017338| 60206635| 60042547| 60044065| 122712524| 60013710| 60028426| 60022927| 60105484| 60015585| 60072763| 60072762| 60004321| 60105081| 60017482| 60027856| 60105368| 60080184| 60010960| 60022193| 60012614| 60027086| 60119065| 60028548| 60015481| 60013141| 60070316| 60274653 | U2: Primary Health Care Corporation| University of Sfax| Institut Supérieur du Sport et de l'Education Physique de Sfax| Institut Supérieur de Sport et de l´Education Physique du Kef| Hopital Farhat Hached Sousse| Université de Sousse| Faculty of Medicine sousse| Hamad Medical Corporation| Neurotrack Technologies, Inc.| Birmingham City University| Coventry University| Institut Sukan Negara Malaysia| Università degli Studi di Genova| Université Paris Nanterre| Laboratoire Interdisciplinaire en Neurosciences, Physiologie et Psychologie : Activité Physique, Santé et Apprentissages - LINP2| Faculty of Medicine of Sfax| Yarmouk University| Autonomous University of Occident| Universidade Federal da Bahia| Universidade Federal do Espírito Santo| University of Tehran| Canadian University Dubai| Inönü Üniversitesi| Aleppo Faculty of Medicine| University of Aleppo| Nagoya City University Graduate School of Medical Sciences| Islamic University of Madinah| Jiangsu University| Universidad del Pais Vasco| Universidad Finis Terrae| Universitetet i Agder| Akademia Wychowania Fizycznego Józefa Piłsudskiego w Warszawie| University of Canberra| Universität Zürich| The University of Alabama at Birmingham| UAB Department of Family and Community Medicine| University of Washington School of Medicine| University of Washington| Norges Teknisk-Naturvitenskapelige Universitet| Université de la Manouba| Institut Supérieur du Sport et de l'Education Physique de Ksar-Saïd | V2: United Arab Emirates| Chile| United Kingdom| Mexico| Spain| Japan| Syrian Arab Republic| Italy| France| Brazil| Qatar| Norway| China| Tunisia| Poland| Jordan| United States| Saudi Arabia| Turkey| Switzerland| Australia| Malaysia| Iran
A3: Fernández-Verdejo R. | B3: Fibro-adipogenic progenitors in physiological adipogenesis and intermuscular adipose tissue remodeling | C3: Flores-Opazo, M.| Kopinke, D.| Helmbacher, F.| Fernández-Verdejo, R.| Tuñón-Suárez, M.| Lynch, G.S.| Contreras, O. | D3: 2024 | E3: 45444 | F3: Molecular Aspects of Medicine | G3: 97 | H3: - | I3: - | J3: ISSN-00982997 | K3: Elsevier Ltd | L3: English | M3: 18.2 | N3: 1.0 | O3: 2947 | P3: 10.1016/j.mam.2024.101277 | Q3: Review | R3: 2-s2.0-85193826870 | S3: Louisiana State University| Universidad de O'Higgins| University of Florida| LSU Pennington Biomedical Research Center| Aix-Marseille Université| CNRS| University of Melbourne| Universidad Finis Terrae| University of New South Wales| Victor Chang Cardiac Research Institute | T3: 60157974| 60013959| 60007567| 60034123| 60102127| 60008134| 60021235| 60007566| 60105368| 60343000| 60343038| 60026553| 60028061| 60028333 | U3: Universidad de O’Higgins| University of Florida| University of Florida College of Medicine| Institut de Biologie du Développement de Marseille| Aix Marseille Université| CNRS Centre National de la Recherche Scientifique| Pennington Biomedical Research Center| Louisiana State University| Universidad Finis Terrae| Department of Anatomy and Physiology| Centre for Muscle Research| University of Melbourne| Victor Chang Cardiac Research Institute| UNSW Sydney | V3: Chile| United States| Australia| France
A4: Tuñón-Suárez M. | B4: Fibro-adipogenic progenitors in physiological adipogenesis and intermuscular adipose tissue remodeling | C4: Flores-Opazo, M.| Kopinke, D.| Helmbacher, F.| Fernández-Verdejo, R.| Tuñón-Suárez, M.| Lynch, G.S.| Contreras, O. | D4: 2024 | E4: 45444 | F4: Molecular Aspects of Medicine | G4: 97 | H4: - | I4: - | J4: ISSN-00982997 | K4: Elsevier Ltd | L4: English | M4: 18.2 | N4: 1.0 | O4: 2947 | P4: 10.1016/j.mam.2024.101277 | Q4: Review | R4: 2-s2.0-85193826870 | S4: Louisiana State University| Universidad de O'Higgins| University of Florida| LSU Pennington Biomedical Research Center| Aix-Marseille Université| CNRS| University of Melbourne| Universidad Finis Terrae| University of New South Wales| Victor Chang Cardiac Research Institute | T4: 60157974| 60013959| 60007567| 60034123| 60102127| 60008134| 60021235| 60007566| 60105368| 60343000| 60343038| 60026553| 60028061| 60028333 | U4: Universidad de O’Higgins| University of Florida| University of Florida College of Medicine| Institut de Biologie du Développement de Marseille| Aix Marseille Université| CNRS Centre National de la Recherche Scientifique| Pennington Biomedical Research Center| Louisiana State University| Universidad Finis Terrae| Department of Anatomy and Physiology| Centre for Muscle Research| University of Melbourne| Victor Chang Cardiac Research Institute| UNSW Sydney | V4: Chile| United States| Australia| France
A5: Chavez-Reyes A. | B5: Therapeutic Antisense Oligonucleotides in Oncology: From Bench to Bedside | C5: Çakan, E.| Lara, O.D.| Szymanowska, A.| Bayraktar, E.| Chavez-Reyes, A.| Lopez-Berestein, G.| Amero, P.| Rodriguez-Aguayo, C. | D5: 2024 | E5: 45536 | F5: Cancers | G5: 16 | H5: 17 | I5: - | J5: ISSN-20726694 | K5: Multidisciplinary Digital Publishing Institute (MDPI) | L5: English | M5: 8.8 | N5: 17.0 | O5: 1462 | P5: 10.3390/cancers16172940 | Q5: Review | R5: 2-s2.0-85203665259 | S5: University of Texas MD Anderson Cancer Center| Hacettepe University| University of North Carolina at Chapel Hill| Gaziantep University| Universidad Finis Terrae | T5: 60015023| 60020484| 60025111| 60017595| 60105368 | U5: The University of Texas MD Anderson Cancer Center| Hacettepe Üniversitesi| The University of North Carolina at Chapel Hill| Gaziantep Üniversitesi| Universidad Finis Terrae | V5: Chile| United States| Turkey
A6: Mayo B. | B6: Curcumin Administration Routes in Breast Cancer Treatment | C6: Mayo, B.| Penroz, S.| Torres, K.| Simón, L. | D6: 2024 | E6: 45597 | F6: International Journal of Molecular Sciences | G6: 25 | H6: 21 | I6: - | J6: ISSN-16616596 | K6: Multidisciplinary Digital Publishing Institute (MDPI) | L6: English | M6: 9.0 | N6: 10.0 | O6: 1273 | P6: 10.3390/ijms252111492 | Q6: Review | R6: 2-s2.0-85208575143 | S6: Universidad Finis Terrae | T6: 601053680000000 | U6: Universidad Finis Terrae | V6: Chile
A7: Penroz S. | B7: Curcumin Administration Routes in Breast Cancer Treatment | C7: Mayo, B.| Penroz, S.| Torres, K.| Simón, L. | D7: 2024 | E7: 45597 | F7: International Journal of Molecular Sciences | G7: 25 | H7: 21 | I7: - | J7: ISSN-16616596 | K7: Multidisciplinary Digital Publishing Institute (MDPI) | L7: English | M7: 9.0 | N7: 10.0 | O7: 1273 | P7: 10.3390/ijms252111492 | Q7: Review | R7: 2-s2.0-85208575143 | S7: Universidad Finis Terrae | T7: 601053680000000 | U7: Universidad Finis Terrae | V7: Chile
A8: Torres K. | B8: Curcumin Administration Routes in Breast Cancer Treatment | C8: Mayo, B.| Penroz, S.| Torres, K.| Simón, L. | D8: 2024 | E8: 45597 | F8: International Journal of Molecular Sciences | G8: 25 | H8: 21 | I8: - | J8: ISSN-16616596 | K8: Multidisciplinary Digital Publishing Institute (MDPI) | L8: English | M8: 9.0 | N8: 10.0 | O8: 1273 | P8: 10.3390/ijms252111492 | Q8: Review | R8: 2-s2.0-85208575143 | S8: Universidad Finis Terrae | T8: 601053680000000 | U8: Universidad Finis Terrae | V8: Chile
A9: Simón L. | B9: Curcumin Administration Routes in Breast Cancer Treatment | C9: Mayo, B.| Penroz, S.| Torres, K.| Simón, L. | D9: 2024 | E9: 45597 | F9: International Journal of Molecular Sciences | G9: 25 | H9: 21 | I9: - | J9: ISSN-16616596 | K9: Multidisciplinary Digital Publishing Institute (MDPI) | L9: English | M9: 9.0 | N9: 10.0 | O9: 1273 | P9: 10.3390/ijms252111492 | Q9: Review | R9: 2-s2.0-85208575143 | S9: Universidad Finis Terrae | T9: 601053680000000 | U9: Universidad Finis Terrae | V9: Chile
A10: Fuentealba J.M. | B10: Management of alcohol use disorder: a gastroenterology and hepatology-focused perspective | C10: Díaz, L.A.| König, D.| Weber, S.| Ayares, G.| Fuentealba, J.M.| Vázquez, V.| Bataller, R.| Kamath, P.S.| Winder, G.S.| Leggio, L.| Arab, J.P. | D10: 2025 | E10: 45778 | F10: The Lancet Gastroenterology and Hepatology | G10: 10 | H10: 5 | I10: 475-490 | J10: ISSN-24681253 | K10: Elsevier Ltd | L10: English | M10: 64.3 | N10: 1.0 | O10: 13113 | P10: 10.1016/S2468-1253(24)00380-7 | Q10: Review | R10: 2-s2.0-86000364846 | S10: National Institutes of Health| Medical University of Vienna| Mayo Clinic Rochester, MN| Centro de Investigación Biomédica en Red| Virginia Commonwealth University| Universidad Finis Terrae| University of Michigan, Ann Arbor| University of California at San Diego| Instituto de Salud Carlos III| Pontificia Universidad Católica de Chile| August Pi i Sunyer Biomedical Research Institute| Instituto Tecnologico de Estudios Superiores de Monterrey | T10: 60029681| 60088718| 60030612| 60011394| 60105368| 60007966| 60001285| 60078879| 60010814| 60030315| 60005558| 60025778| 60033182| 60006577| 60020468| 60016730| 60010966 | U10: Pontificia Universidad Católica de Chile| Escuela de Medicina| University of California, San Diego| Medizinische Universität Wien| Universidad Finis Terrae| Tecnológico de Monterrey| Escuela de Medicina y Ciencias de la Salud TecSalud| Centro de Investigación Biomédica en Red de Enfermedades Hepáticas y Digestivas| Institut d'Investigacions Biomèdiques August Pi i Sunyer - IDIBAPS| Hospital Clínic de Barcelona| Mayo Clinic| University of Michigan, Ann Arbor| University of Michigan Medical School| National Institutes of Health (NIH)| National Institute on Drug Abuse (NIDA)| National Institute on Alcohol Abuse and Alcoholism (NIAAA)| VCU School of Medicine | V10: Chile| Austria| Mexico| Spain| United States
A11: Hidalgo-Rosa Y. | B11: UiO-66(Zr) as drug delivery system for non-steroidal anti-inflammatory drugs | C11: Salazar, J.| Hidalgo-Rosa, Y.| Burboa, P.C.| Wu, Y.-N.| Escalona, N.| Leiva, A.| Zarate, X.| Schott, E. | D11: 2024 | E11: 45444 | F11: Journal of Controlled Release | G11: 370 | H11: - | I11: 392-404 | J11: ISSN-01683659 | K11: Elsevier B.V. | L11: English | M11: 19.4 | N11: 2.0 | O11: 2.47 | P11: 10.1016/j.jconrel.2024.04.035 | Q11: Article | R11: 2-s2.0-85192014123 | S11: Universidad Autónoma de Chile| Ministerio de Planificación, Chile| Universidad Finis Terrae| Rutgers - The State University of New Jersey, New Brunswick| Pontificia Universidad Católica de Chile| Tongji University | T11: 60029681| 60005208| 60073652| 60105371| 60281487| 60105368 | U11: Pontificia Universidad Católica de Chile| Rutgers New Jersey Medical School| Tongji University| Universidad Autónoma de Chile| Núcleo Milenio en Procesos Catalíticos hacia la Química Sustentable| Universidad Finis Terrae | V11: Chile| China| United States
